Workbook
Name Slicer_Designation: #N/A
Name Slicer_Quarter_of_Joining_Date: #N/A
Name Slicer_Team: #N/A
Name Slicer_Team1: #N/A
Name Slicer_Type: #N/A
Name Slicer_Year_of_Joining_Date: #N/A

Sheet Resource
A1: Employee ID | B1: Corrected Employee ID | C1: Employee Name | D1: Employee First Working Day | E1: Corrected Employee First Working Day | F1: Designation | G1: Team | H1: Type | I1: Assigned Project 1 Code | J1: Assigned Project 2 Code | K1: Assigned Project 3 Code | L1: Year of Joining Date | M1: Quarter of Joining Date | N1: Quarter & Year of Joining Date
A2: EMP-001 | B2: ="emp"&TEXT(VALUE(SUBSTITUTE(SUBSTITUTE(UPPER(TRIM(A2)),"EMP",""),"-","")),"000") -> emp001 | C2: Rohit Sharma | D2: 44562 | E2: =IF(D2="","", IF(ISNUMBER(D2),D2, IFERROR(DATEVALUE(D2), IFERROR(DATEVALUE(SUBSTITUTE(SUBSTITUTE(SUBSTITUTE(LOWER(D2),"th",""),".","/"),"-","/")),"Check")))) -> 44562 | F2: Sr. Consultant | G2: Data | H2: FTE | I2: PRJ-020 | J2: PRJ-065 | L2: =IF(E2="","Missing",YEAR(E2)) -> 2022 | M2: =IF(E2="","Missing","Q"&ROUNDUP(MONTH(E2)/3,0)) -> Q1 | N2: =YEAR(E2)&"-Q"&ROUNDUP(MONTH(E2)/3,0) -> 2022-Q1
A3: emp002 | B3: ="emp"&TEXT(VALUE(SUBSTITUTE(SUBSTITUTE(UPPER(TRIM(A3)),"EMP",""),"-","")),"000") -> emp002 | C3: Anjali Verma | D3: 44242 | E3: =IF(D3="","", IF(ISNUMBER(D3),D3, IFERROR(DATEVALUE(D3), IFERROR(DATEVALUE(SUBSTITUTE(SUBSTITUTE(SUBSTITUTE(LOWER(D3),"th",""),".","/"),"-","/")),"Check")))) -> 44242 | F3: Manager | G3: Digital | H3: FTE | I3: PRJ-029 | J3: PRJ-070 | L3: =IF(E3="","Missing",YEAR(E3)) -> 2021 | M3: =IF(E3="","Missing","Q"&ROUNDUP(MONTH(E3)/3,0)) -> Q1 | N3: =YEAR(E3)&"-Q"&ROUNDUP(MONTH(E3)/3,0) -> 2021-Q1
A4: EMP 003 | B4: ="emp"&TEXT(VALUE(SUBSTITUTE(SUBSTITUTE(UPPER(TRIM(A4)),"EMP",""),"-","")),"000") -> emp003 | C4: Suresh Iyer | D4: 44022 | E4: =IF(D4="","", IF(ISNUMBER(D4),D4, IFERROR(DATEVALUE(D4), IFERROR(DATEVALUE(SUBSTITUTE(SUBSTITUTE(SUBSTITUTE(LOWER(D4),"th",""),".","/"),"-","/")),"Check")))) -> 44022 | F4: Lead Consultant | G4: AI | H4: FTE | I4: PRJ-007 | J4: PRJ-056 | L4: =IF(E4="","Missing",YEAR(E4)) -> 2020 | M4: =IF(E4="","Missing","Q"&ROUNDUP(MONTH(E4)/3,0)) -> Q3 | N4: =YEAR(E4)&"-Q"&ROUNDUP(MONTH(E4)/3,0) -> 2020-Q3
A5: EMP-004 | B5: ="emp"&TEXT(VALUE(SUBSTITUTE(SUBSTITUTE(UPPER(TRIM(A5)),"EMP",""),"-","")),"000") -> emp004 | C5: Megha Jain | D5: 03-15-2019 | E5: =IF(D5="","", IF(ISNUMBER(D5),D5, IFERROR(DATEVALUE(D5), IFERROR(DATEVALUE(SUBSTITUTE(SUBSTITUTE(SUBSTITUTE(LOWER(D5),"th",""),".","/"),"-","/")),"Check")))) -> 43539 | F5: Consultant | G5: Digital | H5: FTE | I5: PRJ-040 | J5: PRJ-053 | L5: =IF(E5="","Missing",YEAR(E5)) -> 2019 | M5: =IF(E5="","Missing","Q"&ROUNDUP(MONTH(E5)/3,0)) -> Q1 | N5: =YEAR(E5)&"-Q"&ROUNDUP(MONTH(E5)/3,0) -> 2019-Q1
A6: EMP005 | B6: ="emp"&TEXT(VALUE(SUBSTITUTE(SUBSTITUTE(UPPER(TRIM(A6)),"EMP",""),"-","")),"000") -> emp005 | C6: Neha Malhotra | D6: 45017 | E6: =IF(D6="","", IF(ISNUMBER(D6),D6, IFERROR(DATEVALUE(D6), IFERROR(DATEVALUE(SUBSTITUTE(SUBSTITUTE(SUBSTITUTE(LOWER(D6),"th",""),".","/"),"-","/")),"Check")))) -> 45017 | F6: Senior Consultant | G6: Data | H6: FTE | I6: PRJ-012 | J6: PRJ-067 | K6: PRJ-085 | L6: =IF(E6="","Missing",YEAR(E6)) -> 2023 | M6: =IF(E6="","Missing","Q"&ROUNDUP(MONTH(E6)/3,0)) -> Q2 | N6: =YEAR(E6)&"-Q"&ROUNDUP(MONTH(E6)/3,0) -> 2023-Q2
A7: EMP-006 | B7: ="emp"&TEXT(VALUE(SUBSTITUTE(SUBSTITUTE(UPPER(TRIM(A7)),"EMP",""),"-","")),"000") -> emp006 | C7: Rahul Mehta | D7: 43405 | E7: =IF(D7="","", IF(ISNUMBER(D7),D7, IFERROR(DATEVALUE(D7), IFERROR(DATEVALUE(SUBSTITUTE(SUBSTITUTE(SUBSTITUTE(LOWER(D7),"th",""),".","/"),"-","/")),"Check")))) -> 43405 | F7: Principal Consultant | G7: AI | H7: FTE | I7: PRJ-011 | J7: PRJ-065 | L7: =IF(E7="","Missing",YEAR(E7)) -> 2018 | M7: =IF(E7="","Missing","Q"&ROUNDUP(MONTH(E7)/3,0)) -> Q4 | N7: =YEAR(E7)&"-Q"&ROUNDUP(MONTH(E7)/3,0) -> 2018-Q4
A8: emp-007 | B8: ="emp"&TEXT(VALUE(SUBSTITUTE(SUBSTITUTE(UPPER(TRIM(A8)),"EMP",""),"-","")),"000") -> emp007 | C8: Priya Nair | D8: 42898 | E8: =IF(D8="","", IF(ISNUMBER(D8),D8, IFERROR(DATEVALUE(D8), IFERROR(DATEVALUE(SUBSTITUTE(SUBSTITUTE(SUBSTITUTE(LOWER(D8),"th",""),".","/"),"-","/")),"Check")))) -> 42898 | F8: Consultant | G8: Digital | H8: FTE | I8: PRJ-023 | L8: =IF(E8="","Missing",YEAR(E8)) -> 2017 | M8: =IF(E8="","Missing","Q"&ROUNDUP(MONTH(E8)/3,0)) -> Q2 | N8: =YEAR(E8)&"-Q"&ROUNDUP(MONTH(E8)/3,0) -> 2017-Q2
A9: EMP008 | B9: ="emp"&TEXT(VALUE(SUBSTITUTE(SUBSTITUTE(UPPER(TRIM(A9)),"EMP",""),"-","")),"000") -> emp008 | C9: Vikram Singh | D9: 07.08.2020 | E9: =IF(D9="","", IF(ISNUMBER(D9),D9, IFERROR(DATEVALUE(D9), IFERROR(DATEVALUE(SUBSTITUTE(SUBSTITUTE(SUBSTITUTE(LOWER(D9),"th",""),".","/"),"-","/")),"Check")))) -> 44020 | F9: Consultant | G9: Data | H9: FTE | I9: PRJ-013 | J9: PRJ-051 | L9: =IF(E9="","Missing",YEAR(E9)) -> 2020 | M9: =IF(E9="","Missing","Q"&ROUNDUP(MONTH(E9)/3,0)) -> Q3 | N9: =YEAR(E9)&"-Q"&ROUNDUP(MONTH(E9)/3,0) -> 2020-Q3
A10: EMP-009 | B10: ="emp"&TEXT(VALUE(SUBSTITUTE(SUBSTITUTE(UPPER(TRIM(A10)),"EMP",""),"-","")),"000") -> emp009 | C10: Karan Ahuja | D10: 44571 | E10: =IF(D10="","", IF(ISNUMBER(D10),D10, IFERROR(DATEVALUE(D10), IFERROR(DATEVALUE(SUBSTITUTE(SUBSTITUTE(SUBSTITUTE(LOWER(D10),"th",""),".","/"),"-","/")),"Check")))) -> 44571 | F10: Analyst | G10: Data | H10: Intern | I10: PRJ-004 | L10: =IF(E10="","Missing",YEAR(E10)) -> 2022 | M10: =IF(E10="","Missing","Q"&ROUNDUP(MONTH(E10)/3,0)) -> Q1 | N10: =YEAR(E10)&"-Q"&ROUNDUP(MONTH(E10)/3,0) -> 2022-Q1
A11: EMP-010 | B11: ="emp"&TEXT(VALUE(SUBSTITUTE(SUBSTITUTE(UPPER(TRIM(A11)),"EMP",""),"-","")),"000") -> emp010 | C11: Pooja Kulkarni | D11: 45673 | E11: =IF(D11="","", IF(ISNUMBER(D11),D11, IFERROR(DATEVALUE(D11), IFERROR(DATEVALUE(SUBSTITUTE(SUBSTITUTE(SUBSTITUTE(LOWER(D11),"th",""),".","/"),"-","/")),"Check")))) -> 45673 | F11: Consultant | G11: AI | H11: Intern | I11: PRJ-030 | L11: =IF(E11="","Missing",YEAR(E11)) -> 2025 | M11: =IF(E11="","Missing","Q"&ROUNDUP(MONTH(E11)/3,0)) -> Q1 | N11: =YEAR(E11)&"-Q"&ROUNDUP(MONTH(E11)/3,0) -> 2025-Q1
A12: EMP011 | B12: ="emp"&TEXT(VALUE(SUBSTITUTE(SUBSTITUTE(UPPER(TRIM(A12)),"EMP",""),"-","")),"000") -> emp011 | C12: Aman Gupta | D12: 43713 | E12: =IF(D12="","", IF(ISNUMBER(D12),D12, IFERROR(DATEVALUE(D12), IFERROR(DATEVALUE(SUBSTITUTE(SUBSTITUTE(SUBSTITUTE(LOWER(D12),"th",""),".","/"),"-","/")),"Check")))) -> 43713 | F12: Consultant | G12: Digital | H12: FTE | I12: PRJ-045 | J12: PRJ-060 | L12: =IF(E12="","Missing",YEAR(E12)) -> 2019 | M12: =IF(E12="","Missing","Q"&ROUNDUP(MONTH(E12)/3,0)) -> Q3 | N12: =YEAR(E12)&"-Q"&ROUNDUP(MONTH(E12)/3,0) -> 2019-Q3
A13: EMP-012 | B13: ="emp"&TEXT(VALUE(SUBSTITUTE(SUBSTITUTE(UPPER(TRIM(A13)),"EMP",""),"-","")),"000") -> emp012 | C13: Sneha Rao | D13: 44260 | E13: =IF(D13="","", IF(ISNUMBER(D13),D13, IFERROR(DATEVALUE(D13), IFERROR(DATEVALUE(SUBSTITUTE(SUBSTITUTE(SUBSTITUTE(LOWER(D13),"th",""),".","/"),"-","/")),"Check")))) -> 44260 | F13: Analyst | G13: Data | H13: Intern | I13: PRJ-033 | L13: =IF(E13="","Missing",YEAR(E13)) -> 2021 | M13: =IF(E13="","Missing","Q"&ROUNDUP(MONTH(E13)/3,0)) -> Q1 | N13: =YEAR(E13)&"-Q"&ROUNDUP(MONTH(E13)/3,0) -> 2021-Q1
A14: emp013 | B14: ="emp"&TEXT(VALUE(SUBSTITUTE(SUBSTITUTE(UPPER(TRIM(A14)),"EMP",""),"-","")),"000") -> emp013 | C14: Rakesh Kumar | D14: 45301 | E14: =IF(D14="","", IF(ISNUMBER(D14),D14, IFERROR(DATEVALUE(D14), IFERROR(DATEVALUE(SUBSTITUTE(SUBSTITUTE(SUBSTITUTE(LOWER(D14),"th",""),".","/"),"-","/")),"Check")))) -> 45301 | F14: Sr. Consultant | G14: AI | H14: FTE | I14: PRJ-016 | J14: PRJ-060 | L14: =IF(E14="","Missing",YEAR(E14)) -> 2024 | M14: =IF(E14="","Missing","Q"&ROUNDUP(MONTH(E14)/3,0)) -> Q1 | N14: =YEAR(E14)&"-Q"&ROUNDUP(MONTH(E14)/3,0) -> 2024-Q1
A15: EMP 014 | B15: ="emp"&TEXT(VALUE(SUBSTITUTE(SUBSTITUTE(UPPER(TRIM(A15)),"EMP",""),"-","")),"000") -> emp014 | C15: Kavita Joshi | D15: 42780 | E15: =IF(D15="","", IF(ISNUMBER(D15),D15, IFERROR(DATEVALUE(D15), IFERROR(DATEVALUE(SUBSTITUTE(SUBSTITUTE(SUBSTITUTE(LOWER(D15),"th",""),".","/"),"-","/")),"Check")))) -> 42780 | F15: Consultant | G15: Digital | H15: FTE | I15: PRJ-005 | J15: PRJ-080 | L15: =IF(E15="","Missing",YEAR(E15)) -> 2017 | M15: =IF(E15="","Missing","Q"&ROUNDUP(MONTH(E15)/3,0)) -> Q1 | N15: =YEAR(E15)&"-Q"&ROUNDUP(MONTH(E15)/3,0) -> 2017-Q1
A16: EMP-015 | B16: ="emp"&TEXT(VALUE(SUBSTITUTE(SUBSTITUTE(UPPER(TRIM(A16)),"EMP",""),"-","")),"000") -> emp015 | C16: Nitin Arora | D16: 01.06.2020 | E16: =IF(D16="","", IF(ISNUMBER(D16),D16, IFERROR(DATEVALUE(D16), IFERROR(DATEVALUE(SUBSTITUTE(SUBSTITUTE(SUBSTITUTE(LOWER(D16),"th",""),".","/"),"-","/")),"Check")))) -> 43836 | F16: Lead Consultant | G16: Data | H16: FTE | I16: PRJ-004 | J16: PRJ-076 | K16: PRJ-078 | L16: =IF(E16="","Missing",YEAR(E16)) -> 2020 | M16: =IF(E16="","Missing","Q"&ROUNDUP(MONTH(E16)/3,0)) -> Q1 | N16: =YEAR(E16)&"-Q"&ROUNDUP(MONTH(E16)/3,0) -> 2020-Q1
A17: emp016 | B17: ="emp"&TEXT(VALUE(SUBSTITUTE(SUBSTITUTE(UPPER(TRIM(A17)),"EMP",""),"-","")),"000") -> emp016 | C17: Pankaj Mishra | D17: 42705 | E17: =IF(D17="","", IF(ISNUMBER(D17),D17, IFERROR(DATEVALUE(D17), IFERROR(DATEVALUE(SUBSTITUTE(SUBSTITUTE(SUBSTITUTE(LOWER(D17),"th",""),".","/"),"-","/")),"Check")))) -> 42705 | F17: Analyst | G17: AI | H17: FTE | I17: PRJ-016 | J17: PRJ-070 | L17: =IF(E17="","Missing",YEAR(E17)) -> 2016 | M17: =IF(E17="","Missing","Q"&ROUNDUP(MONTH(E17)/3,0)) -> Q4 | N17: =YEAR(E17)&"-Q"&ROUNDUP(MONTH(E17)/3,0) -> 2016-Q4
A18: EMP-017 | B18: ="emp"&TEXT(VALUE(SUBSTITUTE(SUBSTITUTE(UPPER(TRIM(A18)),"EMP",""),"-","")),"000") -> emp017 | C18: Swati Kulkarni | D18: 44423 | E18: =IF(D18="","", IF(ISNUMBER(D18),D18, IFERROR(DATEVALUE(D18), IFERROR(DATEVALUE(SUBSTITUTE(SUBSTITUTE(SUBSTITUTE(LOWER(D18),"th",""),".","/"),"-","/")),"Check")))) -> 44423 | F18: Consultant | G18: Digital | H18: FTE | I18: PRJ-001 | J18: PRJ-053 | L18: =IF(E18="","Missing",YEAR(E18)) -> 2021 | M18: =IF(E18="","Missing","Q"&ROUNDUP(MONTH(E18)/3,0)) -> Q3 | N18: =YEAR(E18)&"-Q"&ROUNDUP(MONTH(E18)/3,0) -> 2021-Q3
A19: EMP018 | B19: ="emp"&TEXT(VALUE(SUBSTITUTE(SUBSTITUTE(UPPER(TRIM(A19)),"EMP",""),"-","")),"000") -> emp018 | C19: Arjun Mehta | D19: 44621 | E19: =IF(D19="","", IF(ISNUMBER(D19),D19, IFERROR(DATEVALUE(D19), IFERROR(DATEVALUE(SUBSTITUTE(SUBSTITUTE(SUBSTITUTE(LOWER(D19),"th",""),".","/"),"-","/")),"Check")))) -> 44621 | F19: Analyst | G19: Data | H19: Intern | I19: PRJ-028 | L19: =IF(E19="","Missing",YEAR(E19)) -> 2022 | M19: =IF(E19="","Missing","Q"&ROUNDUP(MONTH(E19)/3,0)) -> Q1 | N19: =YEAR(E19)&"-Q"&ROUNDUP(MONTH(E19)/3,0) -> 2022-Q1
A20: EMP-019 | B20: ="emp"&TEXT(VALUE(SUBSTITUTE(SUBSTITUTE(UPPER(TRIM(A20)),"EMP",""),"-","")),"000") -> emp019 | C20: Isha Kapoor | D20: 44123 | E20: =IF(D20="","", IF(ISNUMBER(D20),D20, IFERROR(DATEVALUE(D20), IFERROR(DATEVALUE(SUBSTITUTE(SUBSTITUTE(SUBSTITUTE(LOWER(D20),"th",""),".","/"),"-","/")),"Check")))) -> 44123 | F20: Consultant | G20: AI | H20: FTE | I20: PRJ-007 | J20: PRJ-051 | L20: =IF(E20="","Missing",YEAR(E20)) -> 2020 | M20: =IF(E20="","Missing","Q"&ROUNDUP(MONTH(E20)/3,0)) -> Q4 | N20: =YEAR(E20)&"-Q"&ROUNDUP(MONTH(E20)/3,0) -> 2020-Q4
A21: EMP020 | B21: ="emp"&TEXT(VALUE(SUBSTITUTE(SUBSTITUTE(UPPER(TRIM(A21)),"EMP",""),"-","")),"000") -> emp020 | C21: Mohit Bansal | D21: 43668 | E21: =IF(D21="","", IF(ISNUMBER(D21),D21, IFERROR(DATEVALUE(D21), IFERROR(DATEVALUE(SUBSTITUTE(SUBSTITUTE(SUBSTITUTE(LOWER(D21),"th",""),".","/"),"-","/")),"Check")))) -> 43668 | F21: Senior Consultant | G21: Digital | H21: FTE | I21: PRJ-025 | J21: PRJ-063 | K21: PRJ-084 | L21: =IF(E21="","Missing",YEAR(E21)) -> 2019 | M21: =IF(E21="","Missing","Q"&ROUNDUP(MONTH(E21)/3,0)) -> Q3 | N21: =YEAR(E21)&"-Q"&ROUNDUP(MONTH(E21)/3,0) -> 2019-Q3
A22: emp021 | B22: ="emp"&TEXT(VALUE(SUBSTITUTE(SUBSTITUTE(UPPER(TRIM(A22)),"EMP",""),"-","")),"000") -> emp021 | C22: Nisha Jain | D22: 44207 | E22: =IF(D22="","", IF(ISNUMBER(D22),D22, IFERROR(DATEVALUE(D22), IFERROR(DATEVALUE(SUBSTITUTE(SUBSTITUTE(SUBSTITUTE(LOWER(D22),"th",""),".","/"),"-","/")),"Check")))) -> 44207 | F22: Analyst | G22: Data | H22: Intern | I22: PRJ-020 | L22: =IF(E22="","Missing",YEAR(E22)) -> 2021 | M22: =IF(E22="","Missing","Q"&ROUNDUP(MONTH(E22)/3,0)) -> Q1 | N22: =YEAR(E22)&"-Q"&ROUNDUP(MONTH(E22)/3,0) -> 2021-Q1
A23: EMP-022 | B23: ="emp"&TEXT(VALUE(SUBSTITUTE(SUBSTITUTE(UPPER(TRIM(A23)),"EMP",""),"-","")),"000") -> emp022 | C23: Varun Malhotra | D23: 2018.04.03 | E23: =IF(D23="","", IF(ISNUMBER(D23),D23, IFERROR(DATEVALUE(D23), IFERROR(DATEVALUE(SUBSTITUTE(SUBSTITUTE(SUBSTITUTE(LOWER(D23),"th",""),".","/"),"-","/")),"Check")))) -> 43193 | F23: Consultant | G23: AI | H23: FTE | I23: PRJ-036 | J23: PRJ-081 | L23: =IF(E23="","Missing",YEAR(E23)) -> 2018 | M23: =IF(E23="","Missing","Q"&ROUNDUP(MONTH(E23)/3,0)) -> Q2 | N23: =YEAR(E23)&"-Q"&ROUNDUP(MONTH(E23)/3,0) -> 2018-Q2
A24: EMP 023 | B24: ="emp"&TEXT(VALUE(SUBSTITUTE(SUBSTITUTE(UPPER(TRIM(A24)),"EMP",""),"-","")),"000") -> emp023 | C24: Ritu Saxena | D24: 42884 | E24: =IF(D24="","", IF(ISNUMBER(D24),D24, IFERROR(DATEVALUE(D24), IFERROR(DATEVALUE(SUBSTITUTE(SUBSTITUTE(SUBSTITUTE(LOWER(D24),"th",""),".","/"),"-","/")),"Check")))) -> 42884 | F24: Lead Consultant | G24: Digital | H24: FTE | I24: PRJ-010 | J24: PRJ-074 | L24: =IF(E24="","Missing",YEAR(E24)) -> 2017 | M24: =IF(E24="","Missing","Q"&ROUNDUP(MONTH(E24)/3,0)) -> Q2 | N24: =YEAR(E24)&"-Q"&ROUNDUP(MONTH(E24)/3,0) -> 2017-Q2
A25: EMP-024 | B25: ="emp"&TEXT(VALUE(SUBSTITUTE(SUBSTITUTE(UPPER(TRIM(A25)),"EMP",""),"-","")),"000") -> emp024 | C25: Akash Verma | D25: 44805 | E25: =IF(D25="","", IF(ISNUMBER(D25),D25, IFERROR(DATEVALUE(D25), IFERROR(DATEVALUE(SUBSTITUTE(SUBSTITUTE(SUBSTITUTE(LOWER(D25),"th",""),".","/"),"-","/")),"Check")))) -> 44805 | F25: Analyst | G25: Data | H25: FTE | I25: PRJ-023 | J25: PRJ-061 | L25: =IF(E25="","Missing",YEAR(E25)) -> 2022 | M25: =IF(E25="","Missing","Q"&ROUNDUP(MONTH(E25)/3,0)) -> Q3 | N25: =YEAR(E25)&"-Q"&ROUNDUP(MONTH(E25)/3,0) -> 2022-Q3
A26: EMP025 | B26: ="emp"&TEXT(VALUE(SUBSTITUTE(SUBSTITUTE(UPPER(TRIM(A26)),"EMP",""),"-","")),"000") -> emp025 | C26: Pooja Shah | D26: 43878 | E26: =IF(D26="","", IF(ISNUMBER(D26),D26, IFERROR(DATEVALUE(D26), IFERROR(DATEVALUE(SUBSTITUTE(SUBSTITUTE(SUBSTITUTE(LOWER(D26),"th",""),".","/"),"-","/")),"Check")))) -> 43878 | F26: Consultant | G26: AI | H26: FTE | I26: PRJ-002 | J26: PRJ-070 | L26: =IF(E26="","Missing",YEAR(E26)) -> 2020 | M26: =IF(E26="","Missing","Q"&ROUNDUP(MONTH(E26)/3,0)) -> Q1 | N26: =YEAR(E26)&"-Q"&ROUNDUP(MONTH(E26)/3,0) -> 2020-Q1
A27: emp026 | B27: ="emp"&TEXT(VALUE(SUBSTITUTE(SUBSTITUTE(UPPER(TRIM(A27)),"EMP",""),"-","")),"000") -> emp026 | C27: Kunal Desai | D27: 42439 | E27: =IF(D27="","", IF(ISNUMBER(D27),D27, IFERROR(DATEVALUE(D27), IFERROR(DATEVALUE(SUBSTITUTE(SUBSTITUTE(SUBSTITUTE(LOWER(D27),"th",""),".","/"),"-","/")),"Check")))) -> 42439 | F27: Senior Consultant | G27: Digital | H27: Freelancer | I27: PRJ-013 | L27: =IF(E27="","Missing",YEAR(E27)) -> 2016 | M27: =IF(E27="","Missing","Q"&ROUNDUP(MONTH(E27)/3,0)) -> Q1 | N27: =YEAR(E27)&"-Q"&ROUNDUP(MONTH(E27)/3,0) -> 2016-Q1
A28: EMP-027 | B28: ="emp"&TEXT(VALUE(SUBSTITUTE(SUBSTITUTE(UPPER(TRIM(A28)),"EMP",""),"-","")),"000") -> emp027 | C28: Aditi Chawla | D28: 43777 | E28: =IF(D28="","", IF(ISNUMBER(D28),D28, IFERROR(DATEVALUE(D28), IFERROR(DATEVALUE(SUBSTITUTE(SUBSTITUTE(SUBSTITUTE(LOWER(D28),"th",""),".","/"),"-","/")),"Check")))) -> 43777 | F28: Consultant | G28: Data | H28: FTE | I28: PRJ-007 | J28: PRJ-055 | L28: =IF(E28="","Missing",YEAR(E28)) -> 2019 | M28: =IF(E28="","Missing","Q"&ROUNDUP(MONTH(E28)/3,0)) -> Q4 | N28: =YEAR(E28)&"-Q"&ROUNDUP(MONTH(E28)/3,0) -> 2019-Q4
A29: EMP028 | B29: ="emp"&TEXT(VALUE(SUBSTITUTE(SUBSTITUTE(UPPER(TRIM(A29)),"EMP",""),"-","")),"000") -> emp028 | C29: Sarthak Jain | D29: 44361 | E29: =IF(D29="","", IF(ISNUMBER(D29),D29, IFERROR(DATEVALUE(D29), IFERROR(DATEVALUE(SUBSTITUTE(SUBSTITUTE(SUBSTITUTE(LOWER(D29),"th",""),".","/"),"-","/")),"Check")))) -> 44361 | F29: Analyst | G29: AI | H29: Intern | I29: PRJ-036 | J29: PRJ-086 | L29: =IF(E29="","Missing",YEAR(E29)) -> 2021 | M29: =IF(E29="","Missing","Q"&ROUNDUP(MONTH(E29)/3,0)) -> Q2 | N29: =YEAR(E29)&"-Q"&ROUNDUP(MONTH(E29)/3,0) -> 2021-Q2
A30: EMP-029 | B30: ="emp"&TEXT(VALUE(SUBSTITUTE(SUBSTITUTE(UPPER(TRIM(A30)),"EMP",""),"-","")),"000") -> emp029 | C30: Manish Gupta | D30: 43333 | E30: =IF(D30="","", IF(ISNUMBER(D30),D30, IFERROR(DATEVALUE(D30), IFERROR(DATEVALUE(SUBSTITUTE(SUBSTITUTE(SUBSTITUTE(LOWER(D30),"th",""),".","/"),"-","/")),"Check")))) -> 43333 | F30: Lead Consultant | G30: Digital | H30: FTE | I30: PRJ-015 | J30: PRJ-063 | L30: =IF(E30="","Missing",YEAR(E30)) -> 2018 | M30: =IF(E30="","Missing","Q"&ROUNDUP(MONTH(E30)/3,0)) -> Q3 | N30: =YEAR(E30)&"-Q"&ROUNDUP(MONTH(E30)/3,0) -> 2018-Q3
A31: EMP030 | B31: ="emp"&TEXT(VALUE(SUBSTITUTE(SUBSTITUTE(UPPER(TRIM(A31)),"EMP",""),"-","")),"000") -> emp030 | C31: Riya Khanna | D31: 44900 | E31: =IF(D31="","", IF(ISNUMBER(D31),D31, IFERROR(DATEVALUE(D31), IFERROR(DATEVALUE(SUBSTITUTE(SUBSTITUTE(SUBSTITUTE(LOWER(D31),"th",""),".","/"),"-","/")),"Check")))) -> 44900 | F31: Analyst | G31: Data | H31: Intern | I31: PRJ-021 | L31: =IF(E31="","Missing",YEAR(E31)) -> 2022 | M31: =IF(E31="","Missing","Q"&ROUNDUP(MONTH(E31)/3,0)) -> Q4 | N31: =YEAR(E31)&"-Q"&ROUNDUP(MONTH(E31)/3,0) -> 2022-Q4
A32: emp031 | B32: ="emp"&TEXT(VALUE(SUBSTITUTE(SUBSTITUTE(UPPER(TRIM(A32)),"EMP",""),"-","")),"000") -> emp031 | C32: Deepak Yadav | D32: 42843 | E32: =IF(D32="","", IF(ISNUMBER(D32),D32, IFERROR(DATEVALUE(D32), IFERROR(DATEVALUE(SUBSTITUTE(SUBSTITUTE(SUBSTITUTE(LOWER(D32),"th",""),".","/"),"-","/")),"Check")))) -> 42843 | F32: Consultant | G32: AI | H32: Freelancer | I32: PRJ-011 | J32: PRJ-076 | L32: =IF(E32="","Missing",YEAR(E32)) -> 2017 | M32: =IF(E32="","Missing","Q"&ROUNDUP(MONTH(E32)/3,0)) -> Q2 | N32: =YEAR(E32)&"-Q"&ROUNDUP(MONTH(E32)/3,0) -> 2017-Q2
A33: EMP-032 | B33: ="emp"&TEXT(VALUE(SUBSTITUTE(SUBSTITUTE(UPPER(TRIM(A33)),"EMP",""),"-","")),"000") -> emp032 | C33: Shalini Mehra | D33: 43492 | E33: =IF(D33="","", IF(ISNUMBER(D33),D33, IFERROR(DATEVALUE(D33), IFERROR(DATEVALUE(SUBSTITUTE(SUBSTITUTE(SUBSTITUTE(LOWER(D33),"th",""),".","/"),"-","/")),"Check")))) -> 43492 | F33: Senior Consultant | G33: Digital | H33: FTE | I33: PRJ-050 | J33: PRJ-058 | L33: =IF(E33="","Missing",YEAR(E33)) -> 2019 | M33: =IF(E33="","Missing","Q"&ROUNDUP(MONTH(E33)/3,0)) -> Q1 | N33: =YEAR(E33)&"-Q"&ROUNDUP(MONTH(E33)/3,0) -> 2019-Q1
A34: EMP 033 | B34: ="emp"&TEXT(VALUE(SUBSTITUTE(SUBSTITUTE(UPPER(TRIM(A34)),"EMP",""),"-","")),"000") -> emp033 | C34: Vikas Pandey | D34: 2016.06.09 | E34: =IF(D34="","", IF(ISNUMBER(D34),D34, IFERROR(DATEVALUE(D34), IFERROR(DATEVALUE(SUBSTITUTE(SUBSTITUTE(SUBSTITUTE(LOWER(D34),"th",""),".","/"),"-","/")),"Check")))) -> 42530 | F34: Consultant | G34: Data | H34: Freelancer | I34: PRJ-012 | L34: =IF(E34="","Missing",YEAR(E34)) -> 2016 | M34: =IF(E34="","Missing","Q"&ROUNDUP(MONTH(E34)/3,0)) -> Q2 | N34: =YEAR(E34)&"-Q"&ROUNDUP(MONTH(E34)/3,0) -> 2016-Q2
A35: EMP-034 | B35: ="emp"&TEXT(VALUE(SUBSTITUTE(SUBSTITUTE(UPPER(TRIM(A35)),"EMP",""),"-","")),"000") -> emp034 | C35: Tanya Arora | D35: 43964 | E35: =IF(D35="","", IF(ISNUMBER(D35),D35, IFERROR(DATEVALUE(D35), IFERROR(DATEVALUE(SUBSTITUTE(SUBSTITUTE(SUBSTITUTE(LOWER(D35),"th",""),".","/"),"-","/")),"Check")))) -> 43964 | F35: Analyst | G35: AI | H35: Intern | I35: PRJ-041 | J35: PRJ-081 | L35: =IF(E35="","Missing",YEAR(E35)) -> 2020 | M35: =IF(E35="","Missing","Q"&ROUNDUP(MONTH(E35)/3,0)) -> Q2 | N35: =YEAR(E35)&"-Q"&ROUNDUP(MONTH(E35)/3,0) -> 2020-Q2
A36: EMP035 | B36: ="emp"&TEXT(VALUE(SUBSTITUTE(SUBSTITUTE(UPPER(TRIM(A36)),"EMP",""),"-","")),"000") -> emp035 | C36: Abhishek Sen | D36: 44499 | E36: =IF(D36="","", IF(ISNUMBER(D36),D36, IFERROR(DATEVALUE(D36), IFERROR(DATEVALUE(SUBSTITUTE(SUBSTITUTE(SUBSTITUTE(LOWER(D36),"th",""),".","/"),"-","/")),"Check")))) -> 44499 | F36: Consultant | G36: Digital | H36: FTE | I36: PRJ-034 | J36: PRJ-089 | L36: =IF(E36="","Missing",YEAR(E36)) -> 2021 | M36: =IF(E36="","Missing","Q"&ROUNDUP(MONTH(E36)/3,0)) -> Q4 | N36: =YEAR(E36)&"-Q"&ROUNDUP(MONTH(E36)/3,0) -> 2021-Q4
A37: emp036 | B37: ="emp"&TEXT(VALUE(SUBSTITUTE(SUBSTITUTE(UPPER(TRIM(A37)),"EMP",""),"-","")),"000") -> emp036 | C37: Meenal Kulkarni | D37: 43147 | E37: =IF(D37="","", IF(ISNUMBER(D37),D37, IFERROR(DATEVALUE(D37), IFERROR(DATEVALUE(SUBSTITUTE(SUBSTITUTE(SUBSTITUTE(LOWER(D37),"th",""),".","/"),"-","/")),"Check")))) -> 43147 | F37: Lead Consultant | G37: Data | H37: FTE | I37: PRJ-030 | J37: PRJ-071 | K37: PRJ-079 | L37: =IF(E37="","Missing",YEAR(E37)) -> 2018 | M37: =IF(E37="","Missing","Q"&ROUNDUP(MONTH(E37)/3,0)) -> Q1 | N37: =YEAR(E37)&"-Q"&ROUNDUP(MONTH(E37)/3,0) -> 2018-Q1
A38: EMP-037 | B38: ="emp"&TEXT(VALUE(SUBSTITUTE(SUBSTITUTE(UPPER(TRIM(A38)),"EMP",""),"-","")),"000") -> emp037 | C38: Rohan Iyer | D38: 43717 | E38: =IF(D38="","", IF(ISNUMBER(D38),D38, IFERROR(DATEVALUE(D38), IFERROR(DATEVALUE(SUBSTITUTE(SUBSTITUTE(SUBSTITUTE(LOWER(D38),"th",""),".","/"),"-","/")),"Check")))) -> 43717 | F38: Consultant | G38: AI | H38: FTE | I38: PRJ-002 | J38: PRJ-056 | L38: =IF(E38="","Missing",YEAR(E38)) -> 2019 | M38: =IF(E38="","Missing","Q"&ROUNDUP(MONTH(E38)/3,0)) -> Q3 | N38: =YEAR(E38)&"-Q"&ROUNDUP(MONTH(E38)/3,0) -> 2019-Q3
A39: EMP038 | B39: ="emp"&TEXT(VALUE(SUBSTITUTE(SUBSTITUTE(UPPER(TRIM(A39)),"EMP",""),"-","")),"000") -> emp038 | C39: Simran Kaur | D39: 44585 | E39: =IF(D39="","", IF(ISNUMBER(D39),D39, IFERROR(DATEVALUE(D39), IFERROR(DATEVALUE(SUBSTITUTE(SUBSTITUTE(SUBSTITUTE(LOWER(D39),"th",""),".","/"),"-","/")),"Check")))) -> 44585 | F39: Analyst | G39: Digital | H39: Intern | I39: PRJ-040 | L39: =IF(E39="","Missing",YEAR(E39)) -> 2022 | M39: =IF(E39="","Missing","Q"&ROUNDUP(MONTH(E39)/3,0)) -> Q1 | N39: =YEAR(E39)&"-Q"&ROUNDUP(MONTH(E39)/3,0) -> 2022-Q1
A40: EMP-039 | B40: ="emp"&TEXT(VALUE(SUBSTITUTE(SUBSTITUTE(UPPER(TRIM(A40)),"EMP",""),"-","")),"000") -> emp039 | C40: Gaurav Bhatia | D40: 42311 | E40: =IF(D40="","", IF(ISNUMBER(D40),D40, IFERROR(DATEVALUE(D40), IFERROR(DATEVALUE(SUBSTITUTE(SUBSTITUTE(SUBSTITUTE(LOWER(D40),"th",""),".","/"),"-","/")),"Check")))) -> 42311 | F40: Senior Consultant | G40: Data | H40: Freelancer | I40: PRJ-002 | J40: PRJ-088 | L40: =IF(E40="","Missing",YEAR(E40)) -> 2015 | M40: =IF(E40="","Missing","Q"&ROUNDUP(MONTH(E40)/3,0)) -> Q4 | N40: =YEAR(E40)&"-Q"&ROUNDUP(MONTH(E40)/3,0) -> 2015-Q4
A41: EMP040 | B41: ="emp"&TEXT(VALUE(SUBSTITUTE(SUBSTITUTE(UPPER(TRIM(A41)),"EMP",""),"-","")),"000") -> emp040 | C41: Nivedita Roy | D41: 2020.03.18 | E41: =IF(D41="","", IF(ISNUMBER(D41),D41, IFERROR(DATEVALUE(D41), IFERROR(DATEVALUE(SUBSTITUTE(SUBSTITUTE(SUBSTITUTE(LOWER(D41),"th",""),".","/"),"-","/")),"Check")))) -> 43908 | F41: Consultant | G41: AI | H41: FTE | I41: PRJ-025 | J41: PRJ-086 | L41: =IF(E41="","Missing",YEAR(E41)) -> 2020 | M41: =IF(E41="","Missing","Q"&ROUNDUP(MONTH(E41)/3,0)) -> Q1 | N41: =YEAR(E41)&"-Q"&ROUNDUP(MONTH(E41)/3,0) -> 2020-Q1
A42: emp041 | B42: ="emp"&TEXT(VALUE(SUBSTITUTE(SUBSTITUTE(UPPER(TRIM(A42)),"EMP",""),"-","")),"000") -> emp041 | C42: Shubham Agarwal | D42: 44384 | E42: =IF(D42="","", IF(ISNUMBER(D42),D42, IFERROR(DATEVALUE(D42), IFERROR(DATEVALUE(SUBSTITUTE(SUBSTITUTE(SUBSTITUTE(LOWER(D42),"th",""),".","/"),"-","/")),"Check")))) -> 44384 | F42: Analyst | G42: Digital | H42: Intern | I42: PRJ-025 | L42: =IF(E42="","Missing",YEAR(E42)) -> 2021 | M42: =IF(E42="","Missing","Q"&ROUNDUP(MONTH(E42)/3,0)) -> Q3 | N42: =YEAR(E42)&"-Q"&ROUNDUP(MONTH(E42)/3,0) -> 2021-Q3
A43: EMP-042 | B43: ="emp"&TEXT(VALUE(SUBSTITUTE(SUBSTITUTE(UPPER(TRIM(A43)),"EMP",""),"-","")),"000") -> emp042 | C43: Pallavi Deshpande | D43: 43814 | E43: =IF(D43="","", IF(ISNUMBER(D43),D43, IFERROR(DATEVALUE(D43), IFERROR(DATEVALUE(SUBSTITUTE(SUBSTITUTE(SUBSTITUTE(LOWER(D43),"th",""),".","/"),"-","/")),"Check")))) -> 43814 | F43: Consultant | G43: Data | H43: FTE | I43: PRJ-016 | J43: PRJ-067 | L43: =IF(E43="","Missing",YEAR(E43)) -> 2019 | M43: =IF(E43="","Missing","Q"&ROUNDUP(MONTH(E43)/3,0)) -> Q4 | N43: =YEAR(E43)&"-Q"&ROUNDUP(MONTH(E43)/3,0) -> 2019-Q4
A44: EMP 043 | B44: ="emp"&TEXT(VALUE(SUBSTITUTE(SUBSTITUTE(UPPER(TRIM(A44)),"EMP",""),"-","")),"000") -> emp043 | C44: Harish Nair | D44: 42389 | E44: =IF(D44="","", IF(ISNUMBER(D44),D44, IFERROR(DATEVALUE(D44), IFERROR(DATEVALUE(SUBSTITUTE(SUBSTITUTE(SUBSTITUTE(LOWER(D44),"th",""),".","/"),"-","/")),"Check")))) -> 42389 | F44: Lead Consultant | G44: AI | H44: Freelancer | I44: PRJ-025 | J44: PRJ-072 | L44: =IF(E44="","Missing",YEAR(E44)) -> 2016 | M44: =IF(E44="","Missing","Q"&ROUNDUP(MONTH(E44)/3,0)) -> Q1 | N44: =YEAR(E44)&"-Q"&ROUNDUP(MONTH(E44)/3,0) -> 2016-Q1
A45: EMP-044 | B45: ="emp"&TEXT(VALUE(SUBSTITUTE(SUBSTITUTE(UPPER(TRIM(A45)),"EMP",""),"-","")),"000") -> emp044 | C45: Komal Srivastava | D45: 11th dec 2024 | E45: =IF(D45="","", IF(ISNUMBER(D45),D45, IFERROR(DATEVALUE(D45), IFERROR(DATEVALUE(SUBSTITUTE(SUBSTITUTE(SUBSTITUTE(LOWER(D45),"th",""),".","/"),"-","/")),"Check")))) -> 45637 | F45: Consultant | G45: Digital | H45: FTE | I45: PRJ-010 | L45: =IF(E45="","Missing",YEAR(E45)) -> 2024 | M45: =IF(E45="","Missing","Q"&ROUNDUP(MONTH(E45)/3,0)) -> Q4 | N45: =YEAR(E45)&"-Q"&ROUNDUP(MONTH(E45)/3,0) -> 2024-Q4
A46: EMP045 | B46: ="emp"&TEXT(VALUE(SUBSTITUTE(SUBSTITUTE(UPPER(TRIM(A46)),"EMP",""),"-","")),"000") -> emp045 | C46: Siddharth Bose | D46: 43226 | E46: =IF(D46="","", IF(ISNUMBER(D46),D46, IFERROR(DATEVALUE(D46), IFERROR(DATEVALUE(SUBSTITUTE(SUBSTITUTE(SUBSTITUTE(LOWER(D46),"th",""),".","/"),"-","/")),"Check")))) -> 43226 | F46: Sr Consultant | G46: Data | H46: FTE | I46: PRJ-033 | J46: PRJ-080 | L46: =IF(E46="","Missing",YEAR(E46)) -> 2018 | M46: =IF(E46="","Missing","Q"&ROUNDUP(MONTH(E46)/3,0)) -> Q2 | N46: =YEAR(E46)&"-Q"&ROUNDUP(MONTH(E46)/3,0) -> 2018-Q2
A47: emp046 | B47: ="emp"&TEXT(VALUE(SUBSTITUTE(SUBSTITUTE(UPPER(TRIM(A47)),"EMP",""),"-","")),"000") -> emp046 | C47: Neetu Sharma | D47: 44653 | E47: =IF(D47="","", IF(ISNUMBER(D47),D47, IFERROR(DATEVALUE(D47), IFERROR(DATEVALUE(SUBSTITUTE(SUBSTITUTE(SUBSTITUTE(LOWER(D47),"th",""),".","/"),"-","/")),"Check")))) -> 44653 | F47: Analyst | G47: AI | H47: Intern | I47: PRJ-031 | J47: PRJ-060 | L47: =IF(E47="","Missing",YEAR(E47)) -> 2022 | M47: =IF(E47="","Missing","Q"&ROUNDUP(MONTH(E47)/3,0)) -> Q2 | N47: =YEAR(E47)&"-Q"&ROUNDUP(MONTH(E47)/3,0) -> 2022-Q2
A48: EMP-047 | B48: ="emp"&TEXT(VALUE(SUBSTITUTE(SUBSTITUTE(UPPER(TRIM(A48)),"EMP",""),"-","")),"000") -> emp047 | C48: Pranav Kulkarni | D48: 43036 | E48: =IF(D48="","", IF(ISNUMBER(D48),D48, IFERROR(DATEVALUE(D48), IFERROR(DATEVALUE(SUBSTITUTE(SUBSTITUTE(SUBSTITUTE(LOWER(D48),"th",""),".","/"),"-","/")),"Check")))) -> 43036 | F48: Consultant | G48: Digital | H48: Freelancer | I48: PRJ-006 | J48: PRJ-068 | L48: =IF(E48="","Missing",YEAR(E48)) -> 2017 | M48: =IF(E48="","Missing","Q"&ROUNDUP(MONTH(E48)/3,0)) -> Q4 | N48: =YEAR(E48)&"-Q"&ROUNDUP(MONTH(E48)/3,0) -> 2017-Q4
A49: EMP048 | B49: ="emp"&TEXT(VALUE(SUBSTITUTE(SUBSTITUTE(UPPER(TRIM(A49)),"EMP",""),"-","")),"000") -> emp048 | C49: Ayesha Khan | D49: 43617 | E49: =IF(D49="","", IF(ISNUMBER(D49),D49, IFERROR(DATEVALUE(D49), IFERROR(DATEVALUE(SUBSTITUTE(SUBSTITUTE(SUBSTITUTE(LOWER(D49),"th",""),".","/"),"-","/")),"Check")))) -> 43617 | F49: Analyst | G49: Data | H49: FTE | I49: PRJ-026 | J49: PRJ-069 | L49: =IF(E49="","Missing",YEAR(E49)) -> 2019 | M49: =IF(E49="","Missing","Q"&ROUNDUP(MONTH(E49)/3,0)) -> Q2 | N49: =YEAR(E49)&"-Q"&ROUNDUP(MONTH(E49)/3,0) -> 2019-Q2
A50: EMP-049 | B50: ="emp"&TEXT(VALUE(SUBSTITUTE(SUBSTITUTE(UPPER(TRIM(A50)),"EMP",""),"-","")),"000") -> emp049 | C50: Sanjay Pillai | D50: 42049 | E50: =IF(D50="","", IF(ISNUMBER(D50),D50, IFERROR(DATEVALUE(D50), IFERROR(DATEVALUE(SUBSTITUTE(SUBSTITUTE(SUBSTITUTE(LOWER(D50),"th",""),".","/"),"-","/")),"Check")))) -> 42049 | F50: Principal Consultant | G50: AI | H50: Freelancer | I50: PRJ-021 | J50: PRJ-051 | L50: =IF(E50="","Missing",YEAR(E50)) -> 2015 | M50: =IF(E50="","Missing","Q"&ROUNDUP(MONTH(E50)/3,0)) -> Q1 | N50: =YEAR(E50)&"-Q"&ROUNDUP(MONTH(E50)/3,0) -> 2015-Q1
A51: EMP050 | B51: ="emp"&TEXT(VALUE(SUBSTITUTE(SUBSTITUTE(UPPER(TRIM(A51)),"EMP",""),"-","")),"000") -> emp050 | C51: Ruchi Malhotra | D51: 09th jan 2023 | E51: =IF(D51="","", IF(ISNUMBER(D51),D51, IFERROR(DATEVALUE(D51), IFERROR(DATEVALUE(SUBSTITUTE(SUBSTITUTE(SUBSTITUTE(LOWER(D51),"th",""),".","/"),"-","/")),"Check")))) -> 44935 | F51: Analyst | G51: Digital | H51: Intern | I51: PRJ-015 | L51: =IF(E51="","Missing",YEAR(E51)) -> 2023 | M51: =IF(E51="","Missing","Q"&ROUNDUP(MONTH(E51)/3,0)) -> Q1 | N51: =YEAR(E51)&"-Q"&ROUNDUP(MONTH(E51)/3,0) -> 2023-Q1
A52: EMP051 | B52: ="emp"&TEXT(VALUE(SUBSTITUTE(SUBSTITUTE(UPPER(TRIM(A52)),"EMP",""),"-","")),"000") -> emp051 | C52: Aarav Mehta | D52: 43536 | E52: =IF(D52="","", IF(ISNUMBER(D52),D52, IFERROR(DATEVALUE(D52), IFERROR(DATEVALUE(SUBSTITUTE(SUBSTITUTE(SUBSTITUTE(LOWER(D52),"th",""),".","/"),"-","/")),"Check")))) -> 43536 | F52: Consultant | G52: QA | H52: FTE | I52: PRJ-010 | J52: PRJ-069 | L52: =IF(E52="","Missing",YEAR(E52)) -> 2019 | M52: =IF(E52="","Missing","Q"&ROUNDUP(MONTH(E52)/3,0)) -> Q1 | N52: =YEAR(E52)&"-Q"&ROUNDUP(MONTH(E52)/3,0) -> 2019-Q1
A53: emp052 | B53: ="emp"&TEXT(VALUE(SUBSTITUTE(SUBSTITUTE(UPPER(TRIM(A53)),"EMP",""),"-","")),"000") -> emp052 | C53: Nupur Shah | D53: 43933 | E53: =IF(D53="","", IF(ISNUMBER(D53),D53, IFERROR(DATEVALUE(D53), IFERROR(DATEVALUE(SUBSTITUTE(SUBSTITUTE(SUBSTITUTE(LOWER(D53),"th",""),".","/"),"-","/")),"Check")))) -> 43933 | F53: Analyst | G53: Design | H53: Intern | I53: PRJ-006 | L53: =IF(E53="","Missing",YEAR(E53)) -> 2020 | M53: =IF(E53="","Missing","Q"&ROUNDUP(MONTH(E53)/3,0)) -> Q2 | N53: =YEAR(E53)&"-Q"&ROUNDUP(MONTH(E53)/3,0) -> 2020-Q2
A54: EMP 053 | B54: ="emp"&TEXT(VALUE(SUBSTITUTE(SUBSTITUTE(UPPER(TRIM(A54)),"EMP",""),"-","")),"000") -> emp053 | C54: Siddhant Rao | D54: 43282 | E54: =IF(D54="","", IF(ISNUMBER(D54),D54, IFERROR(DATEVALUE(D54), IFERROR(DATEVALUE(SUBSTITUTE(SUBSTITUTE(SUBSTITUTE(LOWER(D54),"th",""),".","/"),"-","/")),"Check")))) -> 43282 | F54: Senior Consultant | G54: PMO | H54: FTE | I54: PRJ-013 | J54: PRJ-077 | L54: =IF(E54="","Missing",YEAR(E54)) -> 2018 | M54: =IF(E54="","Missing","Q"&ROUNDUP(MONTH(E54)/3,0)) -> Q3 | N54: =YEAR(E54)&"-Q"&ROUNDUP(MONTH(E54)/3,0) -> 2018-Q3
A55: EMP-054 | B55: ="emp"&TEXT(VALUE(SUBSTITUTE(SUBSTITUTE(UPPER(TRIM(A55)),"EMP",""),"-","")),"000") -> emp054 | C55: Kavya Nair | D55: 44440 | E55: =IF(D55="","", IF(ISNUMBER(D55),D55, IFERROR(DATEVALUE(D55), IFERROR(DATEVALUE(SUBSTITUTE(SUBSTITUTE(SUBSTITUTE(LOWER(D55),"th",""),".","/"),"-","/")),"Check")))) -> 44440 | F55: Consultant | G55: QA | H55: FTE | I55: PRJ-005 | J55: PRJ-059 | L55: =IF(E55="","Missing",YEAR(E55)) -> 2021 | M55: =IF(E55="","Missing","Q"&ROUNDUP(MONTH(E55)/3,0)) -> Q3 | N55: =YEAR(E55)&"-Q"&ROUNDUP(MONTH(E55)/3,0) -> 2021-Q3
A56: EMP055 | B56: ="emp"&TEXT(VALUE(SUBSTITUTE(SUBSTITUTE(UPPER(TRIM(A56)),"EMP",""),"-","")),"000") -> emp055 | C56: Harshit Gupta | D56: 43054 | E56: =IF(D56="","", IF(ISNUMBER(D56),D56, IFERROR(DATEVALUE(D56), IFERROR(DATEVALUE(SUBSTITUTE(SUBSTITUTE(SUBSTITUTE(LOWER(D56),"th",""),".","/"),"-","/")),"Check")))) -> 43054 | F56: Lead Consultant | G56: Cloud | H56: FTE | I56: PRJ-009 | J56: PRJ-052 | L56: =IF(E56="","Missing",YEAR(E56)) -> 2017 | M56: =IF(E56="","Missing","Q"&ROUNDUP(MONTH(E56)/3,0)) -> Q4 | N56: =YEAR(E56)&"-Q"&ROUNDUP(MONTH(E56)/3,0) -> 2017-Q4
A57: emp056 | B57: ="emp"&TEXT(VALUE(SUBSTITUTE(SUBSTITUTE(UPPER(TRIM(A57)),"EMP",""),"-","")),"000") -> emp056 | C57: Rohan Kulkarni | D57: 42420 | E57: =IF(D57="","", IF(ISNUMBER(D57),D57, IFERROR(DATEVALUE(D57), IFERROR(DATEVALUE(SUBSTITUTE(SUBSTITUTE(SUBSTITUTE(LOWER(D57),"th",""),".","/"),"-","/")),"Check")))) -> 42420 | F57: Consultant | G57: Support | H57: FTE | I57: PRJ-017 | J57: PRJ-056 | L57: =IF(E57="","Missing",YEAR(E57)) -> 2016 | M57: =IF(E57="","Missing","Q"&ROUNDUP(MONTH(E57)/3,0)) -> Q1 | N57: =YEAR(E57)&"-Q"&ROUNDUP(MONTH(E57)/3,0) -> 2016-Q1
A58: EMP-057 | B58: ="emp"&TEXT(VALUE(SUBSTITUTE(SUBSTITUTE(UPPER(TRIM(A58)),"EMP",""),"-","")),"000") -> emp057 | C58: Pritam Das | D58: 2019.05.09 | E58: =IF(D58="","", IF(ISNUMBER(D58),D58, IFERROR(DATEVALUE(D58), IFERROR(DATEVALUE(SUBSTITUTE(SUBSTITUTE(SUBSTITUTE(LOWER(D58),"th",""),".","/"),"-","/")),"Check")))) -> 43594 | F58: Analyst | G58: Design | H58: FTE | I58: PRJ-006 | J58: PRJ-084 | L58: =IF(E58="","Missing",YEAR(E58)) -> 2019 | M58: =IF(E58="","Missing","Q"&ROUNDUP(MONTH(E58)/3,0)) -> Q2 | N58: =YEAR(E58)&"-Q"&ROUNDUP(MONTH(E58)/3,0) -> 2019-Q2
A59: EMP058 | B59: ="emp"&TEXT(VALUE(SUBSTITUTE(SUBSTITUTE(UPPER(TRIM(A59)),"EMP",""),"-","")),"000") -> emp058 | C59: Shreya Malhotra | D59: 44060 | E59: =IF(D59="","", IF(ISNUMBER(D59),D59, IFERROR(DATEVALUE(D59), IFERROR(DATEVALUE(SUBSTITUTE(SUBSTITUTE(SUBSTITUTE(LOWER(D59),"th",""),".","/"),"-","/")),"Check")))) -> 44060 | F59: Consultant | G59: QA | H59: FTE | I59: PRJ-001 | J59: PRJ-064 | L59: =IF(E59="","Missing",YEAR(E59)) -> 2020 | M59: =IF(E59="","Missing","Q"&ROUNDUP(MONTH(E59)/3,0)) -> Q3 | N59: =YEAR(E59)&"-Q"&ROUNDUP(MONTH(E59)/3,0) -> 2020-Q3
A60: EMP 059 | B60: ="emp"&TEXT(VALUE(SUBSTITUTE(SUBSTITUTE(UPPER(TRIM(A60)),"EMP",""),"-","")),"000") -> emp059 | C60: Kunal Verma | D60: 43125 | E60: =IF(D60="","", IF(ISNUMBER(D60),D60, IFERROR(DATEVALUE(D60), IFERROR(DATEVALUE(SUBSTITUTE(SUBSTITUTE(SUBSTITUTE(LOWER(D60),"th",""),".","/"),"-","/")),"Check")))) -> 43125 | F60: Sr Consultant | G60: PMO | H60: FTE | I60: PRJ-026 | J60: PRJ-064 | K60: PRJ-087 | L60: =IF(E60="","Missing",YEAR(E60)) -> 2018 | M60: =IF(E60="","Missing","Q"&ROUNDUP(MONTH(E60)/3,0)) -> Q1 | N60: =YEAR(E60)&"-Q"&ROUNDUP(MONTH(E60)/3,0) -> 2018-Q1
A61: EMP-060 | B61: ="emp"&TEXT(VALUE(SUBSTITUTE(SUBSTITUTE(UPPER(TRIM(A61)),"EMP",""),"-","")),"000") -> emp060 | C61: Ritu Agarwal | D61: 44361 | E61: =IF(D61="","", IF(ISNUMBER(D61),D61, IFERROR(DATEVALUE(D61), IFERROR(DATEVALUE(SUBSTITUTE(SUBSTITUTE(SUBSTITUTE(LOWER(D61),"th",""),".","/"),"-","/")),"Check")))) -> 44361 | F61: Analyst | G61: Design | H61: FTE | I61: PRJ-018 | J61: PRJ-058 | L61: =IF(E61="","Missing",YEAR(E61)) -> 2021 | M61: =IF(E61="","Missing","Q"&ROUNDUP(MONTH(E61)/3,0)) -> Q2 | N61: =YEAR(E61)&"-Q"&ROUNDUP(MONTH(E61)/3,0) -> 2021-Q2
A62: emp061 | B62: ="emp"&TEXT(VALUE(SUBSTITUTE(SUBSTITUTE(UPPER(TRIM(A62)),"EMP",""),"-","")),"000") -> emp061 | C62: Mohan Iyer | D62: 42981 | E62: =IF(D62="","", IF(ISNUMBER(D62),D62, IFERROR(DATEVALUE(D62), IFERROR(DATEVALUE(SUBSTITUTE(SUBSTITUTE(SUBSTITUTE(LOWER(D62),"th",""),".","/"),"-","/")),"Check")))) -> 42981 | F62: Consultant | G62: Cloud | H62: FTE | I62: PRJ-022 | J62: PRJ-081 | L62: =IF(E62="","Missing",YEAR(E62)) -> 2017 | M62: =IF(E62="","Missing","Q"&ROUNDUP(MONTH(E62)/3,0)) -> Q3 | N62: =YEAR(E62)&"-Q"&ROUNDUP(MONTH(E62)/3,0) -> 2017-Q3
A63: EMP062 | B63: ="emp"&TEXT(VALUE(SUBSTITUTE(SUBSTITUTE(UPPER(TRIM(A63)),"EMP",""),"-","")),"000") -> emp062 | C63: Tanya Bose | D63: 43810 | E63: =IF(D63="","", IF(ISNUMBER(D63),D63, IFERROR(DATEVALUE(D63), IFERROR(DATEVALUE(SUBSTITUTE(SUBSTITUTE(SUBSTITUTE(LOWER(D63),"th",""),".","/"),"-","/")),"Check")))) -> 43810 | F63: Consultant | G63: Support | H63: FTE | I63: PRJ-024 | J63: PRJ-078 | L63: =IF(E63="","Missing",YEAR(E63)) -> 2019 | M63: =IF(E63="","Missing","Q"&ROUNDUP(MONTH(E63)/3,0)) -> Q4 | N63: =YEAR(E63)&"-Q"&ROUNDUP(MONTH(E63)/3,0) -> 2019-Q4
A64: EMP-063 | B64: ="emp"&TEXT(VALUE(SUBSTITUTE(SUBSTITUTE(UPPER(TRIM(A64)),"EMP",""),"-","")),"000") -> emp063 | C64: Aditya Kapoor | D64: 42479 | E64: =IF(D64="","", IF(ISNUMBER(D64),D64, IFERROR(DATEVALUE(D64), IFERROR(DATEVALUE(SUBSTITUTE(SUBSTITUTE(SUBSTITUTE(LOWER(D64),"th",""),".","/"),"-","/")),"Check")))) -> 42479 | F64: Lead Consultant | G64: QA | H64: FTE | I64: PRJ-019 | J64: PRJ-052 | K64: PRJ-059 | L64: =IF(E64="","Missing",YEAR(E64)) -> 2016 | M64: =IF(E64="","Missing","Q"&ROUNDUP(MONTH(E64)/3,0)) -> Q2 | N64: =YEAR(E64)&"-Q"&ROUNDUP(MONTH(E64)/3,0) -> 2016-Q2
A65: EMP064 | B65: ="emp"&TEXT(VALUE(SUBSTITUTE(SUBSTITUTE(UPPER(TRIM(A65)),"EMP",""),"-","")),"000") -> emp064 | C65: Neelam Singh | D65: 44599 | E65: =IF(D65="","", IF(ISNUMBER(D65),D65, IFERROR(DATEVALUE(D65), IFERROR(DATEVALUE(SUBSTITUTE(SUBSTITUTE(SUBSTITUTE(LOWER(D65),"th",""),".","/"),"-","/")),"Check")))) -> 44599 | F65: Analyst | G65: Design | H65: Intern | I65: PRJ-011 | L65: =IF(E65="","Missing",YEAR(E65)) -> 2022 | M65: =IF(E65="","Missing","Q"&ROUNDUP(MONTH(E65)/3,0)) -> Q1 | N65: =YEAR(E65)&"-Q"&ROUNDUP(MONTH(E65)/3,0) -> 2022-Q1
A66: EMP 065 | B66: ="emp"&TEXT(VALUE(SUBSTITUTE(SUBSTITUTE(UPPER(TRIM(A66)),"EMP",""),"-","")),"000") -> emp065 | C66: Varsha Kulkarni | D66: 2018.10.22 | E66: =IF(D66="","", IF(ISNUMBER(D66),D66, IFERROR(DATEVALUE(D66), IFERROR(DATEVALUE(SUBSTITUTE(SUBSTITUTE(SUBSTITUTE(LOWER(D66),"th",""),".","/"),"-","/")),"Check")))) -> 43395 | F66: Consultant | G66: PMO | H66: FTE | I66: PRJ-009 | J66: PRJ-082 | L66: =IF(E66="","Missing",YEAR(E66)) -> 2018 | M66: =IF(E66="","Missing","Q"&ROUNDUP(MONTH(E66)/3,0)) -> Q4 | N66: =YEAR(E66)&"-Q"&ROUNDUP(MONTH(E66)/3,0) -> 2018-Q4
A67: EMP-066 | B67: ="emp"&TEXT(VALUE(SUBSTITUTE(SUBSTITUTE(UPPER(TRIM(A67)),"EMP",""),"-","")),"000") -> emp066 | C67: Aman Choudhary | D67: 43860 | E67: =IF(D67="","", IF(ISNUMBER(D67),D67, IFERROR(DATEVALUE(D67), IFERROR(DATEVALUE(SUBSTITUTE(SUBSTITUTE(SUBSTITUTE(LOWER(D67),"th",""),".","/"),"-","/")),"Check")))) -> 43860 | F67: Sr Consultant | G67: Cloud | H67: FTE | I67: PRJ-020 | J67: PRJ-066 | K67: PRJ-077 | L67: =IF(E67="","Missing",YEAR(E67)) -> 2020 | M67: =IF(E67="","Missing","Q"&ROUNDUP(MONTH(E67)/3,0)) -> Q1 | N67: =YEAR(E67)&"-Q"&ROUNDUP(MONTH(E67)/3,0) -> 2020-Q1
A68: emp067 | B68: ="emp"&TEXT(VALUE(SUBSTITUTE(SUBSTITUTE(UPPER(TRIM(A68)),"EMP",""),"-","")),"000") -> emp067 | C68: Poonam Tiwari | D68: 43621 | E68: =IF(D68="","", IF(ISNUMBER(D68),D68, IFERROR(DATEVALUE(D68), IFERROR(DATEVALUE(SUBSTITUTE(SUBSTITUTE(SUBSTITUTE(LOWER(D68),"th",""),".","/"),"-","/")),"Check")))) -> 43621 | F68: Consultant | G68: Support | H68: FTE | I68: PRJ-031 | L68: =IF(E68="","Missing",YEAR(E68)) -> 2019 | M68: =IF(E68="","Missing","Q"&ROUNDUP(MONTH(E68)/3,0)) -> Q2 | N68: =YEAR(E68)&"-Q"&ROUNDUP(MONTH(E68)/3,0) -> 2019-Q2
A69: EMP068 | B69: ="emp"&TEXT(VALUE(SUBSTITUTE(SUBSTITUTE(UPPER(TRIM(A69)),"EMP",""),"-","")),"000") -> emp068 | C69: Yash Bansal | D69: 44273 | E69: =IF(D69="","", IF(ISNUMBER(D69),D69, IFERROR(DATEVALUE(D69), IFERROR(DATEVALUE(SUBSTITUTE(SUBSTITUTE(SUBSTITUTE(LOWER(D69),"th",""),".","/"),"-","/")),"Check")))) -> 44273 | F69: Analyst | G69: QA | H69: Intern | I69: PRJ-016 | L69: =IF(E69="","Missing",YEAR(E69)) -> 2021 | M69: =IF(E69="","Missing","Q"&ROUNDUP(MONTH(E69)/3,0)) -> Q1 | N69: =YEAR(E69)&"-Q"&ROUNDUP(MONTH(E69)/3,0) -> 2021-Q1
A70: EMP-069 | B70: ="emp"&TEXT(VALUE(SUBSTITUTE(SUBSTITUTE(UPPER(TRIM(A70)),"EMP",""),"-","")),"000") -> emp069 | C70: Nikhil Arora | D70: 42943 | E70: =IF(D70="","", IF(ISNUMBER(D70),D70, IFERROR(DATEVALUE(D70), IFERROR(DATEVALUE(SUBSTITUTE(SUBSTITUTE(SUBSTITUTE(LOWER(D70),"th",""),".","/"),"-","/")),"Check")))) -> 42943 | F70: Consultant | G70: Design | H70: FTE | I70: PRJ-001 | J70: PRJ-053 | L70: =IF(E70="","Missing",YEAR(E70)) -> 2017 | M70: =IF(E70="","Missing","Q"&ROUNDUP(MONTH(E70)/3,0)) -> Q3 | N70: =YEAR(E70)&"-Q"&ROUNDUP(MONTH(E70)/3,0) -> 2017-Q3
A71: EMP070 | B71: ="emp"&TEXT(VALUE(SUBSTITUTE(SUBSTITUTE(UPPER(TRIM(A71)),"EMP",""),"-","")),"000") -> emp070 | C71: Rashi Malhotra | D71: 44692 | E71: =IF(D71="","", IF(ISNUMBER(D71),D71, IFERROR(DATEVALUE(D71), IFERROR(DATEVALUE(SUBSTITUTE(SUBSTITUTE(SUBSTITUTE(LOWER(D71),"th",""),".","/"),"-","/")),"Check")))) -> 44692 | F71: Analyst | G71: PMO | H71: Intern | I71: PRJ-037 | L71: =IF(E71="","Missing",YEAR(E71)) -> 2022 | M71: =IF(E71="","Missing","Q"&ROUNDUP(MONTH(E71)/3,0)) -> Q2 | N71: =YEAR(E71)&"-Q"&ROUNDUP(MONTH(E71)/3,0) -> 2022-Q2
A72: emp071 | B72: ="emp"&TEXT(VALUE(SUBSTITUTE(SUBSTITUTE(UPPER(TRIM(A72)),"EMP",""),"-","")),"000") -> emp071 | C72: Abhinav Jain | D72: 42627 | E72: =IF(D72="","", IF(ISNUMBER(D72),D72, IFERROR(DATEVALUE(D72), IFERROR(DATEVALUE(SUBSTITUTE(SUBSTITUTE(SUBSTITUTE(LOWER(D72),"th",""),".","/"),"-","/")),"Check")))) -> 42627 | F72: Lead Consultant | G72: Cloud | H72: FTE | I72: PRJ-038 | J72: PRJ-071 | L72: =IF(E72="","Missing",YEAR(E72)) -> 2016 | M72: =IF(E72="","Missing","Q"&ROUNDUP(MONTH(E72)/3,0)) -> Q3 | N72: =YEAR(E72)&"-Q"&ROUNDUP(MONTH(E72)/3,0) -> 2016-Q3
A73: EMP072 | B73: ="emp"&TEXT(VALUE(SUBSTITUTE(SUBSTITUTE(UPPER(TRIM(A73)),"EMP",""),"-","")),"000") -> emp072 | C73: Komal Vyas | D73: 43437 | E73: =IF(D73="","", IF(ISNUMBER(D73),D73, IFERROR(DATEVALUE(D73), IFERROR(DATEVALUE(SUBSTITUTE(SUBSTITUTE(SUBSTITUTE(LOWER(D73),"th",""),".","/"),"-","/")),"Check")))) -> 43437 | F73: Consultant | G73: QA | H73: FTE | I73: PRJ-019 | J73: PRJ-075 | L73: =IF(E73="","Missing",YEAR(E73)) -> 2018 | M73: =IF(E73="","Missing","Q"&ROUNDUP(MONTH(E73)/3,0)) -> Q4 | N73: =YEAR(E73)&"-Q"&ROUNDUP(MONTH(E73)/3,0) -> 2018-Q4
A74: EMP 073 | B74: ="emp"&TEXT(VALUE(SUBSTITUTE(SUBSTITUTE(UPPER(TRIM(A74)),"EMP",""),"-","")),"000") -> emp073 | C74: Parth Shah | D74: 43581 | E74: =IF(D74="","", IF(ISNUMBER(D74),D74, IFERROR(DATEVALUE(D74), IFERROR(DATEVALUE(SUBSTITUTE(SUBSTITUTE(SUBSTITUTE(LOWER(D74),"th",""),".","/"),"-","/")),"Check")))) -> 43581 | F74: Sr Consultant | G74: Design | H74: FTE | I74: PRJ-027 | J74: PRJ-074 | K74: PRJ-079 | L74: =IF(E74="","Missing",YEAR(E74)) -> 2019 | M74: =IF(E74="","Missing","Q"&ROUNDUP(MONTH(E74)/3,0)) -> Q2 | N74: =YEAR(E74)&"-Q"&ROUNDUP(MONTH(E74)/3,0) -> 2019-Q2
A75: EMP-074 | B75: ="emp"&TEXT(VALUE(SUBSTITUTE(SUBSTITUTE(UPPER(TRIM(A75)),"EMP",""),"-","")),"000") -> emp074 | C75: Meera Joshi | D75: 44385 | E75: =IF(D75="","", IF(ISNUMBER(D75),D75, IFERROR(DATEVALUE(D75), IFERROR(DATEVALUE(SUBSTITUTE(SUBSTITUTE(SUBSTITUTE(LOWER(D75),"th",""),".","/"),"-","/")),"Check")))) -> 44385 | F75: Analyst | G75: Support | H75: FTE | I75: PRJ-008 | J75: PRJ-072 | L75: =IF(E75="","Missing",YEAR(E75)) -> 2021 | M75: =IF(E75="","Missing","Q"&ROUNDUP(MONTH(E75)/3,0)) -> Q3 | N75: =YEAR(E75)&"-Q"&ROUNDUP(MONTH(E75)/3,0) -> 2021-Q3
A76: EMP075 | B76: ="emp"&TEXT(VALUE(SUBSTITUTE(SUBSTITUTE(UPPER(TRIM(A76)),"EMP",""),"-","")),"000") -> emp075 | C76: Raghav Mishra | D76: 2017.02.16 | E76: =IF(D76="","", IF(ISNUMBER(D76),D76, IFERROR(DATEVALUE(D76), IFERROR(DATEVALUE(SUBSTITUTE(SUBSTITUTE(SUBSTITUTE(LOWER(D76),"th",""),".","/"),"-","/")),"Check")))) -> 42782 | F76: Consultant | G76: PMO | H76: FTE | I76: PRJ-042 | J76: PRJ-073 | L76: =IF(E76="","Missing",YEAR(E76)) -> 2017 | M76: =IF(E76="","Missing","Q"&ROUNDUP(MONTH(E76)/3,0)) -> Q1 | N76: =YEAR(E76)&"-Q"&ROUNDUP(MONTH(E76)/3,0) -> 2017-Q1
A77: emp076 | B77: ="emp"&TEXT(VALUE(SUBSTITUTE(SUBSTITUTE(UPPER(TRIM(A77)),"EMP",""),"-","")),"000") -> emp076 | C77: Snehal Patil | D77: 44133 | E77: =IF(D77="","", IF(ISNUMBER(D77),D77, IFERROR(DATEVALUE(D77), IFERROR(DATEVALUE(SUBSTITUTE(SUBSTITUTE(SUBSTITUTE(LOWER(D77),"th",""),".","/"),"-","/")),"Check")))) -> 44133 | F77: Consultant | G77: QA | H77: FTE | I77: PRJ-002 | L77: =IF(E77="","Missing",YEAR(E77)) -> 2020 | M77: =IF(E77="","Missing","Q"&ROUNDUP(MONTH(E77)/3,0)) -> Q4 | N77: =YEAR(E77)&"-Q"&ROUNDUP(MONTH(E77)/3,0) -> 2020-Q4
A78: EMP-077 | B78: ="emp"&TEXT(VALUE(SUBSTITUTE(SUBSTITUTE(UPPER(TRIM(A78)),"EMP",""),"-","")),"000") -> emp077 | C78: Vimal Khanna | D78: 43113 | E78: =IF(D78="","", IF(ISNUMBER(D78),D78, IFERROR(DATEVALUE(D78), IFERROR(DATEVALUE(SUBSTITUTE(SUBSTITUTE(SUBSTITUTE(LOWER(D78),"th",""),".","/"),"-","/")),"Check")))) -> 43113 | F78: Sr Consultant | G78: Cloud | H78: FTE | I78: PRJ-040 | L78: =IF(E78="","Missing",YEAR(E78)) -> 2018 | M78: =IF(E78="","Missing","Q"&ROUNDUP(MONTH(E78)/3,0)) -> Q1 | N78: =YEAR(E78)&"-Q"&ROUNDUP(MONTH(E78)/3,0) -> 2018-Q1
A79: EMP078 | B79: ="emp"&TEXT(VALUE(SUBSTITUTE(SUBSTITUTE(UPPER(TRIM(A79)),"EMP",""),"-","")),"000") -> emp078 | C79: Aishwarya Kulkarni | D79: 44733 | E79: =IF(D79="","", IF(ISNUMBER(D79),D79, IFERROR(DATEVALUE(D79), IFERROR(DATEVALUE(SUBSTITUTE(SUBSTITUTE(SUBSTITUTE(LOWER(D79),"th",""),".","/"),"-","/")),"Check")))) -> 44733 | F79: Analyst | G79: Design | H79: Intern | I79: PRJ-018 | L79: =IF(E79="","Missing",YEAR(E79)) -> 2022 | M79: =IF(E79="","Missing","Q"&ROUNDUP(MONTH(E79)/3,0)) -> Q2 | N79: =YEAR(E79)&"-Q"&ROUNDUP(MONTH(E79)/3,0) -> 2022-Q2
A80: EMP 079 | B80: ="emp"&TEXT(VALUE(SUBSTITUTE(SUBSTITUTE(UPPER(TRIM(A80)),"EMP",""),"-","")),"000") -> emp079 | C80: Devansh Gupta | D80: 42494 | E80: =IF(D80="","", IF(ISNUMBER(D80),D80, IFERROR(DATEVALUE(D80), IFERROR(DATEVALUE(SUBSTITUTE(SUBSTITUTE(SUBSTITUTE(LOWER(D80),"th",""),".","/"),"-","/")),"Check")))) -> 42494 | F80: Lead Consultant | G80: Support | H80: FTE | I80: PRJ-014 | J80: PRJ-057 | L80: =IF(E80="","Missing",YEAR(E80)) -> 2016 | M80: =IF(E80="","Missing","Q"&ROUNDUP(MONTH(E80)/3,0)) -> Q2 | N80: =YEAR(E80)&"-Q"&ROUNDUP(MONTH(E80)/3,0) -> 2016-Q2
A81: EMP-080 | B81: ="emp"&TEXT(VALUE(SUBSTITUTE(SUBSTITUTE(UPPER(TRIM(A81)),"EMP",""),"-","")),"000") -> emp080 | C81: Pallavi Mehta | D81: 43788 | E81: =IF(D81="","", IF(ISNUMBER(D81),D81, IFERROR(DATEVALUE(D81), IFERROR(DATEVALUE(SUBSTITUTE(SUBSTITUTE(SUBSTITUTE(LOWER(D81),"th",""),".","/"),"-","/")),"Check")))) -> 43788 | F81: Consultant | G81: QA | H81: FTE | I81: PRJ-028 | J81: PRJ-054 | L81: =IF(E81="","Missing",YEAR(E81)) -> 2019 | M81: =IF(E81="","Missing","Q"&ROUNDUP(MONTH(E81)/3,0)) -> Q4 | N81: =YEAR(E81)&"-Q"&ROUNDUP(MONTH(E81)/3,0) -> 2019-Q4
A82: emp081 | B82: ="emp"&TEXT(VALUE(SUBSTITUTE(SUBSTITUTE(UPPER(TRIM(A82)),"EMP",""),"-","")),"000") -> emp081 | C82: Aniket Rao | D82: 42801 | E82: =IF(D82="","", IF(ISNUMBER(D82),D82, IFERROR(DATEVALUE(D82), IFERROR(DATEVALUE(SUBSTITUTE(SUBSTITUTE(SUBSTITUTE(LOWER(D82),"th",""),".","/"),"-","/")),"Check")))) -> 42801 | F82: Consultant | G82: Cloud | H82: Intern | I82: PRJ-048 | J82: PRJ-057 | L82: =IF(E82="","Missing",YEAR(E82)) -> 2017 | M82: =IF(E82="","Missing","Q"&ROUNDUP(MONTH(E82)/3,0)) -> Q1 | N82: =YEAR(E82)&"-Q"&ROUNDUP(MONTH(E82)/3,0) -> 2017-Q1
A83: EMP115 | B83: ="emp"&TEXT(VALUE(SUBSTITUTE(SUBSTITUTE(UPPER(TRIM(A83)),"EMP",""),"-","")),"000") -> emp115 | C83: Shreya Rai | D83: 43788 | E83: =IF(D83="","", IF(ISNUMBER(D83),D83, IFERROR(DATEVALUE(D83), IFERROR(DATEVALUE(SUBSTITUTE(SUBSTITUTE(SUBSTITUTE(LOWER(D83),"th",""),".","/"),"-","/")),"Check")))) -> 43788 | F83: Consultant | G83: Cloud | H83: FTE | I83: PRJ-032 | L83: =IF(E83="","Missing",YEAR(E83)) -> 2019 | M83: =IF(E83="","Missing","Q"&ROUNDUP(MONTH(E83)/3,0)) -> Q4 | N83: =YEAR(E83)&"-Q"&ROUNDUP(MONTH(E83)/3,0) -> 2019-Q4
A84: EMP082 | B84: ="emp"&TEXT(VALUE(SUBSTITUTE(SUBSTITUTE(UPPER(TRIM(A84)),"EMP",""),"-","")),"000") -> emp082 | C84: Rina Dsouza | D84: 2020.09.02 | E84: =IF(D84="","", IF(ISNUMBER(D84),D84, IFERROR(DATEVALUE(D84), IFERROR(DATEVALUE(SUBSTITUTE(SUBSTITUTE(SUBSTITUTE(LOWER(D84),"th",""),".","/"),"-","/")),"Check")))) -> 44076 | F84: Analyst | G84: Design | H84: Intern | I84: PRJ-001 | L84: =IF(E84="","Missing",YEAR(E84)) -> 2020 | M84: =IF(E84="","Missing","Q"&ROUNDUP(MONTH(E84)/3,0)) -> Q3 | N84: =YEAR(E84)&"-Q"&ROUNDUP(MONTH(E84)/3,0) -> 2020-Q3
A85: EMP-083 | B85: ="emp"&TEXT(VALUE(SUBSTITUTE(SUBSTITUTE(UPPER(TRIM(A85)),"EMP",""),"-","")),"000") -> emp083 | C85: Karthik Nair | D85: 43340 | E85: =IF(D85="","", IF(ISNUMBER(D85),D85, IFERROR(DATEVALUE(D85), IFERROR(DATEVALUE(SUBSTITUTE(SUBSTITUTE(SUBSTITUTE(LOWER(D85),"th",""),".","/"),"-","/")),"Check")))) -> 43340 | F85: Consultant | G85: PMO | H85: FTE | I85: PRJ-005 | L85: =IF(E85="","Missing",YEAR(E85)) -> 2018 | M85: =IF(E85="","Missing","Q"&ROUNDUP(MONTH(E85)/3,0)) -> Q3 | N85: =YEAR(E85)&"-Q"&ROUNDUP(MONTH(E85)/3,0) -> 2018-Q3
A86: EMP084 | B86: ="emp"&TEXT(VALUE(SUBSTITUTE(SUBSTITUTE(UPPER(TRIM(A86)),"EMP",""),"-","")),"000") -> emp084 | C86: Shubhi Arora | D86: 44212 | E86: =IF(D86="","", IF(ISNUMBER(D86),D86, IFERROR(DATEVALUE(D86), IFERROR(DATEVALUE(SUBSTITUTE(SUBSTITUTE(SUBSTITUTE(LOWER(D86),"th",""),".","/"),"-","/")),"Check")))) -> 44212 | F86: Analyst | G86: Support | H86: FTE | I86: PRJ-003 | L86: =IF(E86="","Missing",YEAR(E86)) -> 2021 | M86: =IF(E86="","Missing","Q"&ROUNDUP(MONTH(E86)/3,0)) -> Q1 | N86: =YEAR(E86)&"-Q"&ROUNDUP(MONTH(E86)/3,0) -> 2021-Q1
A87: EMP 085 | B87: ="emp"&TEXT(VALUE(SUBSTITUTE(SUBSTITUTE(UPPER(TRIM(A87)),"EMP",""),"-","")),"000") -> emp085 | C87: Manav Kapoor | D87: 42713 | E87: =IF(D87="","", IF(ISNUMBER(D87),D87, IFERROR(DATEVALUE(D87), IFERROR(DATEVALUE(SUBSTITUTE(SUBSTITUTE(SUBSTITUTE(LOWER(D87),"th",""),".","/"),"-","/")),"Check")))) -> 42713 | F87: Sr Consultant | G87: QA | H87: FTE | I87: PRJ-008 | J87: PRJ-075 | K87: PRJ-069 | L87: =IF(E87="","Missing",YEAR(E87)) -> 2016 | M87: =IF(E87="","Missing","Q"&ROUNDUP(MONTH(E87)/3,0)) -> Q4 | N87: =YEAR(E87)&"-Q"&ROUNDUP(MONTH(E87)/3,0) -> 2016-Q4
A88: EMP-086 | B88: ="emp"&TEXT(VALUE(SUBSTITUTE(SUBSTITUTE(UPPER(TRIM(A88)),"EMP",""),"-","")),"000") -> emp086 | C88: Rupal Shah | D88: 43616 | E88: =IF(D88="","", IF(ISNUMBER(D88),D88, IFERROR(DATEVALUE(D88), IFERROR(DATEVALUE(SUBSTITUTE(SUBSTITUTE(SUBSTITUTE(LOWER(D88),"th",""),".","/"),"-","/")),"Check")))) -> 43616 | F88: Consultant | G88: Design | H88: FTE | I88: PRJ-015 | J88: PRJ-068 | L88: =IF(E88="","Missing",YEAR(E88)) -> 2019 | M88: =IF(E88="","Missing","Q"&ROUNDUP(MONTH(E88)/3,0)) -> Q2 | N88: =YEAR(E88)&"-Q"&ROUNDUP(MONTH(E88)/3,0) -> 2019-Q2
A89: emp087 | B89: ="emp"&TEXT(VALUE(SUBSTITUTE(SUBSTITUTE(UPPER(TRIM(A89)),"EMP",""),"-","")),"000") -> emp087 | C89: Vinayak Patil | D89: 42909 | E89: =IF(D89="","", IF(ISNUMBER(D89),D89, IFERROR(DATEVALUE(D89), IFERROR(DATEVALUE(SUBSTITUTE(SUBSTITUTE(SUBSTITUTE(LOWER(D89),"th",""),".","/"),"-","/")),"Check")))) -> 42909 | F89: Lead Consultant | G89: Cloud | H89: FTE | I89: PRJ-017 | L89: =IF(E89="","Missing",YEAR(E89)) -> 2017 | M89: =IF(E89="","Missing","Q"&ROUNDUP(MONTH(E89)/3,0)) -> Q2 | N89: =YEAR(E89)&"-Q"&ROUNDUP(MONTH(E89)/3,0) -> 2017-Q2
A90: EMP088 | B90: ="emp"&TEXT(VALUE(SUBSTITUTE(SUBSTITUTE(UPPER(TRIM(A90)),"EMP",""),"-","")),"000") -> emp088 | C90: Ishita Malhotra | D90: 44624 | E90: =IF(D90="","", IF(ISNUMBER(D90),D90, IFERROR(DATEVALUE(D90), IFERROR(DATEVALUE(SUBSTITUTE(SUBSTITUTE(SUBSTITUTE(LOWER(D90),"th",""),".","/"),"-","/")),"Check")))) -> 44624 | F90: Analyst | G90: PMO | H90: Intern | I90: PRJ-043 | L90: =IF(E90="","Missing",YEAR(E90)) -> 2022 | M90: =IF(E90="","Missing","Q"&ROUNDUP(MONTH(E90)/3,0)) -> Q1 | N90: =YEAR(E90)&"-Q"&ROUNDUP(MONTH(E90)/3,0) -> 2022-Q1
A91: EMP-089 | B91: ="emp"&TEXT(VALUE(SUBSTITUTE(SUBSTITUTE(UPPER(TRIM(A91)),"EMP",""),"-","")),"000") -> emp089 | C91: Saurabh Jain | D91: 43390 | E91: =IF(D91="","", IF(ISNUMBER(D91),D91, IFERROR(DATEVALUE(D91), IFERROR(DATEVALUE(SUBSTITUTE(SUBSTITUTE(SUBSTITUTE(LOWER(D91),"th",""),".","/"),"-","/")),"Check")))) -> 43390 | F91: Consultant | G91: Support | H91: FTE | I91: PRJ-032 | L91: =IF(E91="","Missing",YEAR(E91)) -> 2018 | M91: =IF(E91="","Missing","Q"&ROUNDUP(MONTH(E91)/3,0)) -> Q4 | N91: =YEAR(E91)&"-Q"&ROUNDUP(MONTH(E91)/3,0) -> 2018-Q4
A92: EMP090 | B92: ="emp"&TEXT(VALUE(SUBSTITUTE(SUBSTITUTE(UPPER(TRIM(A92)),"EMP",""),"-","")),"000") -> emp090 | C92: Tanvi Kulkarni | D92: 44024 | E92: =IF(D92="","", IF(ISNUMBER(D92),D92, IFERROR(DATEVALUE(D92), IFERROR(DATEVALUE(SUBSTITUTE(SUBSTITUTE(SUBSTITUTE(LOWER(D92),"th",""),".","/"),"-","/")),"Check")))) -> 44024 | F92: Analyst | G92: Design | H92: FTE | I92: PRJ-029 | L92: =IF(E92="","Missing",YEAR(E92)) -> 2020 | M92: =IF(E92="","Missing","Q"&ROUNDUP(MONTH(E92)/3,0)) -> Q3 | N92: =YEAR(E92)&"-Q"&ROUNDUP(MONTH(E92)/3,0) -> 2020-Q3
A93: emp091 | B93: ="emp"&TEXT(VALUE(SUBSTITUTE(SUBSTITUTE(UPPER(TRIM(A93)),"EMP",""),"-","")),"000") -> emp091 | C93: Keshav Arora | D93: 2016.04.01 | E93: =IF(D93="","", IF(ISNUMBER(D93),D93, IFERROR(DATEVALUE(D93), IFERROR(DATEVALUE(SUBSTITUTE(SUBSTITUTE(SUBSTITUTE(LOWER(D93),"th",""),".","/"),"-","/")),"Check")))) -> 42461 | F93: Consultant | G93: QA | H93: Intern | I93: PRJ-012 | L93: =IF(E93="","Missing",YEAR(E93)) -> 2016 | M93: =IF(E93="","Missing","Q"&ROUNDUP(MONTH(E93)/3,0)) -> Q2 | N93: =YEAR(E93)&"-Q"&ROUNDUP(MONTH(E93)/3,0) -> 2016-Q2
A94: EMP092 | B94: ="emp"&TEXT(VALUE(SUBSTITUTE(SUBSTITUTE(UPPER(TRIM(A94)),"EMP",""),"-","")),"000") -> emp092 | C94: Monica Bansal | D94: 43510 | E94: =IF(D94="","", IF(ISNUMBER(D94),D94, IFERROR(DATEVALUE(D94), IFERROR(DATEVALUE(SUBSTITUTE(SUBSTITUTE(SUBSTITUTE(LOWER(D94),"th",""),".","/"),"-","/")),"Check")))) -> 43510 | F94: Consultant | G94: Cloud | H94: FTE | I94: PRJ-027 | J94: PRJ-077 | L94: =IF(E94="","Missing",YEAR(E94)) -> 2019 | M94: =IF(E94="","Missing","Q"&ROUNDUP(MONTH(E94)/3,0)) -> Q1 | N94: =YEAR(E94)&"-Q"&ROUNDUP(MONTH(E94)/3,0) -> 2019-Q1
A95: EMP 093 | B95: ="emp"&TEXT(VALUE(SUBSTITUTE(SUBSTITUTE(UPPER(TRIM(A95)),"EMP",""),"-","")),"000") -> emp093 | C95: Rajat Khurana | D95: 42973 | E95: =IF(D95="","", IF(ISNUMBER(D95),D95, IFERROR(DATEVALUE(D95), IFERROR(DATEVALUE(SUBSTITUTE(SUBSTITUTE(SUBSTITUTE(LOWER(D95),"th",""),".","/"),"-","/")),"Check")))) -> 42973 | F95: Sr Consultant | G95: PMO | H95: FTE | I95: PRJ-019 | J95: PRJ-066 | L95: =IF(E95="","Missing",YEAR(E95)) -> 2017 | M95: =IF(E95="","Missing","Q"&ROUNDUP(MONTH(E95)/3,0)) -> Q3 | N95: =YEAR(E95)&"-Q"&ROUNDUP(MONTH(E95)/3,0) -> 2017-Q3
A96: EMP-094 | B96: ="emp"&TEXT(VALUE(SUBSTITUTE(SUBSTITUTE(UPPER(TRIM(A96)),"EMP",""),"-","")),"000") -> emp094 | C96: Naina Sethi | D96: 44506 | E96: =IF(D96="","", IF(ISNUMBER(D96),D96, IFERROR(DATEVALUE(D96), IFERROR(DATEVALUE(SUBSTITUTE(SUBSTITUTE(SUBSTITUTE(LOWER(D96),"th",""),".","/"),"-","/")),"Check")))) -> 44506 | F96: Analyst | G96: Support | H96: FTE | I96: PRJ-024 | J96: PRJ-083 | L96: =IF(E96="","Missing",YEAR(E96)) -> 2021 | M96: =IF(E96="","Missing","Q"&ROUNDUP(MONTH(E96)/3,0)) -> Q4 | N96: =YEAR(E96)&"-Q"&ROUNDUP(MONTH(E96)/3,0) -> 2021-Q4
A97: EMP095 | B97: ="emp"&TEXT(VALUE(SUBSTITUTE(SUBSTITUTE(UPPER(TRIM(A97)),"EMP",""),"-","")),"000") -> emp095 | C97: Ashwin Iyer | D97: 43269 | E97: =IF(D97="","", IF(ISNUMBER(D97),D97, IFERROR(DATEVALUE(D97), IFERROR(DATEVALUE(SUBSTITUTE(SUBSTITUTE(SUBSTITUTE(LOWER(D97),"th",""),".","/"),"-","/")),"Check")))) -> 43269 | F97: Lead Consultant | G97: QA | H97: FTE | I97: PRJ-022 | J97: PRJ-090 | L97: =IF(E97="","Missing",YEAR(E97)) -> 2018 | M97: =IF(E97="","Missing","Q"&ROUNDUP(MONTH(E97)/3,0)) -> Q2 | N97: =YEAR(E97)&"-Q"&ROUNDUP(MONTH(E97)/3,0) -> 2018-Q2
A98: emp096 | B98: ="emp"&TEXT(VALUE(SUBSTITUTE(SUBSTITUTE(UPPER(TRIM(A98)),"EMP",""),"-","")),"000") -> emp096 | C98: Preeti Goyal | D98: 43870 | E98: =IF(D98="","", IF(ISNUMBER(D98),D98, IFERROR(DATEVALUE(D98), IFERROR(DATEVALUE(SUBSTITUTE(SUBSTITUTE(SUBSTITUTE(LOWER(D98),"th",""),".","/"),"-","/")),"Check")))) -> 43870 | F98: Consultant | G98: Design | H98: FTE | I98: PRJ-045 | J98: PRJ-063 | L98: =IF(E98="","Missing",YEAR(E98)) -> 2020 | M98: =IF(E98="","Missing","Q"&ROUNDUP(MONTH(E98)/3,0)) -> Q1 | N98: =YEAR(E98)&"-Q"&ROUNDUP(MONTH(E98)/3,0) -> 2020-Q1
A99: EMP-097 | B99: ="emp"&TEXT(VALUE(SUBSTITUTE(SUBSTITUTE(UPPER(TRIM(A99)),"EMP",""),"-","")),"000") -> emp097 | C99: Lakshya Jain | D99: 42643 | E99: =IF(D99="","", IF(ISNUMBER(D99),D99, IFERROR(DATEVALUE(D99), IFERROR(DATEVALUE(SUBSTITUTE(SUBSTITUTE(SUBSTITUTE(LOWER(D99),"th",""),".","/"),"-","/")),"Check")))) -> 42643 | F99: Consultant | G99: Cloud | H99: Intern | I99: PRJ-037 | L99: =IF(E99="","Missing",YEAR(E99)) -> 2016 | M99: =IF(E99="","Missing","Q"&ROUNDUP(MONTH(E99)/3,0)) -> Q3 | N99: =YEAR(E99)&"-Q"&ROUNDUP(MONTH(E99)/3,0) -> 2016-Q3
A100: EMP098 | B100: ="emp"&TEXT(VALUE(SUBSTITUTE(SUBSTITUTE(UPPER(TRIM(A100)),"EMP",""),"-","")),"000") -> emp098 | C100: Bhavya Malhotra | D100: 43470 | E100: =IF(D100="","", IF(ISNUMBER(D100),D100, IFERROR(DATEVALUE(D100), IFERROR(DATEVALUE(SUBSTITUTE(SUBSTITUTE(SUBSTITUTE(LOWER(D100),"th",""),".","/"),"-","/")),"Check")))) -> 43470 | F100: Analyst | G100: PMO | H100: Intern | I100: PRJ-038 | L100: =IF(E100="","Missing",YEAR(E100)) -> 2019 | M100: =IF(E100="","Missing","Q"&ROUNDUP(MONTH(E100)/3,0)) -> Q1 | N100: =YEAR(E100)&"-Q"&ROUNDUP(MONTH(E100)/3,0) -> 2019-Q1
...

Sheet Projects
A1: Project ID | B1: Project Name | C1: Start Date | D1: Corrected Start Date | E1: End Date | F1: Corrected End Date | G1: Revised End Date | H1: Final End Date | I1: Duration (>3 months running projects in green) | J1: Project Type Duration Wise | K1: Project Status | L1: Delay
A2: PRJ-001 | B2: Digital Revamp | C2: 45880 | D2: =IF(C2="","", IF(ISNUMBER(C2),C2, IFERROR(DATEVALUE(C2), IFERROR(DATEVALUE(SUBSTITUTE(SUBSTITUTE(C2,"-","/"),",","")),"Check")))) -> 45880 | E2: 46038 | F2: =IF(E2="","", IF(ISNUMBER(E2),E2, IFERROR(DATEVALUE(E2), IFERROR(DATEVALUE(SUBSTITUTE(SUBSTITUTE(E2,"-","/"),",","")),"Check")))) -> 46038 | G2: 46322 | H2: =IF(G2<>"",G2,F2) -> 46322 | I2: =IF(OR(NOT(ISNUMBER(C2)),NOT(ISNUMBER(H2))),"",H2-C2) -> 442 | J2: =IF(I2>90,"Long Project","Normal") -> Long Project | K2: =IF(OR(H2="",NOT(ISNUMBER(H2))), "Planned/In Progress", IF(H2<TODAY(),"Completed","In Progress")) -> In Progress | L2: =IF(OR(NOT(ISNUMBER(F2)),NOT(ISNUMBER(H2))), "Missing", IF(H2<TODAY(), IF(H2>F2,H2-F2,"On Time"), "In Progress")) -> In Progress
A3: PRJ-002 | B3: AI Chatbot Rollout | C3: 45901 | D3: =IF(C3="","", IF(ISNUMBER(C3),C3, IFERROR(DATEVALUE(C3), IFERROR(DATEVALUE(SUBSTITUTE(SUBSTITUTE(C3,"-","/"),",","")),"Check")))) -> 45901 | E3: 46298 | F3: =IF(E3="","", IF(ISNUMBER(E3),E3, IFERROR(DATEVALUE(E3), IFERROR(DATEVALUE(SUBSTITUTE(SUBSTITUTE(E3,"-","/"),",","")),"Check")))) -> 46298 | H3: =IF(G3<>"",G3,F3) -> 46298 | I3: =IF(OR(NOT(ISNUMBER(C3)),NOT(ISNUMBER(H3))),"",H3-C3) -> 397 | J3: =IF(I3>90,"Long Project","Normal") -> Long Project | K3: =IF(OR(H3="",NOT(ISNUMBER(H3))), "Planned/In Progress", IF(H3<TODAY(),"Completed","In Progress")) -> In Progress | L3: =IF(OR(NOT(ISNUMBER(F3)),NOT(ISNUMBER(H3))), "Missing", IF(H3<TODAY(), IF(H3>F3,H3-F3,"On Time"), "In Progress")) -> In Progress
A4: PRJ-003 | B4: Cloud Migration Phase 1 | C4: 45915 | D4: =IF(C4="","", IF(ISNUMBER(C4),C4, IFERROR(DATEVALUE(C4), IFERROR(DATEVALUE(SUBSTITUTE(SUBSTITUTE(C4,"-","/"),",","")),"Check")))) -> 45915 | E4: 46022 | F4: =IF(E4="","", IF(ISNUMBER(E4),E4, IFERROR(DATEVALUE(E4), IFERROR(DATEVALUE(SUBSTITUTE(SUBSTITUTE(E4,"-","/"),",","")),"Check")))) -> 46022 | G4: 46108 | H4: =IF(G4<>"",G4,F4) -> 46108 | I4: =IF(OR(NOT(ISNUMBER(C4)),NOT(ISNUMBER(H4))),"",H4-C4) -> 193 | J4: =IF(I4>90,"Long Project","Normal") -> Long Project | K4: =IF(OR(H4="",NOT(ISNUMBER(H4))), "Planned/In Progress", IF(H4<TODAY(),"Completed","In Progress")) -> Completed | L4: =IF(OR(NOT(ISNUMBER(F4)),NOT(ISNUMBER(H4))), "Missing", IF(H4<TODAY(), IF(H4>F4,H4-F4,"On Time"), "In Progress")) -> 86
A5: PRJ-004 | B5: Data Lake Setup | C5: 46069 | D5: =IF(C5="","", IF(ISNUMBER(C5),C5, IFERROR(DATEVALUE(C5), IFERROR(DATEVALUE(SUBSTITUTE(SUBSTITUTE(C5,"-","/"),",","")),"Check")))) -> 46069 | E5: 46136 | F5: =IF(E5="","", IF(ISNUMBER(E5),E5, IFERROR(DATEVALUE(E5), IFERROR(DATEVALUE(SUBSTITUTE(SUBSTITUTE(E5,"-","/"),",","")),"Check")))) -> 46136 | H5: =IF(G5<>"",G5,F5) -> 46136 | I5: =IF(OR(NOT(ISNUMBER(C5)),NOT(ISNUMBER(H5))),"",H5-C5) -> 67 | J5: =IF(I5>90,"Long Project","Normal") -> Normal | K5: =IF(OR(H5="",NOT(ISNUMBER(H5))), "Planned/In Progress", IF(H5<TODAY(),"Completed","In Progress")) -> In Progress | L5: =IF(OR(NOT(ISNUMBER(F5)),NOT(ISNUMBER(H5))), "Missing", IF(H5<TODAY(), IF(H5>F5,H5-F5,"On Time"), "In Progress")) -> In Progress
A6: PRJ-005 | B6: CRM Enhancement | C6: 45510 | D6: =IF(C6="","", IF(ISNUMBER(C6),C6, IFERROR(DATEVALUE(C6), IFERROR(DATEVALUE(SUBSTITUTE(SUBSTITUTE(C6,"-","/"),",","")),"Check")))) -> 45510 | E6: 46127 | F6: =IF(E6="","", IF(ISNUMBER(E6),E6, IFERROR(DATEVALUE(E6), IFERROR(DATEVALUE(SUBSTITUTE(SUBSTITUTE(E6,"-","/"),",","")),"Check")))) -> 46127 | H6: =IF(G6<>"",G6,F6) -> 46127 | I6: =IF(OR(NOT(ISNUMBER(C6)),NOT(ISNUMBER(H6))),"",H6-C6) -> 617 | J6: =IF(I6>90,"Long Project","Normal") -> Long Project | K6: =IF(OR(H6="",NOT(ISNUMBER(H6))), "Planned/In Progress", IF(H6<TODAY(),"Completed","In Progress")) -> In Progress | L6: =IF(OR(NOT(ISNUMBER(F6)),NOT(ISNUMBER(H6))), "Missing", IF(H6<TODAY(), IF(H6>F6,H6-F6,"On Time"), "In Progress")) -> In Progress
A7: PRJ-006 | B7: Mobile App Redesign | C7: 45748 | D7: =IF(C7="","", IF(ISNUMBER(C7),C7, IFERROR(DATEVALUE(C7), IFERROR(DATEVALUE(SUBSTITUTE(SUBSTITUTE(C7,"-","/"),",","")),"Check")))) -> 45748 | E7: 46387 | F7: =IF(E7="","", IF(ISNUMBER(E7),E7, IFERROR(DATEVALUE(E7), IFERROR(DATEVALUE(SUBSTITUTE(SUBSTITUTE(E7,"-","/"),",","")),"Check")))) -> 46387 | H7: =IF(G7<>"",G7,F7) -> 46387 | I7: =IF(OR(NOT(ISNUMBER(C7)),NOT(ISNUMBER(H7))),"",H7-C7) -> 639 | J7: =IF(I7>90,"Long Project","Normal") -> Long Project | K7: =IF(OR(H7="",NOT(ISNUMBER(H7))), "Planned/In Progress", IF(H7<TODAY(),"Completed","In Progress")) -> In Progress | L7: =IF(OR(NOT(ISNUMBER(F7)),NOT(ISNUMBER(H7))), "Missing", IF(H7<TODAY(), IF(H7>F7,H7-F7,"On Time"), "In Progress")) -> In Progress
A8: PRJ-007 | B8: AI Demand Forecasting | C8: 45458 | D8: =IF(C8="","", IF(ISNUMBER(C8),C8, IFERROR(DATEVALUE(C8), IFERROR(DATEVALUE(SUBSTITUTE(SUBSTITUTE(C8,"-","/"),",","")),"Check")))) -> 45458 | E8: 46265 | F8: =IF(E8="","", IF(ISNUMBER(E8),E8, IFERROR(DATEVALUE(E8), IFERROR(DATEVALUE(SUBSTITUTE(SUBSTITUTE(E8,"-","/"),",","")),"Check")))) -> 46265 | H8: =IF(G8<>"",G8,F8) -> 46265 | I8: =IF(OR(NOT(ISNUMBER(C8)),NOT(ISNUMBER(H8))),"",H8-C8) -> 807 | J8: =IF(I8>90,"Long Project","Normal") -> Long Project | K8: =IF(OR(H8="",NOT(ISNUMBER(H8))), "Planned/In Progress", IF(H8<TODAY(),"Completed","In Progress")) -> In Progress | L8: =IF(OR(NOT(ISNUMBER(F8)),NOT(ISNUMBER(H8))), "Missing", IF(H8<TODAY(), IF(H8>F8,H8-F8,"On Time"), "In Progress")) -> In Progress
A9: PRJ-008 | B9: QA Automation Suite | C9: 45425 | D9: =IF(C9="","", IF(ISNUMBER(C9),C9, IFERROR(DATEVALUE(C9), IFERROR(DATEVALUE(SUBSTITUTE(SUBSTITUTE(C9,"-","/"),",","")),"Check")))) -> 45425 | E9: 46188 | F9: =IF(E9="","", IF(ISNUMBER(E9),E9, IFERROR(DATEVALUE(E9), IFERROR(DATEVALUE(SUBSTITUTE(SUBSTITUTE(E9,"-","/"),",","")),"Check")))) -> 46188 | H9: =IF(G9<>"",G9,F9) -> 46188 | I9: =IF(OR(NOT(ISNUMBER(C9)),NOT(ISNUMBER(H9))),"",H9-C9) -> 763 | J9: =IF(I9>90,"Long Project","Normal") -> Long Project | K9: =IF(OR(H9="",NOT(ISNUMBER(H9))), "Planned/In Progress", IF(H9<TODAY(),"Completed","In Progress")) -> In Progress | L9: =IF(OR(NOT(ISNUMBER(F9)),NOT(ISNUMBER(H9))), "Missing", IF(H9<TODAY(), IF(H9>F9,H9-F9,"On Time"), "In Progress")) -> In Progress
A10: PRJ-009 | B10: Cloud Cost Optimization | C10: 45689 | D10: =IF(C10="","", IF(ISNUMBER(C10),C10, IFERROR(DATEVALUE(C10), IFERROR(DATEVALUE(SUBSTITUTE(SUBSTITUTE(C10,"-","/"),",","")),"Check")))) -> 45689 | E10: 46142 | F10: =IF(E10="","", IF(ISNUMBER(E10),E10, IFERROR(DATEVALUE(E10), IFERROR(DATEVALUE(SUBSTITUTE(SUBSTITUTE(E10,"-","/"),",","")),"Check")))) -> 46142 | H10: =IF(G10<>"",G10,F10) -> 46142 | I10: =IF(OR(NOT(ISNUMBER(C10)),NOT(ISNUMBER(H10))),"",H10-C10) -> 453 | J10: =IF(I10>90,"Long Project","Normal") -> Long Project | K10: =IF(OR(H10="",NOT(ISNUMBER(H10))), "Planned/In Progress", IF(H10<TODAY(),"Completed","In Progress")) -> In Progress | L10: =IF(OR(NOT(ISNUMBER(F10)),NOT(ISNUMBER(H10))), "Missing", IF(H10<TODAY(), IF(H10>F10,H10-F10,"On Time"), "In Progress")) -> In Progress
A11: PRJ-010 | B11: Website Performance Boost | C11: 45847 | D11: =IF(C11="","", IF(ISNUMBER(C11),C11, IFERROR(DATEVALUE(C11), IFERROR(DATEVALUE(SUBSTITUTE(SUBSTITUTE(C11,"-","/"),",","")),"Check")))) -> 45847 | E11: 46249 | F11: =IF(E11="","", IF(ISNUMBER(E11),E11, IFERROR(DATEVALUE(E11), IFERROR(DATEVALUE(SUBSTITUTE(SUBSTITUTE(E11,"-","/"),",","")),"Check")))) -> 46249 | H11: =IF(G11<>"",G11,F11) -> 46249 | I11: =IF(OR(NOT(ISNUMBER(C11)),NOT(ISNUMBER(H11))),"",H11-C11) -> 402 | J11: =IF(I11>90,"Long Project","Normal") -> Long Project | K11: =IF(OR(H11="",NOT(ISNUMBER(H11))), "Planned/In Progress", IF(H11<TODAY(),"Completed","In Progress")) -> In Progress | L11: =IF(OR(NOT(ISNUMBER(F11)),NOT(ISNUMBER(H11))), "Missing", IF(H11<TODAY(), IF(H11>F11,H11-F11,"On Time"), "In Progress")) -> In Progress
A12: PRJ-011 | B12: AI Resume Screener | C12: 45764 | D12: =IF(C12="","", IF(ISNUMBER(C12),C12, IFERROR(DATEVALUE(C12), IFERROR(DATEVALUE(SUBSTITUTE(SUBSTITUTE(C12,"-","/"),",","")),"Check")))) -> 45764 | E12: 46128 | F12: =IF(E12="","", IF(ISNUMBER(E12),E12, IFERROR(DATEVALUE(E12), IFERROR(DATEVALUE(SUBSTITUTE(SUBSTITUTE(E12,"-","/"),",","")),"Check")))) -> 46128 | H12: =IF(G12<>"",G12,F12) -> 46128 | I12: =IF(OR(NOT(ISNUMBER(C12)),NOT(ISNUMBER(H12))),"",H12-C12) -> 364 | J12: =IF(I12>90,"Long Project","Normal") -> Long Project | K12: =IF(OR(H12="",NOT(ISNUMBER(H12))), "Planned/In Progress", IF(H12<TODAY(),"Completed","In Progress")) -> In Progress | L12: =IF(OR(NOT(ISNUMBER(F12)),NOT(ISNUMBER(H12))), "Missing", IF(H12<TODAY(), IF(H12>F12,H12-F12,"On Time"), "In Progress")) -> In Progress
A13: PRJ-012 | B13: Data Quality Program | C13: 45887 | D13: =IF(C13="","", IF(ISNUMBER(C13),C13, IFERROR(DATEVALUE(C13), IFERROR(DATEVALUE(SUBSTITUTE(SUBSTITUTE(C13,"-","/"),",","")),"Check")))) -> 45887 | E13: 46251 | F13: =IF(E13="","", IF(ISNUMBER(E13),E13, IFERROR(DATEVALUE(E13), IFERROR(DATEVALUE(SUBSTITUTE(SUBSTITUTE(E13,"-","/"),",","")),"Check")))) -> 46251 | H13: =IF(G13<>"",G13,F13) -> 46251 | I13: =IF(OR(NOT(ISNUMBER(C13)),NOT(ISNUMBER(H13))),"",H13-C13) -> 364 | J13: =IF(I13>90,"Long Project","Normal") -> Long Project | K13: =IF(OR(H13="",NOT(ISNUMBER(H13))), "Planned/In Progress", IF(H13<TODAY(),"Completed","In Progress")) -> In Progress | L13: =IF(OR(NOT(ISNUMBER(F13)),NOT(ISNUMBER(H13))), "Missing", IF(H13<TODAY(), IF(H13>F13,H13-F13,"On Time"), "In Progress")) -> In Progress
A14: PRJ-013 | B14: PMO Dashboard Revamp | C14: 45880 | D14: =IF(C14="","", IF(ISNUMBER(C14),C14, IFERROR(DATEVALUE(C14), IFERROR(DATEVALUE(SUBSTITUTE(SUBSTITUTE(C14,"-","/"),",","")),"Check")))) -> 45880 | E14: 46290 | F14: =IF(E14="","", IF(ISNUMBER(E14),E14, IFERROR(DATEVALUE(E14), IFERROR(DATEVALUE(SUBSTITUTE(SUBSTITUTE(E14,"-","/"),",","")),"Check")))) -> 46290 | H14: =IF(G14<>"",G14,F14) -> 46290 | I14: =IF(OR(NOT(ISNUMBER(C14)),NOT(ISNUMBER(H14))),"",H14-C14) -> 410 | J14: =IF(I14>90,"Long Project","Normal") -> Long Project | K14: =IF(OR(H14="",NOT(ISNUMBER(H14))), "Planned/In Progress", IF(H14<TODAY(),"Completed","In Progress")) -> In Progress | L14: =IF(OR(NOT(ISNUMBER(F14)),NOT(ISNUMBER(H14))), "Missing", IF(H14<TODAY(), IF(H14>F14,H14-F14,"On Time"), "In Progress")) -> In Progress
A15: PRJ-014 | B15: Support Ticket Analytics | C15: 45887 | D15: =IF(C15="","", IF(ISNUMBER(C15),C15, IFERROR(DATEVALUE(C15), IFERROR(DATEVALUE(SUBSTITUTE(SUBSTITUTE(C15,"-","/"),",","")),"Check")))) -> 45887 | E15: 46332 | F15: =IF(E15="","", IF(ISNUMBER(E15),E15, IFERROR(DATEVALUE(E15), IFERROR(DATEVALUE(SUBSTITUTE(SUBSTITUTE(E15,"-","/"),",","")),"Check")))) -> 46332 | H15: =IF(G15<>"",G15,F15) -> 46332 | I15: =IF(OR(NOT(ISNUMBER(C15)),NOT(ISNUMBER(H15))),"",H15-C15) -> 445 | J15: =IF(I15>90,"Long Project","Normal") -> Long Project | K15: =IF(OR(H15="",NOT(ISNUMBER(H15))), "Planned/In Progress", IF(H15<TODAY(),"Completed","In Progress")) -> In Progress | L15: =IF(OR(NOT(ISNUMBER(F15)),NOT(ISNUMBER(H15))), "Missing", IF(H15<TODAY(), IF(H15>F15,H15-F15,"On Time"), "In Progress")) -> In Progress
A16: PRJ-015 | B16: Digital Marketing Platform | C16: 45887 | D16: =IF(C16="","", IF(ISNUMBER(C16),C16, IFERROR(DATEVALUE(C16), IFERROR(DATEVALUE(SUBSTITUTE(SUBSTITUTE(C16,"-","/"),",","")),"Check")))) -> 45887 | E16: 46297 | F16: =IF(E16="","", IF(ISNUMBER(E16),E16, IFERROR(DATEVALUE(E16), IFERROR(DATEVALUE(SUBSTITUTE(SUBSTITUTE(E16,"-","/"),",","")),"Check")))) -> 46297 | H16: =IF(G16<>"",G16,F16) -> 46297 | I16: =IF(OR(NOT(ISNUMBER(C16)),NOT(ISNUMBER(H16))),"",H16-C16) -> 410 | J16: =IF(I16>90,"Long Project","Normal") -> Long Project | K16: =IF(OR(H16="",NOT(ISNUMBER(H16))), "Planned/In Progress", IF(H16<TODAY(),"Completed","In Progress")) -> In Progress | L16: =IF(OR(NOT(ISNUMBER(F16)),NOT(ISNUMBER(H16))), "Missing", IF(H16<TODAY(), IF(H16>F16,H16-F16,"On Time"), "In Progress")) -> In Progress
... A24: PRJ-023 | B24: Digital Sales Dashboard | C24: 45887 | D24: =IF(C24="","", IF(ISNUMBER(C24),C24, IFERROR(DATEVALUE(C24), IFERROR(DATEVALUE(SUBSTITUTE(SUBSTITUTE(C24,"-","/"),",","")),"Check")))) -> 45887 | E24: 46297 | F24: =IF(E24="","", IF(ISNUMBER(E24),E24, IFERROR(DATEVALUE(E24), IFERROR(DATEVALUE(SUBSTITUTE(SUBSTITUTE(E24,"-","/"),",","")),"Check")))) -> 46297 | H24: =IF(G24<>"",G24,F24) -> 46297 | I24: =IF(OR(NOT(ISNUMBER(C24)),NOT(ISNUMBER(H24))),"",H24-C24) -> 410 | J24: =IF(I24>90,"Long Project","Normal") -> Long Project | K24: =IF(OR(H24="",NOT(ISNUMBER(H24))), "Planned/In Progress", IF(H24<TODAY(),"Completed","In Progress")) -> In Progress | L24: =IF(OR(NOT(ISNUMBER(F24)),NOT(ISNUMBER(H24))), "Missing", IF(H24<TODAY(), IF(H24>F24,H24-F24,"On Time"), "In Progress")) -> In Progress
A25: PRJ-024 | B25: Support Knowledge Base | C25: 45160 | D25: =IF(C25="","", IF(ISNUMBER(C25),C25, IFERROR(DATEVALUE(C25), IFERROR(DATEVALUE(SUBSTITUTE(SUBSTITUTE(C25,"-","/"),",","")),"Check")))) -> 45160 | E25: 45991 | F25: =IF(E25="","", IF(ISNUMBER(E25),E25, IFERROR(DATEVALUE(E25), IFERROR(DATEVALUE(SUBSTITUTE(SUBSTITUTE(E25,"-","/"),",","")),"Check")))) -> 45991 | G25: 46058 | H25: =IF(G25<>"",G25,F25) -> 46058 | I25: =IF(OR(NOT(ISNUMBER(C25)),NOT(ISNUMBER(H25))),"",H25-C25) -> 898 | J25: =IF(I25>90,"Long Project","Normal") -> Long Project | K25: =IF(OR(H25="",NOT(ISNUMBER(H25))), "Planned/In Progress", IF(H25<TODAY(),"Completed","In Progress")) -> Completed | L25: =IF(OR(NOT(ISNUMBER(F25)),NOT(ISNUMBER(H25))), "Missing", IF(H25<TODAY(), IF(H25>F25,H25-F25,"On Time"), "In Progress")) -> 67
A26: PRJ-025 | B26: AI Voice Bot | C26: 45908 | D26: =IF(C26="","", IF(ISNUMBER(C26),C26, IFERROR(DATEVALUE(C26), IFERROR(DATEVALUE(SUBSTITUTE(SUBSTITUTE(C26,"-","/"),",","")),"Check")))) -> 45908 | E26: 46387 | F26: =IF(E26="","", IF(ISNUMBER(E26),E26, IFERROR(DATEVALUE(E26), IFERROR(DATEVALUE(SUBSTITUTE(SUBSTITUTE(E26,"-","/"),",","")),"Check")))) -> 46387 | H26: =IF(G26<>"",G26,F26) -> 46387 | I26: =IF(OR(NOT(ISNUMBER(C26)),NOT(ISNUMBER(H26))),"",H26-C26) -> 479 | J26: =IF(I26>90,"Long Project","Normal") -> Long Project | K26: =IF(OR(H26="",NOT(ISNUMBER(H26))), "Planned/In Progress", IF(H26<TODAY(),"Completed","In Progress")) -> In Progress | L26: =IF(OR(NOT(ISNUMBER(F26)),NOT(ISNUMBER(H26))), "Missing", IF(H26<TODAY(), IF(H26>F26,H26-F26,"On Time"), "In Progress")) -> In Progress
A27: PRJ-026 | B27: Data Governance Setup | C27: 45922 | D27: =IF(C27="","", IF(ISNUMBER(C27),C27, IFERROR(DATEVALUE(C27), IFERROR(DATEVALUE(SUBSTITUTE(SUBSTITUTE(C27,"-","/"),",","")),"Check")))) -> 45922 | E27: 45996 | F27: =IF(E27="","", IF(ISNUMBER(E27),E27, IFERROR(DATEVALUE(E27), IFERROR(DATEVALUE(SUBSTITUTE(SUBSTITUTE(E27,"-","/"),",","")),"Check")))) -> 45996 | G27: 46234 | H27: =IF(G27<>"",G27,F27) -> 46234 | I27: =IF(OR(NOT(ISNUMBER(C27)),NOT(ISNUMBER(H27))),"",H27-C27) -> 312 | J27: =IF(I27>90,"Long Project","Normal") -> Long Project | K27: =IF(OR(H27="",NOT(ISNUMBER(H27))), "Planned/In Progress", IF(H27<TODAY(),"Completed","In Progress")) -> In Progress | L27: =IF(OR(NOT(ISNUMBER(F27)),NOT(ISNUMBER(H27))), "Missing", IF(H27<TODAY(), IF(H27>F27,H27-F27,"On Time"), "In Progress")) -> In Progress
A28: PRJ-027 | B28: Cloud App Modernization | C28: 45981 | D28: =IF(C28="","", IF(ISNUMBER(C28),C28, IFERROR(DATEVALUE(C28), IFERROR(DATEVALUE(SUBSTITUTE(SUBSTITUTE(C28,"-","/"),",","")),"Check")))) -> 45981 | E28: 46203 | F28: =IF(E28="","", IF(ISNUMBER(E28),E28, IFERROR(DATEVALUE(E28), IFERROR(DATEVALUE(SUBSTITUTE(SUBSTITUTE(E28,"-","/"),",","")),"Check")))) -> 46203 | H28: =IF(G28<>"",G28,F28) -> 46203 | I28: =IF(OR(NOT(ISNUMBER(C28)),NOT(ISNUMBER(H28))),"",H28-C28) -> 222 | J28: =IF(I28>90,"Long Project","Normal") -> Long Project | K28: =IF(OR(H28="",NOT(ISNUMBER(H28))), "Planned/In Progress", IF(H28<TODAY(),"Completed","In Progress")) -> In Progress | L28: =IF(OR(NOT(ISNUMBER(F28)),NOT(ISNUMBER(H28))), "Missing", IF(H28<TODAY(), IF(H28>F28,H28-F28,"On Time"), "In Progress")) -> In Progress
A29: PRJ-028 | B29: QA Metrics Dashboard | C29: 45931 | D29: =IF(C29="","", IF(ISNUMBER(C29),C29, IFERROR(DATEVALUE(C29), IFERROR(DATEVALUE(SUBSTITUTE(SUBSTITUTE(C29,"-","/"),",","")),"Check")))) -> 45931 | E29: 46023 | F29: =IF(E29="","", IF(ISNUMBER(E29),E29, IFERROR(DATEVALUE(E29), IFERROR(DATEVALUE(SUBSTITUTE(SUBSTITUTE(E29,"-","/"),",","")),"Check")))) -> 46023 | G29: 46080 | H29: =IF(G29<>"",G29,F29) -> 46080 | I29: =IF(OR(NOT(ISNUMBER(C29)),NOT(ISNUMBER(H29))),"",H29-C29) -> 149 | J29: =IF(I29>90,"Long Project","Normal") -> Long Project | K29: =IF(OR(H29="",NOT(ISNUMBER(H29))), "Planned/In Progress", IF(H29<TODAY(),"Completed","In Progress")) -> Completed | L29: =IF(OR(NOT(ISNUMBER(F29)),NOT(ISNUMBER(H29))), "Missing", IF(H29<TODAY(), IF(H29>F29,H29-F29,"On Time"), "In Progress")) -> 57
A30: PRJ-029 | B30: Digital Onboarding Flow | C30: 46030 | D30: =IF(C30="","", IF(ISNUMBER(C30),C30, IFERROR(DATEVALUE(C30), IFERROR(DATEVALUE(SUBSTITUTE(SUBSTITUTE(C30,"-","/"),",","")),"Check")))) -> 46030 | E30: 46115 | F30: =IF(E30="","", IF(ISNUMBER(E30),E30, IFERROR(DATEVALUE(E30), IFERROR(DATEVALUE(SUBSTITUTE(SUBSTITUTE(E30,"-","/"),",","")),"Check")))) -> 46115 | G30: 46136 | H30: =IF(G30<>"",G30,F30) -> 46136 | I30: =IF(OR(NOT(ISNUMBER(C30)),NOT(ISNUMBER(H30))),"",H30-C30) -> 106 | J30: =IF(I30>90,"Long Project","Normal") -> Long Project | K30: =IF(OR(H30="",NOT(ISNUMBER(H30))), "Planned/In Progress", IF(H30<TODAY(),"Completed","In Progress")) -> In Progress | L30: =IF(OR(NOT(ISNUMBER(F30)),NOT(ISNUMBER(H30))), "Missing", IF(H30<TODAY(), IF(H30>F30,H30-F30,"On Time"), "In Progress")) -> In Progress
A31: PRJ-030 | B31: AI Chat Analytics | C31: 45908 | D31: =IF(C31="","", IF(ISNUMBER(C31),C31, IFERROR(DATEVALUE(C31), IFERROR(DATEVALUE(SUBSTITUTE(SUBSTITUTE(C31,"-","/"),",","")),"Check")))) -> 45908 | E31: 46022 | F31: =IF(E31="","", IF(ISNUMBER(E31),E31, IFERROR(DATEVALUE(E31), IFERROR(DATEVALUE(SUBSTITUTE(SUBSTITUTE(E31,"-","/"),",","")),"Check")))) -> 46022 | G31: 46066 | H31: =IF(G31<>"",G31,F31) -> 46066 | I31: =IF(OR(NOT(ISNUMBER(C31)),NOT(ISNUMBER(H31))),"",H31-C31) -> 158 | J31: =IF(I31>90,"Long Project","Normal") -> Long Project | K31: =IF(OR(H31="",NOT(ISNUMBER(H31))), "Planned/In Progress", IF(H31<TODAY(),"Completed","In Progress")) -> Completed | L31: =IF(OR(NOT(ISNUMBER(F31)),NOT(ISNUMBER(H31))), "Missing", IF(H31<TODAY(), IF(H31>F31,H31-F31,"On Time"), "In Progress")) -> 44
A32: PRJ-031 | B32: Support Automation | C32: 45748 | D32: =IF(C32="","", IF(ISNUMBER(C32),C32, IFERROR(DATEVALUE(C32), IFERROR(DATEVALUE(SUBSTITUTE(SUBSTITUTE(C32,"-","/"),",","")),"Check")))) -> 45748 | E32: 45838 | F32: =IF(E32="","", IF(ISNUMBER(E32),E32, IFERROR(DATEVALUE(E32), IFERROR(DATEVALUE(SUBSTITUTE(SUBSTITUTE(E32,"-","/"),",","")),"Check")))) -> 45838 | H32: =IF(G32<>"",G32,F32) -> 45838 | I32: =IF(OR(NOT(ISNUMBER(C32)),NOT(ISNUMBER(H32))),"",H32-C32) -> 90 | J32: =IF(I32>90,"Long Project","Normal") -> Normal | K32: =IF(OR(H32="",NOT(ISNUMBER(H32))), "Planned/In Progress", IF(H32<TODAY(),"Completed","In Progress")) -> Completed | L32: =IF(OR(NOT(ISNUMBER(F32)),NOT(ISNUMBER(H32))), "Missing", IF(H32<TODAY(), IF(H32>F32,H32-F32,"On Time"), "In Progress")) -> On Time
A33: PRJ-032 | B33: Cloud Monitoring Setup | C33: 45748 | D33: =IF(C33="","", IF(ISNUMBER(C33),C33, IFERROR(DATEVALUE(C33), IFERROR(DATEVALUE(SUBSTITUTE(SUBSTITUTE(C33,"-","/"),",","")),"Check")))) -> 45748 | E33: 46265 | F33: =IF(E33="","", IF(ISNUMBER(E33),E33, IFERROR(DATEVALUE(E33), IFERROR(DATEVALUE(SUBSTITUTE(SUBSTITUTE(E33,"-","/"),",","")),"Check")))) -> 46265 | H33: =IF(G33<>"",G33,F33) -> 46265 | I33: =IF(OR(NOT(ISNUMBER(C33)),NOT(ISNUMBER(H33))),"",H33-C33) -> 517 | J33: =IF(I33>90,"Long Project","Normal") -> Long Project | K33: =IF(OR(H33="",NOT(ISNUMBER(H33))), "Planned/In Progress", IF(H33<TODAY(),"Completed","In Progress")) -> In Progress | L33: =IF(OR(NOT(ISNUMBER(F33)),NOT(ISNUMBER(H33))), "Missing", IF(H33<TODAY(), IF(H33>F33,H33-F33,"On Time"), "In Progress")) -> In Progress
A34: PRJ-033 | B34: Data Reporting Factory | C34: 45748 | D34: =IF(C34="","", IF(ISNUMBER(C34),C34, IFERROR(DATEVALUE(C34), IFERROR(DATEVALUE(SUBSTITUTE(SUBSTITUTE(C34,"-","/"),",","")),"Check")))) -> 45748 | E34: 46276 | F34: =IF(E34="","", IF(ISNUMBER(E34),E34, IFERROR(DATEVALUE(E34), IFERROR(DATEVALUE(SUBSTITUTE(SUBSTITUTE(E34,"-","/"),",","")),"Check")))) -> 46276 | H34: =IF(G34<>"",G34,F34) -> 46276 | I34: =IF(OR(NOT(ISNUMBER(C34)),NOT(ISNUMBER(H34))),"",H34-C34) -> 528 | J34: =IF(I34>90,"Long Project","Normal") -> Long Project | K34: =IF(OR(H34="",NOT(ISNUMBER(H34))), "Planned/In Progress", IF(H34<TODAY(),"Completed","In Progress")) -> In Progress | L34: =IF(OR(NOT(ISNUMBER(F34)),NOT(ISNUMBER(H34))), "Missing", IF(H34<TODAY(), IF(H34>F34,H34-F34,"On Time"), "In Progress")) -> In Progress
A35: PRJ-034 | B35: Digital UX Cleanup | C35: 45748 | D35: =IF(C35="","", IF(ISNUMBER(C35),C35, IFERROR(DATEVALUE(C35), IFERROR(DATEVALUE(SUBSTITUTE(SUBSTITUTE(C35,"-","/"),",","")),"Check")))) -> 45748 | E35: 46112 | F35: =IF(E35="","", IF(ISNUMBER(E35),E35, IFERROR(DATEVALUE(E35), IFERROR(DATEVALUE(SUBSTITUTE(SUBSTITUTE(E35,"-","/"),",","")),"Check")))) -> 46112 | H35: =IF(G35<>"",G35,F35) -> 46112 | I35: =IF(OR(NOT(ISNUMBER(C35)),NOT(ISNUMBER(H35))),"",H35-C35) -> 364 | J35: =IF(I35>90,"Long Project","Normal") -> Long Project | K35: =IF(OR(H35="",NOT(ISNUMBER(H35))), "Planned/In Progress", IF(H35<TODAY(),"Completed","In Progress")) -> Completed | L35: =IF(OR(NOT(ISNUMBER(F35)),NOT(ISNUMBER(H35))), "Missing", IF(H35<TODAY(), IF(H35>F35,H35-F35,"On Time"), "In Progress")) -> On Time
A36: PRJ-035 | B36: QA Regression Automation | C36: 45748 | D36: =IF(C36="","", IF(ISNUMBER(C36),C36, IFERROR(DATEVALUE(C36), IFERROR(DATEVALUE(SUBSTITUTE(SUBSTITUTE(C36,"-","/"),",","")),"Check")))) -> 45748 | E36: 46170 | F36: =IF(E36="","", IF(ISNUMBER(E36),E36, IFERROR(DATEVALUE(E36), IFERROR(DATEVALUE(SUBSTITUTE(SUBSTITUTE(E36,"-","/"),",","")),"Check")))) -> 46170 | H36: =IF(G36<>"",G36,F36) -> 46170 | I36: =IF(OR(NOT(ISNUMBER(C36)),NOT(ISNUMBER(H36))),"",H36-C36) -> 422 | J36: =IF(I36>90,"Long Project","Normal") -> Long Project | K36: =IF(OR(H36="",NOT(ISNUMBER(H36))), "Planned/In Progress", IF(H36<TODAY(),"Completed","In Progress")) -> In Progress | L36: =IF(OR(NOT(ISNUMBER(F36)),NOT(ISNUMBER(H36))), "Missing", IF(H36<TODAY(), IF(H36>F36,H36-F36,"On Time"), "In Progress")) -> In Progress
A37: PRJ-036 | B37: AI Model Retraining | C37: 45748 | D37: =IF(C37="","", IF(ISNUMBER(C37),C37, IFERROR(DATEVALUE(C37), IFERROR(DATEVALUE(SUBSTITUTE(SUBSTITUTE(C37,"-","/"),",","")),"Check")))) -> 45748 | E37: 46324 | F37: =IF(E37="","", IF(ISNUMBER(E37),E37, IFERROR(DATEVALUE(E37), IFERROR(DATEVALUE(SUBSTITUTE(SUBSTITUTE(E37,"-","/"),",","")),"Check")))) -> 46324 | H37: =IF(G37<>"",G37,F37) -> 46324 | I37: =IF(OR(NOT(ISNUMBER(C37)),NOT(ISNUMBER(H37))),"",H37-C37) -> 576 | J37: =IF(I37>90,"Long Project","Normal") -> Long Project | K37: =IF(OR(H37="",NOT(ISNUMBER(H37))), "Planned/In Progress", IF(H37<TODAY(),"Completed","In Progress")) -> In Progress | L37: =IF(OR(NOT(ISNUMBER(F37)),NOT(ISNUMBER(H37))), "Missing", IF(H37<TODAY(), IF(H37>F37,H37-F37,"On Time"), "In Progress")) -> In Progress
A38: PRJ-037 | B38: Cloud Infra Audit | C38: 45748 | D38: =IF(C38="","", IF(ISNUMBER(C38),C38, IFERROR(DATEVALUE(C38), IFERROR(DATEVALUE(SUBSTITUTE(SUBSTITUTE(C38,"-","/"),",","")),"Check")))) -> 45748 | E38: 46387 | F38: =IF(E38="","", IF(ISNUMBER(E38),E38, IFERROR(DATEVALUE(E38), IFERROR(DATEVALUE(SUBSTITUTE(SUBSTITUTE(E38,"-","/"),",","")),"Check")))) -> 46387 | H38: =IF(G38<>"",G38,F38) -> 46387 | I38: =IF(OR(NOT(ISNUMBER(C38)),NOT(ISNUMBER(H38))),"",H38-C38) -> 639 | J38: =IF(I38>90,"Long Project","Normal") -> Long Project | K38: =IF(OR(H38="",NOT(ISNUMBER(H38))), "Planned/In Progress", IF(H38<TODAY(),"Completed","In Progress")) -> In Progress | L38: =IF(OR(NOT(ISNUMBER(F38)),NOT(ISNUMBER(H38))), "Missing", IF(H38<TODAY(), IF(H38>F38,H38-F38,"On Time"), "In Progress")) -> In Progress
A39: PRJ-038 | B39: Support SLA Tracker | C39: 45936 | D39: =IF(C39="","", IF(ISNUMBER(C39),C39, IFERROR(DATEVALUE(C39), IFERROR(DATEVALUE(SUBSTITUTE(SUBSTITUTE(C39,"-","/"),",","")),"Check")))) -> 45936 | E39: 46038 | F39: =IF(E39="","", IF(ISNUMBER(E39),E39, IFERROR(DATEVALUE(E39), IFERROR(DATEVALUE(SUBSTITUTE(SUBSTITUTE(E39,"-","/"),",","")),"Check")))) -> 46038 | H39: =IF(G39<>"",G39,F39) -> 46038 | I39: =IF(OR(NOT(ISNUMBER(C39)),NOT(ISNUMBER(H39))),"",H39-C39) -> 102 | J39: =IF(I39>90,"Long Project","Normal") -> Long Project | K39: =IF(OR(H39="",NOT(ISNUMBER(H39))), "Planned/In Progress", IF(H39<TODAY(),"Completed","In Progress")) -> Completed | L39: =IF(OR(NOT(ISNUMBER(F39)),NOT(ISNUMBER(H39))), "Missing", IF(H39<TODAY(), IF(H39>F39,H39-F39,"On Time"), "In Progress")) -> On Time
A40: PRJ-039 | B40: Data Cost Optimization | C40: 45929 | D40: =IF(C40="","", IF(ISNUMBER(C40),C40, IFERROR(DATEVALUE(C40), IFERROR(DATEVALUE(SUBSTITUTE(SUBSTITUTE(C40,"-","/"),",","")),"Check")))) -> 45929 | E40: 46310 | F40: =IF(E40="","", IF(ISNUMBER(E40),E40, IFERROR(DATEVALUE(E40), IFERROR(DATEVALUE(SUBSTITUTE(SUBSTITUTE(E40,"-","/"),",","")),"Check")))) -> 46310 | H40: =IF(G40<>"",G40,F40) -> 46310 | I40: =IF(OR(NOT(ISNUMBER(C40)),NOT(ISNUMBER(H40))),"",H40-C40) -> 381 | J40: =IF(I40>90,"Long Project","Normal") -> Long Project | K40: =IF(OR(H40="",NOT(ISNUMBER(H40))), "Planned/In Progress", IF(H40<TODAY(),"Completed","In Progress")) -> In Progress | L40: =IF(OR(NOT(ISNUMBER(F40)),NOT(ISNUMBER(H40))), "Missing", IF(H40<TODAY(), IF(H40>F40,H40-F40,"On Time"), "In Progress")) -> In Progress
A41: PRJ-040 | B41: Digital Campaign Tracker | C41: 45929 | D41: =IF(C41="","", IF(ISNUMBER(C41),C41, IFERROR(DATEVALUE(C41), IFERROR(DATEVALUE(SUBSTITUTE(SUBSTITUTE(C41,"-","/"),",","")),"Check")))) -> 45929 | E41: 46387 | F41: =IF(E41="","", IF(ISNUMBER(E41),E41, IFERROR(DATEVALUE(E41), IFERROR(DATEVALUE(SUBSTITUTE(SUBSTITUTE(E41,"-","/"),",","")),"Check")))) -> 46387 | H41: =IF(G41<>"",G41,F41) -> 46387 | I41: =IF(OR(NOT(ISNUMBER(C41)),NOT(ISNUMBER(H41))),"",H41-C41) -> 458 | J41: =IF(I41>90,"Long Project","Normal") -> Long Project | K41: =IF(OR(H41="",NOT(ISNUMBER(H41))), "Planned/In Progress", IF(H41<TODAY(),"Completed","In Progress")) -> In Progress | L41: =IF(OR(NOT(ISNUMBER(F41)),NOT(ISNUMBER(H41))), "Missing", IF(H41<TODAY(), IF(H41>F41,H41-F41,"On Time"), "In Progress")) -> In Progress
A42: PRJ-041 | B42: AI Knowledge Assistant | C42: 45929 | D42: =IF(C42="","", IF(ISNUMBER(C42),C42, IFERROR(DATEVALUE(C42), IFERROR(DATEVALUE(SUBSTITUTE(SUBSTITUTE(C42,"-","/"),",","")),"Check")))) -> 45929 | E42: 46387 | F42: =IF(E42="","", IF(ISNUMBER(E42),E42, IFERROR(DATEVALUE(E42), IFERROR(DATEVALUE(SUBSTITUTE(SUBSTITUTE(E42,"-","/"),",","")),"Check")))) -> 46387 | H42: =IF(G42<>"",G42,F42) -> 46387 | I42: =IF(OR(NOT(ISNUMBER(C42)),NOT(ISNUMBER(H42))),"",H42-C42) -> 458 | J42: =IF(I42>90,"Long Project","Normal") -> Long Project | K42: =IF(OR(H42="",NOT(ISNUMBER(H42))), "Planned/In Progress", IF(H42<TODAY(),"Completed","In Progress")) -> In Progress | L42: =IF(OR(NOT(ISNUMBER(F42)),NOT(ISNUMBER(H42))), "Missing", IF(H42<TODAY(), IF(H42>F42,H42-F42,"On Time"), "In Progress")) -> In Progress
A43: PRJ-042 | B43: QA Tool Evaluation | C43: 45915 | D43: =IF(C43="","", IF(ISNUMBER(C43),C43, IFERROR(DATEVALUE(C43), IFERROR(DATEVALUE(SUBSTITUTE(SUBSTITUTE(C43,"-","/"),",","")),"Check")))) -> 45915 | E43: 46081 | F43: =IF(E43="","", IF(ISNUMBER(E43),E43, IFERROR(DATEVALUE(E43), IFERROR(DATEVALUE(SUBSTITUTE(SUBSTITUTE(E43,"-","/"),",","")),"Check")))) -> 46081 | H43: =IF(G43<>"",G43,F43) -> 46081 | I43: =IF(OR(NOT(ISNUMBER(C43)),NOT(ISNUMBER(H43))),"",H43-C43) -> 166 | J43: =IF(I43>90,"Long Project","Normal") -> Long Project | K43: =IF(OR(H43="",NOT(ISNUMBER(H43))), "Planned/In Progress", IF(H43<TODAY(),"Completed","In Progress")) -> Completed | L43: =IF(OR(NOT(ISNUMBER(F43)),NOT(ISNUMBER(H43))), "Missing", IF(H43<TODAY(), IF(H43>F43,H43-F43,"On Time"), "In Progress")) -> On Time
... A47: PRJ-046 | B47: AI Testing Framework | C47: 46076 | D47: =IF(C47="","", IF(ISNUMBER(C47),C47, IFERROR(DATEVALUE(C47), IFERROR(DATEVALUE(SUBSTITUTE(SUBSTITUTE(C47,"-","/"),",","")),"Check")))) -> 46076 | E47: 46234 | F47: =IF(E47="","", IF(ISNUMBER(E47),E47, IFERROR(DATEVALUE(E47), IFERROR(DATEVALUE(SUBSTITUTE(SUBSTITUTE(E47,"-","/"),",","")),"Check")))) -> 46234 | H47: =IF(G47<>"",G47,F47) -> 46234 | I47: =IF(OR(NOT(ISNUMBER(C47)),NOT(ISNUMBER(H47))),"",H47-C47) -> 158 | J47: =IF(I47>90,"Long Project","Normal") -> Long Project | K47: =IF(OR(H47="",NOT(ISNUMBER(H47))), "Planned/In Progress", IF(H47<TODAY(),"Completed","In Progress")) -> In Progress | L47: =IF(OR(NOT(ISNUMBER(F47)),NOT(ISNUMBER(H47))), "Missing", IF(H47<TODAY(), IF(H47>F47,H47-F47,"On Time"), "In Progress")) -> In Progress
A48: PRJ-047 | B48: Support Load Analysis | C48: 45950 | D48: =IF(C48="","", IF(ISNUMBER(C48),C48, IFERROR(DATEVALUE(C48), IFERROR(DATEVALUE(SUBSTITUTE(SUBSTITUTE(C48,"-","/"),",","")),"Check")))) -> 45950 | E48: 46038 | F48: =IF(E48="","", IF(ISNUMBER(E48),E48, IFERROR(DATEVALUE(E48), IFERROR(DATEVALUE(SUBSTITUTE(SUBSTITUTE(E48,"-","/"),",","")),"Check")))) -> 46038 | G48: 46059 | H48: =IF(G48<>"",G48,F48) -> 46059 | I48: =IF(OR(NOT(ISNUMBER(C48)),NOT(ISNUMBER(H48))),"",H48-C48) -> 109 | J48: =IF(I48>90,"Long Project","Normal") -> Long Project | K48: =IF(OR(H48="",NOT(ISNUMBER(H48))), "Planned/In Progress", IF(H48<TODAY(),"Completed","In Progress")) -> Completed | L48: =IF(OR(NOT(ISNUMBER(F48)),NOT(ISNUMBER(H48))), "Missing", IF(H48<TODAY(), IF(H48>F48,H48-F48,"On Time"), "In Progress")) -> 21
A49: PRJ-048 | B49: Cloud Backup Automation | C49: 46023 | D49: =IF(C49="","", IF(ISNUMBER(C49),C49, IFERROR(DATEVALUE(C49), IFERROR(DATEVALUE(SUBSTITUTE(SUBSTITUTE(C49,"-","/"),",","")),"Check")))) -> 46023 | E49: 46171 | F49: =IF(E49="","", IF(ISNUMBER(E49),E49, IFERROR(DATEVALUE(E49), IFERROR(DATEVALUE(SUBSTITUTE(SUBSTITUTE(E49,"-","/"),",","")),"Check")))) -> 46171 | H49: =IF(G49<>"",G49,F49) -> 46171 | I49: =IF(OR(NOT(ISNUMBER(C49)),NOT(ISNUMBER(H49))),"",H49-C49) -> 148 | J49: =IF(I49>90,"Long Project","Normal") -> Long Project | K49: =IF(OR(H49="",NOT(ISNUMBER(H49))), "Planned/In Progress", IF(H49<TODAY(),"Completed","In Progress")) -> In Progress | L49: =IF(OR(NOT(ISNUMBER(F49)),NOT(ISNUMBER(H49))), "Missing", IF(H49<TODAY(), IF(H49>F49,H49-F49,"On Time"), "In Progress")) -> In Progress
A50: PRJ-049 | B50: Data Visualization Revamp | C50: 45912 | D50: =IF(C50="","", IF(ISNUMBER(C50),C50, IFERROR(DATEVALUE(C50), IFERROR(DATEVALUE(SUBSTITUTE(SUBSTITUTE(C50,"-","/"),",","")),"Check")))) -> 45912 | E50: 46326 | F50: =IF(E50="","", IF(ISNUMBER(E50),E50, IFERROR(DATEVALUE(E50), IFERROR(DATEVALUE(SUBSTITUTE(SUBSTITUTE(E50,"-","/"),",","")),"Check")))) -> 46326 | H50: =IF(G50<>"",G50,F50) -> 46326 | I50: =IF(OR(NOT(ISNUMBER(C50)),NOT(ISNUMBER(H50))),"",H50-C50) -> 414 | J50: =IF(I50>90,"Long Project","Normal") -> Long Project | K50: =IF(OR(H50="",NOT(ISNUMBER(H50))), "Planned/In Progress", IF(H50<TODAY(),"Completed","In Progress")) -> In Progress | L50: =IF(OR(NOT(ISNUMBER(F50)),NOT(ISNUMBER(H50))), "Missing", IF(H50<TODAY(), IF(H50>F50,H50-F50,"On Time"), "In Progress")) -> In Progress
A51: PRJ-050 | B51: Digital Workflow Automation | C51: 45945 | D51: =IF(C51="","", IF(ISNUMBER(C51),C51, IFERROR(DATEVALUE(C51), IFERROR(DATEVALUE(SUBSTITUTE(SUBSTITUTE(C51,"-","/"),",","")),"Check")))) -> 45945 | E51: 46365 | F51: =IF(E51="","", IF(ISNUMBER(E51),E51, IFERROR(DATEVALUE(E51), IFERROR(DATEVALUE(SUBSTITUTE(SUBSTITUTE(E51,"-","/"),",","")),"Check")))) -> 46365 | G51: 46037 | H51: =IF(G51<>"",G51,F51) -> 46037 | I51: =IF(OR(NOT(ISNUMBER(C51)),NOT(ISNUMBER(H51))),"",H51-C51) -> 92 | J51: =IF(I51>90,"Long Project","Normal") -> Long Project | K51: =IF(OR(H51="",NOT(ISNUMBER(H51))), "Planned/In Progress", IF(H51<TODAY(),"Completed","In Progress")) -> Completed | L51: =IF(OR(NOT(ISNUMBER(F51)),NOT(ISNUMBER(H51))), "Missing", IF(H51<TODAY(), IF(H51>F51,H51-F51,"On Time"), "In Progress")) -> On Time
A52: PRJ-051 | B52: AI Document Analyzer | C52: 45931 | D52: =IF(C52="","", IF(ISNUMBER(C52),C52, IFERROR(DATEVALUE(C52), IFERROR(DATEVALUE(SUBSTITUTE(SUBSTITUTE(C52,"-","/"),",","")),"Check")))) -> 45931 | E52: 46022 | F52: =IF(E52="","", IF(ISNUMBER(E52),E52, IFERROR(DATEVALUE(E52), IFERROR(DATEVALUE(SUBSTITUTE(SUBSTITUTE(E52,"-","/"),",","")),"Check")))) -> 46022 | G52: 46112 | H52: =IF(G52<>"",G52,F52) -> 46112 | I52: =IF(OR(NOT(ISNUMBER(C52)),NOT(ISNUMBER(H52))),"",H52-C52) -> 181 | J52: =IF(I52>90,"Long Project","Normal") -> Long Project | K52: =IF(OR(H52="",NOT(ISNUMBER(H52))), "Planned/In Progress", IF(H52<TODAY(),"Completed","In Progress")) -> Completed | L52: =IF(OR(NOT(ISNUMBER(F52)),NOT(ISNUMBER(H52))), "Missing", IF(H52<TODAY(), IF(H52>F52,H52-F52,"On Time"), "In Progress")) -> 90
A53: PRJ-052 | B53: Cloud Access Review | C53: 45963 | D53: =IF(C53="","", IF(ISNUMBER(C53),C53, IFERROR(DATEVALUE(C53), IFERROR(DATEVALUE(SUBSTITUTE(SUBSTITUTE(C53,"-","/"),",","")),"Check")))) -> 45963 | E53: 46129 | F53: =IF(E53="","", IF(ISNUMBER(E53),E53, IFERROR(DATEVALUE(E53), IFERROR(DATEVALUE(SUBSTITUTE(SUBSTITUTE(E53,"-","/"),",","")),"Check")))) -> 46129 | H53: =IF(G53<>"",G53,F53) -> 46129 | I53: =IF(OR(NOT(ISNUMBER(C53)),NOT(ISNUMBER(H53))),"",H53-C53) -> 166 | J53: =IF(I53>90,"Long Project","Normal") -> Long Project | K53: =IF(OR(H53="",NOT(ISNUMBER(H53))), "Planned/In Progress", IF(H53<TODAY(),"Completed","In Progress")) -> In Progress | L53: =IF(OR(NOT(ISNUMBER(F53)),NOT(ISNUMBER(H53))), "Missing", IF(H53<TODAY(), IF(H53>F53,H53-F53,"On Time"), "In Progress")) -> In Progress
A54: PRJ-053 | B54: Digital Funnel Optimization | C54: 45793 | D54: =IF(C54="","", IF(ISNUMBER(C54),C54, IFERROR(DATEVALUE(C54), IFERROR(DATEVALUE(SUBSTITUTE(SUBSTITUTE(C54,"-","/"),",","")),"Check")))) -> 45793 | E54: 46242 | F54: =IF(E54="","", IF(ISNUMBER(E54),E54, IFERROR(DATEVALUE(E54), IFERROR(DATEVALUE(SUBSTITUTE(SUBSTITUTE(E54,"-","/"),",","")),"Check")))) -> 46242 | H54: =IF(G54<>"",G54,F54) -> 46242 | I54: =IF(OR(NOT(ISNUMBER(C54)),NOT(ISNUMBER(H54))),"",H54-C54) -> 449 | J54: =IF(I54>90,"Long Project","Normal") -> Long Project | K54: =IF(OR(H54="",NOT(ISNUMBER(H54))), "Planned/In Progress", IF(H54<TODAY(),"Completed","In Progress")) -> In Progress | L54: =IF(OR(NOT(ISNUMBER(F54)),NOT(ISNUMBER(H54))), "Missing", IF(H54<TODAY(), IF(H54>F54,H54-F54,"On Time"), "In Progress")) -> In Progress
A55: PRJ-054 | B55: QA Tool Migration | C55: 45793 | D55: =IF(C55="","", IF(ISNUMBER(C55),C55, IFERROR(DATEVALUE(C55), IFERROR(DATEVALUE(SUBSTITUTE(SUBSTITUTE(C55,"-","/"),",","")),"Check")))) -> 45793 | E55: 46172 | F55: =IF(E55="","", IF(ISNUMBER(E55),E55, IFERROR(DATEVALUE(E55), IFERROR(DATEVALUE(SUBSTITUTE(SUBSTITUTE(E55,"-","/"),",","")),"Check")))) -> 46172 | H55: =IF(G55<>"",G55,F55) -> 46172 | I55: =IF(OR(NOT(ISNUMBER(C55)),NOT(ISNUMBER(H55))),"",H55-C55) -> 379 | J55: =IF(I55>90,"Long Project","Normal") -> Long Project | K55: =IF(OR(H55="",NOT(ISNUMBER(H55))), "Planned/In Progress", IF(H55<TODAY(),"Completed","In Progress")) -> In Progress | L55: =IF(OR(NOT(ISNUMBER(F55)),NOT(ISNUMBER(H55))), "Missing", IF(H55<TODAY(), IF(H55>F55,H55-F55,"On Time"), "In Progress")) -> In Progress
A56: PRJ-055 | B56: Data Pipeline Stabilization | C56: 45824 | D56: =IF(C56="","", IF(ISNUMBER(C56),C56, IFERROR(DATEVALUE(C56), IFERROR(DATEVALUE(SUBSTITUTE(SUBSTITUTE(C56,"-","/"),",","")),"Check")))) -> 45824 | E56: 46291 | F56: =IF(E56="","", IF(ISNUMBER(E56),E56, IFERROR(DATEVALUE(E56), IFERROR(DATEVALUE(SUBSTITUTE(SUBSTITUTE(E56,"-","/"),",","")),"Check")))) -> 46291 | H56: =IF(G56<>"",G56,F56) -> 46291 | I56: =IF(OR(NOT(ISNUMBER(C56)),NOT(ISNUMBER(H56))),"",H56-C56) -> 467 | J56: =IF(I56>90,"Long Project","Normal") -> Long Project | K56: =IF(OR(H56="",NOT(ISNUMBER(H56))), "Planned/In Progress", IF(H56<TODAY(),"Completed","In Progress")) -> In Progress | L56: =IF(OR(NOT(ISNUMBER(F56)),NOT(ISNUMBER(H56))), "Missing", IF(H56<TODAY(), IF(H56>F56,H56-F56,"On Time"), "In Progress")) -> In Progress
A57: PRJ-056 | B57: AI Knowledge Search | C57: 45847 | D57: =IF(C57="","", IF(ISNUMBER(C57),C57, IFERROR(DATEVALUE(C57), IFERROR(DATEVALUE(SUBSTITUTE(SUBSTITUTE(C57,"-","/"),",","")),"Check")))) -> 45847 | E57: 46290 | F57: =IF(E57="","", IF(ISNUMBER(E57),E57, IFERROR(DATEVALUE(E57), IFERROR(DATEVALUE(SUBSTITUTE(SUBSTITUTE(E57,"-","/"),",","")),"Check")))) -> 46290 | H57: =IF(G57<>"",G57,F57) -> 46290 | I57: =IF(OR(NOT(ISNUMBER(C57)),NOT(ISNUMBER(H57))),"",H57-C57) -> 443 | J57: =IF(I57>90,"Long Project","Normal") -> Long Project | K57: =IF(OR(H57="",NOT(ISNUMBER(H57))), "Planned/In Progress", IF(H57<TODAY(),"Completed","In Progress")) -> In Progress | L57: =IF(OR(NOT(ISNUMBER(F57)),NOT(ISNUMBER(H57))), "Missing", IF(H57<TODAY(), IF(H57>F57,H57-F57,"On Time"), "In Progress")) -> In Progress
A58: PRJ-057 | B58: Cloud Log Monitoring | C58: 45842 | D58: =IF(C58="","", IF(ISNUMBER(C58),C58, IFERROR(DATEVALUE(C58), IFERROR(DATEVALUE(SUBSTITUTE(SUBSTITUTE(C58,"-","/"),",","")),"Check")))) -> 45842 | E58: 46251 | F58: =IF(E58="","", IF(ISNUMBER(E58),E58, IFERROR(DATEVALUE(E58), IFERROR(DATEVALUE(SUBSTITUTE(SUBSTITUTE(E58,"-","/"),",","")),"Check")))) -> 46251 | H58: =IF(G58<>"",G58,F58) -> 46251 | I58: =IF(OR(NOT(ISNUMBER(C58)),NOT(ISNUMBER(H58))),"",H58-C58) -> 409 | J58: =IF(I58>90,"Long Project","Normal") -> Long Project | K58: =IF(OR(H58="",NOT(ISNUMBER(H58))), "Planned/In Progress", IF(H58<TODAY(),"Completed","In Progress")) -> In Progress | L58: =IF(OR(NOT(ISNUMBER(F58)),NOT(ISNUMBER(H58))), "Missing", IF(H58<TODAY(), IF(H58>F58,H58-F58,"On Time"), "In Progress")) -> In Progress
A59: PRJ-058 | B59: Digital Asset Cleanup | C59: 45839 | D59: =IF(C59="","", IF(ISNUMBER(C59),C59, IFERROR(DATEVALUE(C59), IFERROR(DATEVALUE(SUBSTITUTE(SUBSTITUTE(C59,"-","/"),",","")),"Check")))) -> 45839 | E59: 46234 | F59: =IF(E59="","", IF(ISNUMBER(E59),E59, IFERROR(DATEVALUE(E59), IFERROR(DATEVALUE(SUBSTITUTE(SUBSTITUTE(E59,"-","/"),",","")),"Check")))) -> 46234 | H59: =IF(G59<>"",G59,F59) -> 46234 | I59: =IF(OR(NOT(ISNUMBER(C59)),NOT(ISNUMBER(H59))),"",H59-C59) -> 395 | J59: =IF(I59>90,"Long Project","Normal") -> Long Project | K59: =IF(OR(H59="",NOT(ISNUMBER(H59))), "Planned/In Progress", IF(H59<TODAY(),"Completed","In Progress")) -> In Progress | L59: =IF(OR(NOT(ISNUMBER(F59)),NOT(ISNUMBER(H59))), "Missing", IF(H59<TODAY(), IF(H59>F59,H59-F59,"On Time"), "In Progress")) -> In Progress
A60: PRJ-059 | B60: QA Automation Expansion | C60: 45810 | D60: =IF(C60="","", IF(ISNUMBER(C60),C60, IFERROR(DATEVALUE(C60), IFERROR(DATEVALUE(SUBSTITUTE(SUBSTITUTE(C60,"-","/"),",","")),"Check")))) -> 45810 | E60: 46224 | F60: =IF(E60="","", IF(ISNUMBER(E60),E60, IFERROR(DATEVALUE(E60), IFERROR(DATEVALUE(SUBSTITUTE(SUBSTITUTE(E60,"-","/"),",","")),"Check")))) -> 46224 | H60: =IF(G60<>"",G60,F60) -> 46224 | I60: =IF(OR(NOT(ISNUMBER(C60)),NOT(ISNUMBER(H60))),"",H60-C60) -> 414 | J60: =IF(I60>90,"Long Project","Normal") -> Long Project | K60: =IF(OR(H60="",NOT(ISNUMBER(H60))), "Planned/In Progress", IF(H60<TODAY(),"Completed","In Progress")) -> In Progress | L60: =IF(OR(NOT(ISNUMBER(F60)),NOT(ISNUMBER(H60))), "Missing", IF(H60<TODAY(), IF(H60>F60,H60-F60,"On Time"), "In Progress")) -> In Progress
A61: PRJ-060 | B61: AI Lead Scoring | C61: 45748 | D61: =IF(C61="","", IF(ISNUMBER(C61),C61, IFERROR(DATEVALUE(C61), IFERROR(DATEVALUE(SUBSTITUTE(SUBSTITUTE(C61,"-","/"),",","")),"Check")))) -> 45748 | E61: 46387 | F61: =IF(E61="","", IF(ISNUMBER(E61),E61, IFERROR(DATEVALUE(E61), IFERROR(DATEVALUE(SUBSTITUTE(SUBSTITUTE(E61,"-","/"),",","")),"Check")))) -> 46387 | H61: =IF(G61<>"",G61,F61) -> 46387 | I61: =IF(OR(NOT(ISNUMBER(C61)),NOT(ISNUMBER(H61))),"",H61-C61) -> 639 | J61: =IF(I61>90,"Long Project","Normal") -> Long Project | K61: =IF(OR(H61="",NOT(ISNUMBER(H61))), "Planned/In Progress", IF(H61<TODAY(),"Completed","In Progress")) -> In Progress | L61: =IF(OR(NOT(ISNUMBER(F61)),NOT(ISNUMBER(H61))), "Missing", IF(H61<TODAY(), IF(H61>F61,H61-F61,"On Time"), "In Progress")) -> In Progress
A62: PRJ-061 | B62: Data Mastering Program | C62: 45748 | D62: =IF(C62="","", IF(ISNUMBER(C62),C62, IFERROR(DATEVALUE(C62), IFERROR(DATEVALUE(SUBSTITUTE(SUBSTITUTE(C62,"-","/"),",","")),"Check")))) -> 45748 | E62: 46387 | F62: =IF(E62="","", IF(ISNUMBER(E62),E62, IFERROR(DATEVALUE(E62), IFERROR(DATEVALUE(SUBSTITUTE(SUBSTITUTE(E62,"-","/"),",","")),"Check")))) -> 46387 | H62: =IF(G62<>"",G62,F62) -> 46387 | I62: =IF(OR(NOT(ISNUMBER(C62)),NOT(ISNUMBER(H62))),"",H62-C62) -> 639 | J62: =IF(I62>90,"Long Project","Normal") -> Long Project | K62: =IF(OR(H62="",NOT(ISNUMBER(H62))), "Planned/In Progress", IF(H62<TODAY(),"Completed","In Progress")) -> In Progress | L62: =IF(OR(NOT(ISNUMBER(F62)),NOT(ISNUMBER(H62))), "Missing", IF(H62<TODAY(), IF(H62>F62,H62-F62,"On Time"), "In Progress")) -> In Progress
A63: PRJ-062 | B63: Cloud Patch Management | C63: 46049 | D63: =IF(C63="","", IF(ISNUMBER(C63),C63, IFERROR(DATEVALUE(C63), IFERROR(DATEVALUE(SUBSTITUTE(SUBSTITUTE(C63,"-","/"),",","")),"Check")))) -> 46049 | E63: 46136 | F63: =IF(E63="","", IF(ISNUMBER(E63),E63, IFERROR(DATEVALUE(E63), IFERROR(DATEVALUE(SUBSTITUTE(SUBSTITUTE(E63,"-","/"),",","")),"Check")))) -> 46136 | H63: =IF(G63<>"",G63,F63) -> 46136 | I63: =IF(OR(NOT(ISNUMBER(C63)),NOT(ISNUMBER(H63))),"",H63-C63) -> 87 | J63: =IF(I63>90,"Long Project","Normal") -> Normal | K63: =IF(OR(H63="",NOT(ISNUMBER(H63))), "Planned/In Progress", IF(H63<TODAY(),"Completed","In Progress")) -> In Progress | L63: =IF(OR(NOT(ISNUMBER(F63)),NOT(ISNUMBER(H63))), "Missing", IF(H63<TODAY(), IF(H63>F63,H63-F63,"On Time"), "In Progress")) -> In Progress
A64: PRJ-063 | B64: Digital Payment Journey | C64: 46028 | D64: =IF(C64="","", IF(ISNUMBER(C64),C64, IFERROR(DATEVALUE(C64), IFERROR(DATEVALUE(SUBSTITUTE(SUBSTITUTE(C64,"-","/"),",","")),"Check")))) -> 46028 | E64: 46077 | F64: =IF(E64="","", IF(ISNUMBER(E64),E64, IFERROR(DATEVALUE(E64), IFERROR(DATEVALUE(SUBSTITUTE(SUBSTITUTE(E64,"-","/"),",","")),"Check")))) -> 46077 | H64: =IF(G64<>"",G64,F64) -> 46077 | I64: =IF(OR(NOT(ISNUMBER(C64)),NOT(ISNUMBER(H64))),"",H64-C64) -> 49 | J64: =IF(I64>90,"Long Project","Normal") -> Normal | K64: =IF(OR(H64="",NOT(ISNUMBER(H64))), "Planned/In Progress", IF(H64<TODAY(),"Completed","In Progress")) -> Completed | L64: =IF(OR(NOT(ISNUMBER(F64)),NOT(ISNUMBER(H64))), "Missing", IF(H64<TODAY(), IF(H64>F64,H64-F64,"On Time"), "In Progress")) -> On Time
A65: PRJ-064 | B65: QA Performance Metrics | C65: 45839 | D65: =IF(C65="","", IF(ISNUMBER(C65),C65, IFERROR(DATEVALUE(C65), IFERROR(DATEVALUE(SUBSTITUTE(SUBSTITUTE(C65,"-","/"),",","")),"Check")))) -> 45839 | E65: 46387 | F65: =IF(E65="","", IF(ISNUMBER(E65),E65, IFERROR(DATEVALUE(E65), IFERROR(DATEVALUE(SUBSTITUTE(SUBSTITUTE(E65,"-","/"),",","")),"Check")))) -> 46387 | G65: 46059 | H65: =IF(G65<>"",G65,F65) -> 46059 | I65: =IF(OR(NOT(ISNUMBER(C65)),NOT(ISNUMBER(H65))),"",H65-C65) -> 220 | J65: =IF(I65>90,"Long Project","Normal") -> Long Project | K65: =IF(OR(H65="",NOT(ISNUMBER(H65))), "Planned/In Progress", IF(H65<TODAY(),"Completed","In Progress")) -> Completed | L65: =IF(OR(NOT(ISNUMBER(F65)),NOT(ISNUMBER(H65))), "Missing", IF(H65<TODAY(), IF(H65>F65,H65-F65,"On Time"), "In Progress")) -> On Time
A66: PRJ-065 | B66: AI Risk Scoring Model | C66: 46083 | D66: =IF(C66="","", IF(ISNUMBER(C66),C66, IFERROR(DATEVALUE(C66), IFERROR(DATEVALUE(SUBSTITUTE(SUBSTITUTE(C66,"-","/"),",","")),"Check")))) -> 46083 | E66: TBD | F66: TBD | H66: =IF(G66<>"",G66,F66) -> TBD | I66: =IF(OR(NOT(ISNUMBER(C66)),NOT(ISNUMBER(H66))),"",H66-C66) | J66: In Progress | K66: =IF(OR(H66="",NOT(ISNUMBER(H66))), "Planned/In Progress", IF(H66<TODAY(),"Completed","In Progress")) -> Planned/In Progress | L66: =IF(OR(NOT(ISNUMBER(F66)),NOT(ISNUMBER(H66))), "Missing", IF(H66<TODAY(), IF(H66>F66,H66-F66,"On Time"), "In Progress")) -> Missing
A67: PRJ-066 | B67: Cloud Capacity Planning | C67: 46076 | D67: =IF(C67="","", IF(ISNUMBER(C67),C67, IFERROR(DATEVALUE(C67), IFERROR(DATEVALUE(SUBSTITUTE(SUBSTITUTE(C67,"-","/"),",","")),"Check")))) -> 46076 | E67: TBD | F67: TBD | H67: =IF(G67<>"",G67,F67) -> TBD | I67: =IF(OR(NOT(ISNUMBER(C67)),NOT(ISNUMBER(H67))),"",H67-C67) | J67: In Progress | K67: =IF(OR(H67="",NOT(ISNUMBER(H67))), "Planned/In Progress", IF(H67<TODAY(),"Completed","In Progress")) -> Planned/In Progress | L67: =IF(OR(NOT(ISNUMBER(F67)),NOT(ISNUMBER(H67))), "Missing", IF(H67<TODAY(), IF(H67>F67,H67-F67,"On Time"), "In Progress")) -> Missing
A68: PRJ-067 | B68: Data Reporting Cleanup | C68: 46069 | D68: =IF(C68="","", IF(ISNUMBER(C68),C68, IFERROR(DATEVALUE(C68), IFERROR(DATEVALUE(SUBSTITUTE(SUBSTITUTE(C68,"-","/"),",","")),"Check")))) -> 46069 | E68: 46094 | F68: =IF(E68="","", IF(ISNUMBER(E68),E68, IFERROR(DATEVALUE(E68), IFERROR(DATEVALUE(SUBSTITUTE(SUBSTITUTE(E68,"-","/"),",","")),"Check")))) -> 46094 | H68: =IF(G68<>"",G68,F68) -> 46094 | I68: =IF(OR(NOT(ISNUMBER(C68)),NOT(ISNUMBER(H68))),"",H68-C68) -> 25 | J68: =IF(I68>90,"Long Project","Normal") -> Normal | K68: =IF(OR(H68="",NOT(ISNUMBER(H68))), "Planned/In Progress", IF(H68<TODAY(),"Completed","In Progress")) -> Completed | L68: =IF(OR(NOT(ISNUMBER(F68)),NOT(ISNUMBER(H68))), "Missing", IF(H68<TODAY(), IF(H68>F68,H68-F68,"On Time"), "In Progress")) -> On Time
A69: PRJ-068 | B69: Digital SEO Revamp | C69: 46083 | D69: =IF(C69="","", IF(ISNUMBER(C69),C69, IFERROR(DATEVALUE(C69), IFERROR(DATEVALUE(SUBSTITUTE(SUBSTITUTE(C69,"-","/"),",","")),"Check")))) -> 46083 | E69: 46122 | F69: =IF(E69="","", IF(ISNUMBER(E69),E69, IFERROR(DATEVALUE(E69), IFERROR(DATEVALUE(SUBSTITUTE(SUBSTITUTE(E69,"-","/"),",","")),"Check")))) -> 46122 | H69: =IF(G69<>"",G69,F69) -> 46122 | I69: =IF(OR(NOT(ISNUMBER(C69)),NOT(ISNUMBER(H69))),"",H69-C69) -> 39 | J69: =IF(I69>90,"Long Project","Normal") -> Normal | K69: =IF(OR(H69="",NOT(ISNUMBER(H69))), "Planned/In Progress", IF(H69<TODAY(),"Completed","In Progress")) -> Completed | L69: =IF(OR(NOT(ISNUMBER(F69)),NOT(ISNUMBER(H69))), "Missing", IF(H69<TODAY(), IF(H69>F69,H69-F69,"On Time"), "In Progress")) -> On Time
A70: PRJ-069 | B70: QA Defect Analytics | C70: 45580 | D70: =IF(C70="","", IF(ISNUMBER(C70),C70, IFERROR(DATEVALUE(C70), IFERROR(DATEVALUE(SUBSTITUTE(SUBSTITUTE(C70,"-","/"),",","")),"Check")))) -> 45580 | E70: 46234 | F70: =IF(E70="","", IF(ISNUMBER(E70),E70, IFERROR(DATEVALUE(E70), IFERROR(DATEVALUE(SUBSTITUTE(SUBSTITUTE(E70,"-","/"),",","")),"Check")))) -> 46234 | H70: =IF(G70<>"",G70,F70) -> 46234 | I70: =IF(OR(NOT(ISNUMBER(C70)),NOT(ISNUMBER(H70))),"",H70-C70) -> 654 | J70: =IF(I70>90,"Long Project","Normal") -> Long Project | K70: =IF(OR(H70="",NOT(ISNUMBER(H70))), "Planned/In Progress", IF(H70<TODAY(),"Completed","In Progress")) -> In Progress | L70: =IF(OR(NOT(ISNUMBER(F70)),NOT(ISNUMBER(H70))), "Missing", IF(H70<TODAY(), IF(H70>F70,H70-F70,"On Time"), "In Progress")) -> In Progress
A71: PRJ-070 | B71: AI Chatbot Enhancement | C71: 45910 | D71: =IF(C71="","", IF(ISNUMBER(C71),C71, IFERROR(DATEVALUE(C71), IFERROR(DATEVALUE(SUBSTITUTE(SUBSTITUTE(C71,"-","/"),",","")),"Check")))) -> 45910 | E71: 46022 | F71: =IF(E71="","", IF(ISNUMBER(E71),E71, IFERROR(DATEVALUE(E71), IFERROR(DATEVALUE(SUBSTITUTE(SUBSTITUTE(E71,"-","/"),",","")),"Check")))) -> 46022 | G71: 46112 | H71: =IF(G71<>"",G71,F71) -> 46112 | I71: =IF(OR(NOT(ISNUMBER(C71)),NOT(ISNUMBER(H71))),"",H71-C71) -> 202 | J71: =IF(I71>90,"Long Project","Normal") -> Long Project | K71: =IF(OR(H71="",NOT(ISNUMBER(H71))), "Planned/In Progress", IF(H71<TODAY(),"Completed","In Progress")) -> Completed | L71: =IF(OR(NOT(ISNUMBER(F71)),NOT(ISNUMBER(H71))), "Missing", IF(H71<TODAY(), IF(H71>F71,H71-F71,"On Time"), "In Progress")) -> 90
A72: PRJ-071 | B72: Cloud API Gateway Setup | C72: 45686 | D72: =IF(C72="","", IF(ISNUMBER(C72),C72, IFERROR(DATEVALUE(C72), IFERROR(DATEVALUE(SUBSTITUTE(SUBSTITUTE(C72,"-","/"),",","")),"Check")))) -> 45686 | E72: 46249 | F72: =IF(E72="","", IF(ISNUMBER(E72),E72, IFERROR(DATEVALUE(E72), IFERROR(DATEVALUE(SUBSTITUTE(SUBSTITUTE(E72,"-","/"),",","")),"Check")))) -> 46249 | H72: =IF(G72<>"",G72,F72) -> 46249 | I72: =IF(OR(NOT(ISNUMBER(C72)),NOT(ISNUMBER(H72))),"",H72-C72) -> 563 | J72: =IF(I72>90,"Long Project","Normal") -> Long Project | K72: =IF(OR(H72="",NOT(ISNUMBER(H72))), "Planned/In Progress", IF(H72<TODAY(),"Completed","In Progress")) -> In Progress | L72: =IF(OR(NOT(ISNUMBER(F72)),NOT(ISNUMBER(H72))), "Missing", IF(H72<TODAY(), IF(H72>F72,H72-F72,"On Time"), "In Progress")) -> In Progress
A73: PRJ-072 | B73: Support Workflow Automation | C73: 45630 | D73: =IF(C73="","", IF(ISNUMBER(C73),C73, IFERROR(DATEVALUE(C73), IFERROR(DATEVALUE(SUBSTITUTE(SUBSTITUTE(C73,"-","/"),",","")),"Check")))) -> 45630 | E73: 46102 | F73: =IF(E73="","", IF(ISNUMBER(E73),E73, IFERROR(DATEVALUE(E73), IFERROR(DATEVALUE(SUBSTITUTE(SUBSTITUTE(E73,"-","/"),",","")),"Check")))) -> 46102 | H73: =IF(G73<>"",G73,F73) -> 46102 | I73: =IF(OR(NOT(ISNUMBER(C73)),NOT(ISNUMBER(H73))),"",H73-C73) -> 472 | J73: =IF(I73>90,"Long Project","Normal") -> Long Project | K73: =IF(OR(H73="",NOT(ISNUMBER(H73))), "Planned/In Progress", IF(H73<TODAY(),"Completed","In Progress")) -> Completed | L73: =IF(OR(NOT(ISNUMBER(F73)),NOT(ISNUMBER(H73))), "Missing", IF(H73<TODAY(), IF(H73>F73,H73-F73,"On Time"), "In Progress")) -> On Time
A74: PRJ-073 | B74: Data Compliance Audit | C74: 45672 | D74: =IF(C74="","", IF(ISNUMBER(C74),C74, IFERROR(DATEVALUE(C74), IFERROR(DATEVALUE(SUBSTITUTE(SUBSTITUTE(C74,"-","/"),",","")),"Check")))) -> 45672 | E74: 46127 | F74: =IF(E74="","", IF(ISNUMBER(E74),E74, IFERROR(DATEVALUE(E74), IFERROR(DATEVALUE(SUBSTITUTE(SUBSTITUTE(E74,"-","/"),",","")),"Check")))) -> 46127 | H74: =IF(G74<>"",G74,F74) -> 46127 | I74: =IF(OR(NOT(ISNUMBER(C74)),NOT(ISNUMBER(H74))),"",H74-C74) -> 455 | J74: =IF(I74>90,"Long Project","Normal") -> Long Project | K74: =IF(OR(H74="",NOT(ISNUMBER(H74))), "Planned/In Progress", IF(H74<TODAY(),"Completed","In Progress")) -> In Progress | L74: =IF(OR(NOT(ISNUMBER(F74)),NOT(ISNUMBER(H74))), "Missing", IF(H74<TODAY(), IF(H74>F74,H74-F74,"On Time"), "In Progress")) -> In Progress
A75: PRJ-074 | B75: Digital CMS Upgrade | C75: 45915 | D75: =IF(C75="","", IF(ISNUMBER(C75),C75, IFERROR(DATEVALUE(C75), IFERROR(DATEVALUE(SUBSTITUTE(SUBSTITUTE(C75,"-","/"),",","")),"Check")))) -> 45915 | E75: 46354 | F75: =IF(E75="","", IF(ISNUMBER(E75),E75, IFERROR(DATEVALUE(E75), IFERROR(DATEVALUE(SUBSTITUTE(SUBSTITUTE(E75,"-","/"),",","")),"Check")))) -> 46354 | H75: =IF(G75<>"",G75,F75) -> 46354 | I75: =IF(OR(NOT(ISNUMBER(C75)),NOT(ISNUMBER(H75))),"",H75-C75) -> 439 | J75: =IF(I75>90,"Long Project","Normal") -> Long Project | K75: =IF(OR(H75="",NOT(ISNUMBER(H75))), "Planned/In Progress", IF(H75<TODAY(),"Completed","In Progress")) -> In Progress | L75: =IF(OR(NOT(ISNUMBER(F75)),NOT(ISNUMBER(H75))), "Missing", IF(H75<TODAY(), IF(H75>F75,H75-F75,"On Time"), "In Progress")) -> In Progress
A76: PRJ-075 | B76: QA Release Readiness | C76: 45922 | D76: =IF(C76="","", IF(ISNUMBER(C76),C76, IFERROR(DATEVALUE(C76), IFERROR(DATEVALUE(SUBSTITUTE(SUBSTITUTE(C76,"-","/"),",","")),"Check")))) -> 45922 | E76: 46069 | F76: =IF(E76="","", IF(ISNUMBER(E76),E76, IFERROR(DATEVALUE(E76), IFERROR(DATEVALUE(SUBSTITUTE(SUBSTITUTE(E76,"-","/"),",","")),"Check")))) -> 46069 | H76: =IF(G76<>"",G76,F76) -> 46069 | I76: =IF(OR(NOT(ISNUMBER(C76)),NOT(ISNUMBER(H76))),"",H76-C76) -> 147 | J76: =IF(I76>90,"Long Project","Normal") -> Long Project | K76: =IF(OR(H76="",NOT(ISNUMBER(H76))), "Planned/In Progress", IF(H76<TODAY(),"Completed","In Progress")) -> Completed | L76: =IF(OR(NOT(ISNUMBER(F76)),NOT(ISNUMBER(H76))), "Missing", IF(H76<TODAY(), IF(H76>F76,H76-F76,"On Time"), "In Progress")) -> On Time
A77: PRJ-076 | B77: AI Customer Insights | C77: 45663 | D77: =IF(C77="","", IF(ISNUMBER(C77),C77, IFERROR(DATEVALUE(C77), IFERROR(DATEVALUE(SUBSTITUTE(SUBSTITUTE(C77,"-","/"),",","")),"Check")))) -> 45663 | E77: 46387 | F77: =IF(E77="","", IF(ISNUMBER(E77),E77, IFERROR(DATEVALUE(E77), IFERROR(DATEVALUE(SUBSTITUTE(SUBSTITUTE(E77,"-","/"),",","")),"Check")))) -> 46387 | H77: =IF(G77<>"",G77,F77) -> 46387 | I77: =IF(OR(NOT(ISNUMBER(C77)),NOT(ISNUMBER(H77))),"",H77-C77) -> 724 | J77: =IF(I77>90,"Long Project","Normal") -> Long Project | K77: =IF(OR(H77="",NOT(ISNUMBER(H77))), "Planned/In Progress", IF(H77<TODAY(),"Completed","In Progress")) -> In Progress | L77: =IF(OR(NOT(ISNUMBER(F77)),NOT(ISNUMBER(H77))), "Missing", IF(H77<TODAY(), IF(H77>F77,H77-F77,"On Time"), "In Progress")) -> In Progress
A78: PRJ-077 | B78: Cloud Resource Tagging | C78: 45861 | D78: =IF(C78="","", IF(ISNUMBER(C78),C78, IFERROR(DATEVALUE(C78), IFERROR(DATEVALUE(SUBSTITUTE(SUBSTITUTE(C78,"-","/"),",","")),"Check")))) -> 45861 | E78: 46048 | F78: =IF(E78="","", IF(ISNUMBER(E78),E78, IFERROR(DATEVALUE(E78), IFERROR(DATEVALUE(SUBSTITUTE(SUBSTITUTE(E78,"-","/"),",","")),"Check")))) -> 46048 | G78: 46111 | H78: =IF(G78<>"",G78,F78) -> 46111 | I78: =IF(OR(NOT(ISNUMBER(C78)),NOT(ISNUMBER(H78))),"",H78-C78) -> 250 | J78: =IF(I78>90,"Long Project","Normal") -> Long Project | K78: =IF(OR(H78="",NOT(ISNUMBER(H78))), "Planned/In Progress", IF(H78<TODAY(),"Completed","In Progress")) -> Completed | L78: =IF(OR(NOT(ISNUMBER(F78)),NOT(ISNUMBER(H78))), "Missing", IF(H78<TODAY(), IF(H78>F78,H78-F78,"On Time"), "In Progress")) -> 63
A79: PRJ-078 | B79: Support Capacity Analysis | C79: 45895 | D79: =IF(C79="","", IF(ISNUMBER(C79),C79, IFERROR(DATEVALUE(C79), IFERROR(DATEVALUE(SUBSTITUTE(SUBSTITUTE(C79,"-","/"),",","")),"Check")))) -> 45895 | E79: 46354 | F79: =IF(E79="","", IF(ISNUMBER(E79),E79, IFERROR(DATEVALUE(E79), IFERROR(DATEVALUE(SUBSTITUTE(SUBSTITUTE(E79,"-","/"),",","")),"Check")))) -> 46354 | G79: 46038 | H79: =IF(G79<>"",G79,F79) -> 46038 | I79: =IF(OR(NOT(ISNUMBER(C79)),NOT(ISNUMBER(H79))),"",H79-C79) -> 143 | J79: =IF(I79>90,"Long Project","Normal") -> Long Project | K79: =IF(OR(H79="",NOT(ISNUMBER(H79))), "Planned/In Progress", IF(H79<TODAY(),"Completed","In Progress")) -> Completed | L79: =IF(OR(NOT(ISNUMBER(F79)),NOT(ISNUMBER(H79))), "Missing", IF(H79<TODAY(), IF(H79>F79,H79-F79,"On Time"), "In Progress")) -> On Time
A80: PRJ-079 | B80: Data Visualization Standards | C80: 45915 | D80: =IF(C80="","", IF(ISNUMBER(C80),C80, IFERROR(DATEVALUE(C80), IFERROR(DATEVALUE(SUBSTITUTE(SUBSTITUTE(C80,"-","/"),",","")),"Check")))) -> 45915 | E80: 46375 | F80: =IF(E80="","", IF(ISNUMBER(E80),E80, IFERROR(DATEVALUE(E80), IFERROR(DATEVALUE(SUBSTITUTE(SUBSTITUTE(E80,"-","/"),",","")),"Check")))) -> 46375 | H80: =IF(G80<>"",G80,F80) -> 46375 | I80: =IF(OR(NOT(ISNUMBER(C80)),NOT(ISNUMBER(H80))),"",H80-C80) -> 460 | J80: =IF(I80>90,"Long Project","Normal") -> Long Project | K80: =IF(OR(H80="",NOT(ISNUMBER(H80))), "Planned/In Progress", IF(H80<TODAY(),"Completed","In Progress")) -> In Progress | L80: =IF(OR(NOT(ISNUMBER(F80)),NOT(ISNUMBER(H80))), "Missing", IF(H80<TODAY(), IF(H80>F80,H80-F80,"On Time"), "In Progress")) -> In Progress
A81: PRJ-080 | B81: Digital Lead Dashboard | C81: 45820 | D81: =IF(C81="","", IF(ISNUMBER(C81),C81, IFERROR(DATEVALUE(C81), IFERROR(DATEVALUE(SUBSTITUTE(SUBSTITUTE(C81,"-","/"),",","")),"Check")))) -> 45820 | E81: 46249 | F81: =IF(E81="","", IF(ISNUMBER(E81),E81, IFERROR(DATEVALUE(E81), IFERROR(DATEVALUE(SUBSTITUTE(SUBSTITUTE(E81,"-","/"),",","")),"Check")))) -> 46249 | H81: =IF(G81<>"",G81,F81) -> 46249 | I81: =IF(OR(NOT(ISNUMBER(C81)),NOT(ISNUMBER(H81))),"",H81-C81) -> 429 | J81: =IF(I81>90,"Long Project","Normal") -> Long Project | K81: =IF(OR(H81="",NOT(ISNUMBER(H81))), "Planned/In Progress", IF(H81<TODAY(),"Completed","In Progress")) -> In Progress | L81: =IF(OR(NOT(ISNUMBER(F81)),NOT(ISNUMBER(H81))), "Missing", IF(H81<TODAY(), IF(H81>F81,H81-F81,"On Time"), "In Progress")) -> In Progress
A82: PRJ-081 | B82: AI Model Monitoring | C82: 45927 | D82: =IF(C82="","", IF(ISNUMBER(C82),C82, IFERROR(DATEVALUE(C82), IFERROR(DATEVALUE(SUBSTITUTE(SUBSTITUTE(C82,"-","/"),",","")),"Check")))) -> 45927 | E82: 46387 | F82: =IF(E82="","", IF(ISNUMBER(E82),E82, IFERROR(DATEVALUE(E82), IFERROR(DATEVALUE(SUBSTITUTE(SUBSTITUTE(E82,"-","/"),",","")),"Check")))) -> 46387 | G82: 46059 | H82: =IF(G82<>"",G82,F82) -> 46059 | I82: =IF(OR(NOT(ISNUMBER(C82)),NOT(ISNUMBER(H82))),"",H82-C82) -> 132 | J82: =IF(I82>90,"Long Project","Normal") -> Long Project | K82: =IF(OR(H82="",NOT(ISNUMBER(H82))), "Planned/In Progress", IF(H82<TODAY(),"Completed","In Progress")) -> Completed | L82: =IF(OR(NOT(ISNUMBER(F82)),NOT(ISNUMBER(H82))), "Missing", IF(H82<TODAY(), IF(H82>F82,H82-F82,"On Time"), "In Progress")) -> On Time
A83: PRJ-082 | B83: QA Tool Rationalization | C83: 45519 | D83: =IF(C83="","", IF(ISNUMBER(C83),C83, IFERROR(DATEVALUE(C83), IFERROR(DATEVALUE(SUBSTITUTE(SUBSTITUTE(C83,"-","/"),",","")),"Check")))) -> 45519 | E83: TBD | F83: TBD | H83: =IF(G83<>"",G83,F83) -> TBD | I83: =IF(OR(NOT(ISNUMBER(C83)),NOT(ISNUMBER(H83))),"",H83-C83) | J83: In Progress | K83: =IF(OR(H83="",NOT(ISNUMBER(H83))), "Planned/In Progress", IF(H83<TODAY(),"Completed","In Progress")) -> Planned/In Progress | L83: =IF(OR(NOT(ISNUMBER(F83)),NOT(ISNUMBER(H83))), "Missing", IF(H83<TODAY(), IF(H83>F83,H83-F83,"On Time"), "In Progress")) -> Missing
A84: PRJ-083 | B84: Cloud DR Drill | C84: 45748 | D84: =IF(C84="","", IF(ISNUMBER(C84),C84, IFERROR(DATEVALUE(C84), IFERROR(DATEVALUE(SUBSTITUTE(SUBSTITUTE(C84,"-","/"),",","")),"Check")))) -> 45748 | E84: 46326 | F84: =IF(E84="","", IF(ISNUMBER(E84),E84, IFERROR(DATEVALUE(E84), IFERROR(DATEVALUE(SUBSTITUTE(SUBSTITUTE(E84,"-","/"),",","")),"Check")))) -> 46326 | H84: =IF(G84<>"",G84,F84) -> 46326 | I84: =IF(OR(NOT(ISNUMBER(C84)),NOT(ISNUMBER(H84))),"",H84-C84) -> 578 | J84: =IF(I84>90,"Long Project","Normal") -> Long Project | K84: =IF(OR(H84="",NOT(ISNUMBER(H84))), "Planned/In Progress", IF(H84<TODAY(),"Completed","In Progress")) -> In Progress | L84: =IF(OR(NOT(ISNUMBER(F84)),NOT(ISNUMBER(H84))), "Missing", IF(H84<TODAY(), IF(H84>F84,H84-F84,"On Time"), "In Progress")) -> In Progress
A85: PRJ-084 | B85: Digital UX Benchmarking | C85: TBD | D85: TBD | E85: TBD | F85: TBD | H85: =IF(G85<>"",G85,F85) -> TBD | I85: =IF(OR(NOT(ISNUMBER(C85)),NOT(ISNUMBER(H85))),"",H85-C85) | J85: In Progress | K85: =IF(OR(H85="",NOT(ISNUMBER(H85))), "Planned/In Progress", IF(H85<TODAY(),"Completed","In Progress")) -> Planned/In Progress | L85: =IF(OR(NOT(ISNUMBER(F85)),NOT(ISNUMBER(H85))), "Missing", IF(H85<TODAY(), IF(H85>F85,H85-F85,"On Time"), "In Progress")) -> Missing
A86: PRJ-085 | B86: Data Quality Scorecard | C86: 45428 | D86: =IF(C86="","", IF(ISNUMBER(C86),C86, IFERROR(DATEVALUE(C86), IFERROR(DATEVALUE(SUBSTITUTE(SUBSTITUTE(C86,"-","/"),",","")),"Check")))) -> 45428 | E86: 46262 | F86: =IF(E86="","", IF(ISNUMBER(E86),E86, IFERROR(DATEVALUE(E86), IFERROR(DATEVALUE(SUBSTITUTE(SUBSTITUTE(E86,"-","/"),",","")),"Check")))) -> 46262 | H86: =IF(G86<>"",G86,F86) -> 46262 | I86: =IF(OR(NOT(ISNUMBER(C86)),NOT(ISNUMBER(H86))),"",H86-C86) -> 834 | J86: =IF(I86>90,"Long Project","Normal") -> Long Project | K86: =IF(OR(H86="",NOT(ISNUMBER(H86))), "Planned/In Progress", IF(H86<TODAY(),"Completed","In Progress")) -> In Progress | L86: =IF(OR(NOT(ISNUMBER(F86)),NOT(ISNUMBER(H86))), "Missing", IF(H86<TODAY(), IF(H86>F86,H86-F86,"On Time"), "In Progress")) -> In Progress
A87: PRJ-086 | B87: AI Prompt Optimization | C87: TBD | D87: TBD | E87: TBD | F87: TBD | H87: =IF(G87<>"",G87,F87) -> TBD | I87: =IF(OR(NOT(ISNUMBER(C87)),NOT(ISNUMBER(H87))),"",H87-C87) | J87: In Progress | K87: =IF(OR(H87="",NOT(ISNUMBER(H87))), "Planned/In Progress", IF(H87<TODAY(),"Completed","In Progress")) -> Planned/In Progress | L87: =IF(OR(NOT(ISNUMBER(F87)),NOT(ISNUMBER(H87))), "Missing", IF(H87<TODAY(), IF(H87>F87,H87-F87,"On Time"), "In Progress")) -> Missing
A88: PRJ-087 | B88: Cloud FinOps Tracker | C88: 45803 | D88: =IF(C88="","", IF(ISNUMBER(C88),C88, IFERROR(DATEVALUE(C88), IFERROR(DATEVALUE(SUBSTITUTE(SUBSTITUTE(C88,"-","/"),",","")),"Check")))) -> 45803 | E88: 46022 | F88: =IF(E88="","", IF(ISNUMBER(E88),E88, IFERROR(DATEVALUE(E88), IFERROR(DATEVALUE(SUBSTITUTE(SUBSTITUTE(E88,"-","/"),",","")),"Check")))) -> 46022 | G88: 46312 | H88: =IF(G88<>"",G88,F88) -> 46312 | I88: =IF(OR(NOT(ISNUMBER(C88)),NOT(ISNUMBER(H88))),"",H88-C88) -> 509 | J88: =IF(I88>90,"Long Project","Normal") -> Long Project | K88: =IF(OR(H88="",NOT(ISNUMBER(H88))), "Planned/In Progress", IF(H88<TODAY(),"Completed","In Progress")) -> In Progress | L88: =IF(OR(NOT(ISNUMBER(F88)),NOT(ISNUMBER(H88))), "Missing", IF(H88<TODAY(), IF(H88>F88,H88-F88,"On Time"), "In Progress")) -> In Progress
A89: PRJ-088 | B89: Support Chat Analytics | C89: 45741 | D89: =IF(C89="","", IF(ISNUMBER(C89),C89, IFERROR(DATEVALUE(C89), IFERROR(DATEVALUE(SUBSTITUTE(SUBSTITUTE(C89,"-","/"),",","")),"Check")))) -> 45741 | E89: 46186 | F89: =IF(E89="","", IF(ISNUMBER(E89),E89, IFERROR(DATEVALUE(E89), IFERROR(DATEVALUE(SUBSTITUTE(SUBSTITUTE(E89,"-","/"),",","")),"Check")))) -> 46186 | H89: =IF(G89<>"",G89,F89) -> 46186 | I89: =IF(OR(NOT(ISNUMBER(C89)),NOT(ISNUMBER(H89))),"",H89-C89) -> 445 | J89: =IF(I89>90,"Long Project","Normal") -> Long Project | K89: =IF(OR(H89="",NOT(ISNUMBER(H89))), "Planned/In Progress", IF(H89<TODAY(),"Completed","In Progress")) -> In Progress | L89: =IF(OR(NOT(ISNUMBER(F89)),NOT(ISNUMBER(H89))), "Missing", IF(H89<TODAY(), IF(H89>F89,H89-F89,"On Time"), "In Progress")) -> In Progress
A90: PRJ-089 | B90: Digital Conversion Analysis | C90: 45823 | D90: =IF(C90="","", IF(ISNUMBER(C90),C90, IFERROR(DATEVALUE(C90), IFERROR(DATEVALUE(SUBSTITUTE(SUBSTITUTE(C90,"-","/"),",","")),"Check")))) -> 45823 | E90: 46053 | F90: =IF(E90="","", IF(ISNUMBER(E90),E90, IFERROR(DATEVALUE(E90), IFERROR(DATEVALUE(SUBSTITUTE(SUBSTITUTE(E90,"-","/"),",","")),"Check")))) -> 46053 | H90: =IF(G90<>"",G90,F90) -> 46053 | I90: =IF(OR(NOT(ISNUMBER(C90)),NOT(ISNUMBER(H90))),"",H90-C90) -> 230 | J90: =IF(I90>90,"Long Project","Normal") -> Long Project | K90: =IF(OR(H90="",NOT(ISNUMBER(H90))), "Planned/In Progress", IF(H90<TODAY(),"Completed","In Progress")) -> Completed | L90: =IF(OR(NOT(ISNUMBER(F90)),NOT(ISNUMBER(H90))), "Missing", IF(H90<TODAY(), IF(H90>F90,H90-F90,"On Time"), "In Progress")) -> On Time
A91: PRJ-090 | B91: QA Environment Cleanup | C91: 45894 | D91: =IF(C91="","", IF(ISNUMBER(C91),C91, IFERROR(DATEVALUE(C91), IFERROR(DATEVALUE(SUBSTITUTE(SUBSTITUTE(C91,"-","/"),",","")),"Check")))) -> 45894 | E91: 46294 | F91: =IF(E91="","", IF(ISNUMBER(E91),E91, IFERROR(DATEVALUE(E91), IFERROR(DATEVALUE(SUBSTITUTE(SUBSTITUTE(E91,"-","/"),",","")),"Check")))) -> 46294 | H91: =IF(G91<>"",G91,F91) -> 46294 | I91: =IF(OR(NOT(ISNUMBER(C91)),NOT(ISNUMBER(H91))),"",H91-C91) -> 400 | J91: =IF(I91>90,"Long Project","Normal") -> Long Project | K91: =IF(OR(H91="",NOT(ISNUMBER(H91))), "Planned/In Progress", IF(H91<TODAY(),"Completed","In Progress")) -> In Progress | L91: =IF(OR(NOT(ISNUMBER(F91)),NOT(ISNUMBER(H91))), "Missing", IF(H91<TODAY(), IF(H91>F91,H91-F91,"On Time"), "In Progress")) -> In Progress
L93: I calculated project delays by comparing planned and final end dates, incorporating revised timelines and categorizing projects as delayed, on-time, or in-progress.

Sheet Team Structure Analysis 
A3: Count of Employee Name | B3: Column Labels
A4: Row Labels | B4: FTE | C4: Intern | D4: Grand Total
A5: AI | B5: 11 | C5: 6 | D5: 17
A6: Analyst | B6: 1 | C6: 5 | D6: 6
A7: Consultant | B7: 5 | C7: 1 | D7: 6
A8: Lead Consultant | B8: 1 | D8: 1
A9: Principal Consultant | B9: 2 | D9: 2
A10: Sr. Consultant | B10: 2 | D10: 2
A11: Data | B11: 15 | C11: 6 | D11: 21
A12: Analyst | B12: 3 | C12: 6 | D12: 9
A13: Consultant | B13: 3 | D13: 3
A14: Lead Consultant | B14: 4 | D14: 4
A15: Senior Consultant | B15: 1 | D15: 1
A16: Sr Consultant | B16: 1 | D16: 1
A17: Sr. Consultant | B17: 3 | D17: 3
A18: Digital | B18: 12 | C18: 3 | D18: 15
A19: Analyst | C19: 3 | D19: 3
A20: Consultant | B20: 7 | D20: 7
A21: Lead Consultant | B21: 2 | D21: 2
A22: Manager | B22: 1 | D22: 1
A23: Senior Consultant | B23: 2 | D23: 2
A24: Grand Total | B24: 38 | C24: 15 | D24: 53
A27: I created a pivot-based interactive view using slicers to dynamically analyze employee distribution across teams, designations, and employment types.

Sheet Long-Running Projects Identific
A1: Project Type Duration Wise | B1: (All)
A3: Row Labels | B3: Count of Duration (>3 months running projects in green) | D3: I calculated project duration using cleaned start and end dates, incorporating revised timelines where available, and flagged projects exceeding 90 days.
A4: PRJ-001 | B4: 1
A5: PRJ-002 | B5: 1
A6: PRJ-003 | B6: 1
A7: PRJ-004 | B7: 1
A8: PRJ-005 | B8: 1
A9: PRJ-006 | B9: 1
A10: PRJ-007 | B10: 1
A11: PRJ-008 | B11: 1
A12: PRJ-009 | B12: 1
A13: PRJ-010 | B13: 1
A14: PRJ-011 | B14: 1
A15: PRJ-012 | B15: 1
... A94: Grand Total | B94: 90

Sheet Employee Cohort Filtering 
A3: Row Labels | B3: Count of Employee Name
A4: 2015 | B4: 2
A5: Q1 | B5: 1
A6: Q4 | B6: 1
A7: 2016 | B7: 15
A8: Q1 | B8: 3
A9: Q2 | B9: 6
A10: Q3 | B10: 2
A11: Q4 | B11: 4
A12: 2017 | B12: 16
A13: Q1 | B13: 6
A14: Q2 | B14: 5
A15: Q3 | B15: 3
A16: Q4 | B16: 2
A17: 2018 | B17: 14
A18: Q1 | B18: 4
A19: Q2 | B19: 3
A20: Q3 | B20: 3 | E20: I derived Year and Quarter from employee joining dates and built a pivot-based cohort view with slicers for dynamic filtering.
A21: Q4 | B21: 4
A22: 2019 | B22: 19
A23: Q1 | B23: 5
A24: Q2 | B24: 5
A25: Q3 | B25: 3
A26: Q4 | B26: 6
A27: 2020 | B27: 18
A28: Q1 | B28: 7
A29: Q2 | B29: 2
A30: Q3 | B30: 6
A31: Q4 | B31: 3
A32: 2021 | B32: 13
A33: Q1 | B33: 5
A34: Q2 | B34: 2
A35: Q3 | B35: 4
A36: Q4 | B36: 2
A37: 2022 | B37: 14
A38: Q1 | B38: 6
A39: Q2 | B39: 5
A40: Q3 | B40: 2
A41: Q4 | B41: 1
A42: 2023 | B42: 4
A43: Q1 | B43: 2
A44: Q2 | B44: 1
A45: Q4 | B45: 1
A46: 2024 | B46: 4
A47: Q1 | B47: 2
A48: Q4 | B48: 2
A49: 2025 | B49: 8
A50: Q1 | B50: 1
A51: Q4 | B51: 7
A52: Missing | B52: 2
A53: Missing | B53: 2
A54: Grand Total | B54: 129

Sheet Employee–Project Mapping 
A1: Corrected Employee ID | B1: Employee Name | C1: Employee First Working Day | D1: Corrected Employee First Working Day | E1: Designation | F1: Team | G1: Type | H1: Year of Joining Date | I1: Quarter of Joining Date | J1: Quarter & Year of Joining Date | K1: Project Code | L1: Start Date | M1: End Date | N1: Active Project Count | O1: Over Allocation | Q1: Overallocated Employees
A2: emp062 | B2: Tanya Bose | C2: 43810 | D2: 43810 | E2: Consultant | F2: Support | G2: FTE | H2: 2019 | I2: Q4 | J2: 2019-Q4 | K2: PRJ-024 | L2: =_xlfn.XLOOKUP(K2, Projects!$A:$A, Projects!$D:$D) -> 45160 | M2: =_xlfn.XLOOKUP(K2, Projects!$A:$A, Projects!$F:$F) -> 45991 | N2: =COUNTIFS(A:A,A2, L:L,"<="&M2, M:M,">="&L2) -> 2 | O2: =IF(N2>2,"Overallocated","OK") -> OK | Q2: Emp ID | R2: Emp Name
A3: emp094 | B3: Naina Sethi | C3: 44506 | D3: 44506 | E3: Analyst | F3: Support | G3: FTE | H3: 2021 | I3: Q4 | J3: 2021-Q4 | K3: PRJ-024 | L3: =_xlfn.XLOOKUP(K3, Projects!$A:$A, Projects!$D:$D) -> 45160 | M3: =_xlfn.XLOOKUP(K3, Projects!$A:$A, Projects!$F:$F) -> 45991 | N3: =COUNTIFS(A:A,A3, L:L,"<="&M3, M:M,">="&L3) -> 2 | O3: =IF(N3>2,"Overallocated","OK") -> OK | Q3: {=_xlfn.UNIQUE(_xlfn._xlws.FILTER(CHOOSE({1,2}, A2:A200, B2:B200), O2:O200="Overallocated"))} -> emp085 | R3: Manav Kapoor
A4: emp060 | B4: Ritu Agarwal | C4: 44361 | D4: 44361 | E4: Analyst | F4: Design | G4: FTE | H4: 2021 | I4: Q2 | J4: 2021-Q2 | K4: PRJ-018 | L4: =_xlfn.XLOOKUP(K4, Projects!$A:$A, Projects!$D:$D) -> 45407 | M4: =_xlfn.XLOOKUP(K4, Projects!$A:$A, Projects!$F:$F) -> 46081 | N4: =COUNTIFS(A:A,A4, L:L,"<="&M4, M:M,">="&L4) -> 2 | O4: =IF(N4>2,"Overallocated","OK") -> OK | Q4: emp005 | R4: Neha Malhotra
A5: emp078 | B5: Aishwarya Kulkarni | C5: 44733 | D5: 44733 | E5: Analyst | F5: Design | G5: Intern | H5: 2022 | I5: Q2 | J5: 2022-Q2 | K5: PRJ-018 | L5: =_xlfn.XLOOKUP(K5, Projects!$A:$A, Projects!$D:$D) -> 45407 | M5: =_xlfn.XLOOKUP(K5, Projects!$A:$A, Projects!$F:$F) -> 46081 | N5: =COUNTIFS(A:A,A5, L:L,"<="&M5, M:M,">="&L5) -> 1 | O5: =IF(N5>2,"Overallocated","OK") -> OK | Q5: emp063 | R5: Aditya Kapoor
A6: emp074 | B6: Meera Joshi | C6: 44385 | D6: 44385 | E6: Analyst | F6: Support | G6: FTE | H6: 2021 | I6: Q3 | J6: 2021-Q3 | K6: PRJ-008 | L6: =_xlfn.XLOOKUP(K6, Projects!$A:$A, Projects!$D:$D) -> 45425 | M6: =_xlfn.XLOOKUP(K6, Projects!$A:$A, Projects!$F:$F) -> 46188 | N6: =COUNTIFS(A:A,A6, L:L,"<="&M6, M:M,">="&L6) -> 2 | O6: =IF(N6>2,"Overallocated","OK") -> OK | Q6: emp015 | R6: Nitin Arora
A7: emp085 | B7: Manav Kapoor | C7: 42713 | D7: 42713 | E7: Sr Consultant | F7: QA | G7: FTE | H7: 2016 | I7: Q4 | J7: 2016-Q4 | K7: PRJ-008 | L7: =_xlfn.XLOOKUP(K7, Projects!$A:$A, Projects!$D:$D) -> 45425 | M7: =_xlfn.XLOOKUP(K7, Projects!$A:$A, Projects!$F:$F) -> 46188 | N7: =COUNTIFS(A:A,A7, L:L,"<="&M7, M:M,">="&L7) -> 3 | O7: =IF(N7>2,"Overallocated","OK") -> Overallocated | Q7: emp036 | R7: Meenal Kulkarni
A8: emp100 | B8: Juhi Kapoor | C8: 44774 | D8: 44774 | E8: Analyst | F8: QA | G8: Intern | H8: 2022 | I8: Q3 | J8: 2022-Q3 | K8: PRJ-008 | L8: =_xlfn.XLOOKUP(K8, Projects!$A:$A, Projects!$D:$D) -> 45425 | M8: =_xlfn.XLOOKUP(K8, Projects!$A:$A, Projects!$F:$F) -> 46188 | N8: =COUNTIFS(A:A,A8, L:L,"<="&M8, M:M,">="&L8) -> 1 | O8: =IF(N8>2,"Overallocated","OK") -> OK | Q8: emp123 | R8: Srishti Jain
A9: emp005 | B9: Neha Malhotra | C9: 45017 | D9: 45017 | E9: Senior Consultant | F9: Data | G9: FTE | H9: 2023 | I9: Q2 | J9: 2023-Q2 | K9: PRJ-085 | L9: =_xlfn.XLOOKUP(K9, Projects!$A:$A, Projects!$D:$D) -> 45428 | M9: =_xlfn.XLOOKUP(K9, Projects!$A:$A, Projects!$F:$F) -> 46262 | N9: =COUNTIFS(A:A,A9, L:L,"<="&M9, M:M,">="&L9) -> 3 | O9: =IF(N9>2,"Overallocated","OK") -> Overallocated | Q9: emp046 | R9: Neetu Sharma
A10: emp111 | B10: Sakshi Ahuja | C10: 45281 | D10: 45281 | E10: Lead Consultant | F10: Data | G10: FTE | H10: 2023 | I10: Q4 | J10: 2023-Q4 | K10: PRJ-085 | L10: =_xlfn.XLOOKUP(K10, Projects!$A:$A, Projects!$D:$D) -> 45428 | M10: =_xlfn.XLOOKUP(K10, Projects!$A:$A, Projects!$F:$F) -> 46262 | N10: =COUNTIFS(A:A,A10, L:L,"<="&M10, M:M,">="&L10) -> 2 | O10: =IF(N10>2,"Overallocated","OK") -> OK | Q10: emp059 | R10: Kunal Verma
A11: emp003 | B11: Suresh Iyer | C11: 44022 | D11: 44022 | E11: Lead Consultant | F11: AI | G11: FTE | H11: 2020 | I11: Q3 | J11: 2020-Q3 | K11: PRJ-007 | L11: =_xlfn.XLOOKUP(K11, Projects!$A:$A, Projects!$D:$D) -> 45458 | M11: =_xlfn.XLOOKUP(K11, Projects!$A:$A, Projects!$F:$F) -> 46265 | N11: =COUNTIFS(A:A,A11, L:L,"<="&M11, M:M,">="&L11) -> 2 | O11: =IF(N11>2,"Overallocated","OK") -> OK | Q11: emp130 | R11: Priya Ratwani
A12: emp019 | B12: Isha Kapoor | C12: 44123 | D12: 44123 | E12: Consultant | F12: AI | G12: FTE | H12: 2020 | I12: Q4 | J12: 2020-Q4 | K12: PRJ-007 | L12: =_xlfn.XLOOKUP(K12, Projects!$A:$A, Projects!$D:$D) -> 45458 | M12: =_xlfn.XLOOKUP(K12, Projects!$A:$A, Projects!$F:$F) -> 46265 | N12: =COUNTIFS(A:A,A12, L:L,"<="&M12, M:M,">="&L12) -> 2 | O12: =IF(N12>2,"Overallocated","OK") -> OK | Q12: emp073 | R12: Parth Shah
A13: emp027 | B13: Aditi Chawla | C13: 43777 | D13: 43777 | E13: Consultant | F13: Data | G13: FTE | H13: 2019 | I13: Q4 | J13: 2019-Q4 | K13: PRJ-007 | L13: =_xlfn.XLOOKUP(K13, Projects!$A:$A, Projects!$D:$D) -> 45458 | M13: =_xlfn.XLOOKUP(K13, Projects!$A:$A, Projects!$F:$F) -> 46265 | N13: =COUNTIFS(A:A,A13, L:L,"<="&M13, M:M,">="&L13) -> 2 | O13: =IF(N13>2,"Overallocated","OK") -> OK
A14: emp063 | B14: Aditya Kapoor | C14: 42479 | D14: 42479 | E14: Lead Consultant | F14: QA | G14: FTE | H14: 2016 | I14: Q2 | J14: 2016-Q2 | K14: PRJ-019 | L14: =_xlfn.XLOOKUP(K14, Projects!$A:$A, Projects!$D:$D) -> 45474 | M14: =_xlfn.XLOOKUP(K14, Projects!$A:$A, Projects!$F:$F) -> 45992 | N14: =COUNTIFS(A:A,A14, L:L,"<="&M14, M:M,">="&L14) -> 3 | O14: =IF(N14>2,"Overallocated","OK") -> Overallocated
A15: emp072 | B15: Komal Vyas | C15: 43437 | D15: 43437 | E15: Consultant | F15: QA | G15: FTE | H15: 2018 | I15: Q4 | J15: 2018-Q4 | K15: PRJ-019 | L15: =_xlfn.XLOOKUP(K15, Projects!$A:$A, Projects!$D:$D) -> 45474 | M15: =_xlfn.XLOOKUP(K15, Projects!$A:$A, Projects!$F:$F) -> 45992 | N15: =COUNTIFS(A:A,A15, L:L,"<="&M15, M:M,">="&L15) -> 2 | O15: =IF(N15>2,"Overallocated","OK") -> OK | Q15: I joined employee-project mapping with project timelines and applied overlap logic using COUNTIFS to identify employees handling more than two concurrent projects.
A16: emp093 | B16: Rajat Khurana | C16: 42973 | D16: 42973 | E16: Sr Consultant | F16: PMO | G16: FTE | H16: 2017 | I16: Q3 | J16: 2017-Q3 | K16: PRJ-019 | L16: =_xlfn.XLOOKUP(K16, Projects!$A:$A, Projects!$D:$D) -> 45474 | M16: =_xlfn.XLOOKUP(K16, Projects!$A:$A, Projects!$F:$F) -> 45992 | N16: =COUNTIFS(A:A,A16, L:L,"<="&M16, M:M,">="&L16) -> 1 | O16: =IF(N16>2,"Overallocated","OK") -> OK
A17: emp014 | B17: Kavita Joshi | C17: 42780 | D17: 42780 | E17: Consultant | F17: Digital | G17: FTE | H17: 2017 | I17: Q1 | J17: 2017-Q1 | K17: PRJ-005 | L17: =_xlfn.XLOOKUP(K17, Projects!$A:$A, Projects!$D:$D) -> 45510 | M17: =_xlfn.XLOOKUP(K17, Projects!$A:$A, Projects!$F:$F) -> 46127 | N17: =COUNTIFS(A:A,A17, L:L,"<="&M17, M:M,">="&L17) -> 2 | O17: =IF(N17>2,"Overallocated","OK") -> OK
A18: emp054 | B18: Kavya Nair | C18: 44440 | D18: 44440 | E18: Consultant | F18: QA | G18: FTE | H18: 2021 | I18: Q3 | J18: 2021-Q3 | K18: PRJ-005 | L18: =_xlfn.XLOOKUP(K18, Projects!$A:$A, Projects!$D:$D) -> 45510 | M18: =_xlfn.XLOOKUP(K18, Projects!$A:$A, Projects!$F:$F) -> 46127 | N18: =COUNTIFS(A:A,A18, L:L,"<="&M18, M:M,">="&L18) -> 2 | O18: =IF(N18>2,"Overallocated","OK") -> OK
A19: emp083 | B19: Karthik Nair | C19: 43340 | D19: 43340 | E19: Consultant | F19: PMO | G19: FTE | H19: 2018 | I19: Q3 | J19: 2018-Q3 | K19: PRJ-005 | L19: =_xlfn.XLOOKUP(K19, Projects!$A:$A, Projects!$D:$D) -> 45510 | M19: =_xlfn.XLOOKUP(K19, Projects!$A:$A, Projects!$F:$F) -> 46127 | N19: =COUNTIFS(A:A,A19, L:L,"<="&M19, M:M,">="&L19) -> 1 | O19: =IF(N19>2,"Overallocated","OK") -> OK
A20: emp065 | B20: Varsha Kulkarni | C20: 2018.10.22 | D20: 43395 | E20: Consultant | F20: PMO | G20: FTE | H20: 2018 | I20: Q4 | J20: 2018-Q4 | K20: PRJ-082 | L20: =_xlfn.XLOOKUP(K20, Projects!$A:$A, Projects!$D:$D) -> 45519 | M20: =_xlfn.XLOOKUP(K20, Projects!$A:$A, Projects!$F:$F) -> TBD | N20: =COUNTIFS(A:A,A20, L:L,"<="&M20, M:M,">="&L20) -> 0 | O20: =IF(N20>2,"Overallocated","OK") -> OK
A21: emp103 | B21: Siddhesh Kunda | E21: Manager | F21: QA | G21: FTe | H21: Missing | I21: Missing | J21: Missing | K21: PRJ-082 | L21: 45519 | M21: TBD | N21: =COUNTIFS(A:A,A21, L:L,"<="&M21, M:M,">="&L21) -> 0 | O21: =IF(N21>2,"Overallocated","OK") -> OK | Q21: I dynamically extracted overallocated employees using FILTER to create a live view of high-risk resource allocation
A22: emp048 | B22: Ayesha Khan | C22: 43617 | D22: 43617 | E22: Analyst | F22: Data | G22: FTE | H22: 2019 | I22: Q2 | J22: 2019-Q2 | K22: PRJ-069 | L22: =_xlfn.XLOOKUP(K22, Projects!$A:$A, Projects!$D:$D) -> 45580 | M22: =_xlfn.XLOOKUP(K22, Projects!$A:$A, Projects!$F:$F) -> 46234 | N22: =COUNTIFS(A:A,A22, L:L,"<="&M22, M:M,">="&L22) -> 2 | O22: =IF(N22>2,"Overallocated","OK") -> OK
A23: emp085 | B23: Manav Kapoor | C23: 42713 | D23: 42713 | E23: Sr Consultant | F23: QA | G23: FTE | H23: 2016 | I23: Q4 | J23: 2016-Q4 | K23: PRJ-069 | L23: =_xlfn.XLOOKUP(K23, Projects!$A:$A, Projects!$D:$D) -> 45580 | M23: =_xlfn.XLOOKUP(K23, Projects!$A:$A, Projects!$F:$F) -> 46234 | N23: =COUNTIFS(A:A,A23, L:L,"<="&M23, M:M,">="&L23) -> 3 | O23: =IF(N23>2,"Overallocated","OK") -> Overallocated
A24: emp043 | B24: Harish Nair | C24: 42389 | D24: 42389 | E24: Lead Consultant | F24: AI | G24: Freelancer | H24: 2016 | I24: Q1 | J24: 2016-Q1 | K24: PRJ-072 | L24: =_xlfn.XLOOKUP(K24, Projects!$A:$A, Projects!$D:$D) -> 45630 | M24: =_xlfn.XLOOKUP(K24, Projects!$A:$A, Projects!$F:$F) -> 46102 | N24: =COUNTIFS(A:A,A24, L:L,"<="&M24, M:M,">="&L24) -> 2 | O24: =IF(N24>2,"Overallocated","OK") -> OK
A25: emp074 | B25: Meera Joshi | C25: 44385 | D25: 44385 | E25: Analyst | F25: Support | G25: FTE | H25: 2021 | I25: Q3 | J25: 2021-Q3 | K25: PRJ-072 | L25: =_xlfn.XLOOKUP(K25, Projects!$A:$A, Projects!$D:$D) -> 45630 | M25: =_xlfn.XLOOKUP(K25, Projects!$A:$A, Projects!$F:$F) -> 46102 | N25: =COUNTIFS(A:A,A25, L:L,"<="&M25, M:M,">="&L25) -> 2 | O25: =IF(N25>2,"Overallocated","OK") -> OK
A26: emp001 | B26: Rohit Sharma | C26: 44562 | D26: 44562 | E26: Sr. Consultant | F26: Data | G26: FTE | H26: 2022 | I26: Q1 | J26: 2022-Q1 | K26: PRJ-020 | L26: =_xlfn.XLOOKUP(K26, Projects!$A:$A, Projects!$D:$D) -> 45658 | M26: =_xlfn.XLOOKUP(K26, Projects!$A:$A, Projects!$F:$F) -> 46053 | N26: =COUNTIFS(A:A,A26, L:L,"<="&M26, M:M,">="&L26) -> 1 | O26: =IF(N26>2,"Overallocated","OK") -> OK
A27: emp021 | B27: Nisha Jain | C27: 44207 | D27: 44207 | E27: Analyst | F27: Data | G27: Intern | H27: 2021 | I27: Q1 | J27: 2021-Q1 | K27: PRJ-020 | L27: =_xlfn.XLOOKUP(K27, Projects!$A:$A, Projects!$D:$D) -> 45658 | M27: =_xlfn.XLOOKUP(K27, Projects!$A:$A, Projects!$F:$F) -> 46053 | N27: =COUNTIFS(A:A,A27, L:L,"<="&M27, M:M,">="&L27) -> 1 | O27: =IF(N27>2,"Overallocated","OK") -> OK
A28: emp061 | B28: Mohan Iyer | C28: 42981 | D28: 42981 | E28: Consultant | F28: Cloud | G28: FTE | H28: 2017 | I28: Q3 | J28: 2017-Q3 | K28: PRJ-022 | L28: =_xlfn.XLOOKUP(K28, Projects!$A:$A, Projects!$D:$D) -> 45658 | M28: =_xlfn.XLOOKUP(K28, Projects!$A:$A, Projects!$F:$F) -> 46043 | N28: =COUNTIFS(A:A,A28, L:L,"<="&M28, M:M,">="&L28) -> 2 | O28: =IF(N28>2,"Overallocated","OK") -> OK
A29: emp066 | B29: Aman Choudhary | C29: 43860 | D29: 43860 | E29: Sr Consultant | F29: Cloud | G29: FTE | H29: 2020 | I29: Q1 | J29: 2020-Q1 | K29: PRJ-020 | L29: =_xlfn.XLOOKUP(K29, Projects!$A:$A, Projects!$D:$D) -> 45658 | M29: =_xlfn.XLOOKUP(K29, Projects!$A:$A, Projects!$F:$F) -> 46053 | N29: =COUNTIFS(A:A,A29, L:L,"<="&M29, M:M,">="&L29) -> 2 | O29: =IF(N29>2,"Overallocated","OK") -> OK
A30: emp095 | B30: Ashwin Iyer | C30: 43269 | D30: 43269 | E30: Lead Consultant | F30: QA | G30: FTE | H30: 2018 | I30: Q2 | J30: 2018-Q2 | K30: PRJ-022 | L30: =_xlfn.XLOOKUP(K30, Projects!$A:$A, Projects!$D:$D) -> 45658 | M30: =_xlfn.XLOOKUP(K30, Projects!$A:$A, Projects!$F:$F) -> 46043 | N30: =COUNTIFS(A:A,A30, L:L,"<="&M30, M:M,">="&L30) -> 2 | O30: =IF(N30>2,"Overallocated","OK") -> OK
A31: emp015 | B31: Nitin Arora | C31: 01.06.2020 | D31: 43836 | E31: Lead Consultant | F31: Data | G31: FTE | H31: 2020 | I31: Q1 | J31: 2020-Q1 | K31: PRJ-076 | L31: =_xlfn.XLOOKUP(K31, Projects!$A:$A, Projects!$D:$D) -> 45663 | M31: =_xlfn.XLOOKUP(K31, Projects!$A:$A, Projects!$F:$F) -> 46387 | N31: =COUNTIFS(A:A,A31, L:L,"<="&M31, M:M,">="&L31) -> 3 | O31: =IF(N31>2,"Overallocated","OK") -> Overallocated
A32: emp031 | B32: Deepak Yadav | C32: 42843 | D32: 42843 | E32: Consultant | F32: AI | G32: Freelancer | H32: 2017 | I32: Q2 | J32: 2017-Q2 | K32: PRJ-076 | L32: =_xlfn.XLOOKUP(K32, Projects!$A:$A, Projects!$D:$D) -> 45663 | M32: =_xlfn.XLOOKUP(K32, Projects!$A:$A, Projects!$F:$F) -> 46387 | N32: =COUNTIFS(A:A,A32, L:L,"<="&M32, M:M,">="&L32) -> 2 | O32: =IF(N32>2,"Overallocated","OK") -> OK
A33: emp107 | B33: Neelam Jha | E33: Principal Consultant | F33: AI | G33: FTE | H33: Missing | I33: Missing | J33: Missing | K33: PRJ-076 | L33: =_xlfn.XLOOKUP(K33, Projects!$A:$A, Projects!$D:$D) -> 45663 | M33: =_xlfn.XLOOKUP(K33, Projects!$A:$A, Projects!$F:$F) -> 46387 | N33: =COUNTIFS(A:A,A33, L:L,"<="&M33, M:M,">="&L33) -> 2 | O33: =IF(N33>2,"Overallocated","OK") -> OK
A34: emp075 | B34: Raghav Mishra | C34: 2017.02.16 | D34: 42782 | E34: Consultant | F34: PMO | G34: FTE | H34: 2017 | I34: Q1 | J34: 2017-Q1 | K34: PRJ-073 | L34: =_xlfn.XLOOKUP(K34, Projects!$A:$A, Projects!$D:$D) -> 45672 | M34: =_xlfn.XLOOKUP(K34, Projects!$A:$A, Projects!$F:$F) -> 46127 | N34: =COUNTIFS(A:A,A34, L:L,"<="&M34, M:M,">="&L34) -> 2 | O34: =IF(N34>2,"Overallocated","OK") -> OK
A35: emp152 | B35: Deepak Galgotiya | C35: 44956 | D35: 44956 | E35: Lead Consultant | F35: Data | G35: Freelancer | H35: 2023 | I35: Q1 | J35: 2023-Q1 | K35: PRJ-073 | L35: =_xlfn.XLOOKUP(K35, Projects!$A:$A, Projects!$D:$D) -> 45672 | M35: =_xlfn.XLOOKUP(K35, Projects!$A:$A, Projects!$F:$F) -> 46127 | N35: =COUNTIFS(A:A,A35, L:L,"<="&M35, M:M,">="&L35) -> 2 | O35: =IF(N35>2,"Overallocated","OK") -> OK
A36: emp036 | B36: Meenal Kulkarni | C36: 43147 | D36: 43147 | E36: Lead Consultant | F36: Data | G36: FTE | H36: 2018 | I36: Q1 | J36: 2018-Q1 | K36: PRJ-071 | L36: =_xlfn.XLOOKUP(K36, Projects!$A:$A, Projects!$D:$D) -> 45686 | M36: =_xlfn.XLOOKUP(K36, Projects!$A:$A, Projects!$F:$F) -> 46249 | N36: =COUNTIFS(A:A,A36, L:L,"<="&M36, M:M,">="&L36) -> 3 | O36: =IF(N36>2,"Overallocated","OK") -> Overallocated
A37: emp071 | B37: Abhinav Jain | C37: 42627 | D37: 42627 | E37: Lead Consultant | F37: Cloud | G37: FTE | H37: 2016 | I37: Q3 | J37: 2016-Q3 | K37: PRJ-071 | L37: =_xlfn.XLOOKUP(K37, Projects!$A:$A, Projects!$D:$D) -> 45686 | M37: =_xlfn.XLOOKUP(K37, Projects!$A:$A, Projects!$F:$F) -> 46249 | N37: =COUNTIFS(A:A,A37, L:L,"<="&M37, M:M,">="&L37) -> 2 | O37: =IF(N37>2,"Overallocated","OK") -> OK
A38: emp117 | B38: Himanshi Mathur | C38: 12-31-25 | D38: 46022 | E38: Consultant | F38: Cloud | G38: Freelancer | H38: 2025 | I38: Q4 | J38: 2025-Q4 | K38: PRJ-071 | L38: 45686 | M38: 46249 | N38: =COUNTIFS(A:A,A38, L:L,"<="&M38, M:M,">="&L38) -> 2 | O38: =IF(N38>2,"Overallocated","OK") -> OK
A39: emp055 | B39: Harshit Gupta | C39: 43054 | D39: 43054 | E39: Lead Consultant | F39: Cloud | G39: FTE | H39: 2017 | I39: Q4 | J39: 2017-Q4 | K39: PRJ-009 | L39: =_xlfn.XLOOKUP(K39, Projects!$A:$A, Projects!$D:$D) -> 45689 | M39: =_xlfn.XLOOKUP(K39, Projects!$A:$A, Projects!$F:$F) -> 46142 | N39: =COUNTIFS(A:A,A39, L:L,"<="&M39, M:M,">="&L39) -> 2 | O39: =IF(N39>2,"Overallocated","OK") -> OK
A40: emp065 | B40: Varsha Kulkarni | C40: 2018.10.22 | D40: 43395 | E40: Consultant | F40: PMO | G40: FTE | H40: 2018 | I40: Q4 | J40: 2018-Q4 | K40: PRJ-009 | L40: =_xlfn.XLOOKUP(K40, Projects!$A:$A, Projects!$D:$D) -> 45689 | M40: =_xlfn.XLOOKUP(K40, Projects!$A:$A, Projects!$F:$F) -> 46142 | N40: =COUNTIFS(A:A,A40, L:L,"<="&M40, M:M,">="&L40) -> 1 | O40: =IF(N40>2,"Overallocated","OK") -> OK
A41: emp039 | B41: Gaurav Bhatia | C41: 42311 | D41: 42311 | E41: Senior Consultant | F41: Data | G41: Freelancer | H41: 2015 | I41: Q4 | J41: 2015-Q4 | K41: PRJ-088 | L41: =_xlfn.XLOOKUP(K41, Projects!$A:$A, Projects!$D:$D) -> 45741 | M41: =_xlfn.XLOOKUP(K41, Projects!$A:$A, Projects!$F:$F) -> 46186 | N41: =COUNTIFS(A:A,A41, L:L,"<="&M41, M:M,">="&L41) -> 2 | O41: =IF(N41>2,"Overallocated","OK") -> OK
A42: emp101 | B42: Taarak Goyal | C42: 45333 | D42: 45333 | E42: Sr. Consultant | F42: Design | G42: FTE | H42: 2024 | I42: Q1 | J42: 2024-Q1 | K42: PRJ-088 | L42: =_xlfn.XLOOKUP(K42, Projects!$A:$A, Projects!$D:$D) -> 45741 | M42: =_xlfn.XLOOKUP(K42, Projects!$A:$A, Projects!$F:$F) -> 46186 | N42: =COUNTIFS(A:A,A42, L:L,"<="&M42, M:M,">="&L42) -> 2 | O42: =IF(N42>2,"Overallocated","OK") -> OK
A43: emp123 | B43: Srishti Jain | C43: 2016.12.31 | D43: 42735 | E43: Sr. Consultant | F43: Data | G43: FTE | H43: 2016 | I43: Q4 | J43: 2016-Q4 | K43: PRJ-088 | L43: =_xlfn.XLOOKUP(K43, Projects!$A:$A, Projects!$D:$D) -> 45741 | M43: =_xlfn.XLOOKUP(K43, Projects!$A:$A, Projects!$F:$F) -> 46186 | N43: =COUNTIFS(A:A,A43, L:L,"<="&M43, M:M,">="&L43) -> 6 | O43: =IF(N43>2,"Overallocated","OK") -> Overallocated
A44: emp122 | B44: Ruby Gupta | C44: 44733 | D44: 44733 | E44: Consultant | F44: Support | G44: FTE | H44: 2022 | I44: Q2 | J44: 2022-Q2 | K44: PRJ-088 | L44: =_xlfn.XLOOKUP(K44, Projects!$A:$A, Projects!$D:$D) -> 45741 | M44: =_xlfn.XLOOKUP(K44, Projects!$A:$A, Projects!$F:$F) -> 46186 | N44: =COUNTIFS(A:A,A44, L:L,"<="&M44, M:M,">="&L44) -> 2 | O44: =IF(N44>2,"Overallocated","OK") -> OK
A45: emp123 | B45: Srishti Jain | C45: 42735 | D45: 42735 | E45: Sr. Consultant | F45: Data | G45: FTE | H45: 2016 | I45: Q4 | J45: 2016-Q4 | K45: PRJ-088 | L45: =_xlfn.XLOOKUP(K45, Projects!$A:$A, Projects!$D:$D) -> 45741 | M45: =_xlfn.XLOOKUP(K45, Projects!$A:$A, Projects!$F:$F) -> 46186 | N45: =COUNTIFS(A:A,A45, L:L,"<="&M45, M:M,">="&L45) -> 6 | O45: =IF(N45>2,"Overallocated","OK") -> Overallocated
A46: emp011 | B46: Aman Gupta | C46: 43713 | D46: 43713 | E46: Consultant | F46: Digital | G46: FTE | H46: 2019 | I46: Q3 | J46: 2019-Q3 | K46: PRJ-060 | L46: =_xlfn.XLOOKUP(K46, Projects!$A:$A, Projects!$D:$D) -> 45748 | M46: =_xlfn.XLOOKUP(K46, Projects!$A:$A, Projects!$F:$F) -> 46387 | N46: =COUNTIFS(A:A,A46, L:L,"<="&M46, M:M,">="&L46) -> 2 | O46: =IF(N46>2,"Overallocated","OK") -> OK
A47: emp012 | B47: Sneha Rao | C47: 44260 | D47: 44260 | E47: Analyst | F47: Data | G47: Intern | H47: 2021 | I47: Q1 | J47: 2021-Q1 | K47: PRJ-033 | L47: =_xlfn.XLOOKUP(K47, Projects!$A:$A, Projects!$D:$D) -> 45748 | M47: =_xlfn.XLOOKUP(K47, Projects!$A:$A, Projects!$F:$F) -> 46276 | N47: =COUNTIFS(A:A,A47, L:L,"<="&M47, M:M,">="&L47) -> 1 | O47: =IF(N47>2,"Overallocated","OK") -> OK
A48: emp013 | B48: Rakesh Kumar | C48: 45301 | D48: 45301 | E48: Sr. Consultant | F48: AI | G48: FTE | H48: 2024 | I48: Q1 | J48: 2024-Q1 | K48: PRJ-060 | L48: =_xlfn.XLOOKUP(K48, Projects!$A:$A, Projects!$D:$D) -> 45748 | M48: =_xlfn.XLOOKUP(K48, Projects!$A:$A, Projects!$F:$F) -> 46387 | N48: =COUNTIFS(A:A,A48, L:L,"<="&M48, M:M,">="&L48) -> 2 | O48: =IF(N48>2,"Overallocated","OK") -> OK
A49: emp022 | B49: Varun Malhotra | C49: 2018.04.03 | D49: 43193 | E49: Consultant | F49: AI | G49: FTE | H49: 2018 | I49: Q2 | J49: 2018-Q2 | K49: PRJ-036 | L49: =_xlfn.XLOOKUP(K49, Projects!$A:$A, Projects!$D:$D) -> 45748 | M49: =_xlfn.XLOOKUP(K49, Projects!$A:$A, Projects!$F:$F) -> 46324 | N49: =COUNTIFS(A:A,A49, L:L,"<="&M49, M:M,">="&L49) -> 2 | O49: =IF(N49>2,"Overallocated","OK") -> OK
A50: emp024 | B50: Akash Verma | C50: 44805 | D50: 44805 | E50: Analyst | F50: Data | G50: FTE | H50: 2022 | I50: Q3 | J50: 2022-Q3 | K50: PRJ-061 | L50: =_xlfn.XLOOKUP(K50, Projects!$A:$A, Projects!$D:$D) -> 45748 | M50: =_xlfn.XLOOKUP(K50, Projects!$A:$A, Projects!$F:$F) -> 46387 | N50: =COUNTIFS(A:A,A50, L:L,"<="&M50, M:M,">="&L50) -> 2 | O50: =IF(N50>2,"Overallocated","OK") -> OK
A51: emp028 | B51: Sarthak Jain | C51: 44361 | D51: 44361 | E51: Analyst | F51: AI | G51: Intern | H51: 2021 | I51: Q2 | J51: 2021-Q2 | K51: PRJ-036 | L51: =_xlfn.XLOOKUP(K51, Projects!$A:$A, Projects!$D:$D) -> 45748 | M51: =_xlfn.XLOOKUP(K51, Projects!$A:$A, Projects!$F:$F) -> 46324 | N51: =COUNTIFS(A:A,A51, L:L,"<="&M51, M:M,">="&L51) -> 1 | O51: =IF(N51>2,"Overallocated","OK") -> OK
A52: emp035 | B52: Abhishek Sen | C52: 44499 | D52: 44499 | E52: Consultant | F52: Digital | G52: FTE | H52: 2021 | I52: Q4 | J52: 2021-Q4 | K52: PRJ-034 | L52: =_xlfn.XLOOKUP(K52, Projects!$A:$A, Projects!$D:$D) -> 45748 | M52: =_xlfn.XLOOKUP(K52, Projects!$A:$A, Projects!$F:$F) -> 46112 | N52: =COUNTIFS(A:A,A52, L:L,"<="&M52, M:M,">="&L52) -> 2 | O52: =IF(N52>2,"Overallocated","OK") -> OK
A53: emp045 | B53: Siddharth Bose | C53: 43226 | D53: 43226 | E53: Sr Consultant | F53: Data | G53: FTE | H53: 2018 | I53: Q2 | J53: 2018-Q2 | K53: PRJ-033 | L53: =_xlfn.XLOOKUP(K53, Projects!$A:$A, Projects!$D:$D) -> 45748 | M53: =_xlfn.XLOOKUP(K53, Projects!$A:$A, Projects!$F:$F) -> 46276 | N53: =COUNTIFS(A:A,A53, L:L,"<="&M53, M:M,">="&L53) -> 2 | O53: =IF(N53>2,"Overallocated","OK") -> OK
A54: emp046 | B54: Neetu Sharma | C54: 44653 | D54: 44653 | E54: Analyst | F54: AI | G54: Intern | H54: 2022 | I54: Q2 | J54: 2022-Q2 | K54: PRJ-031 | L54: =_xlfn.XLOOKUP(K54, Projects!$A:$A, Projects!$D:$D) -> 45748 | M54: =_xlfn.XLOOKUP(K54, Projects!$A:$A, Projects!$F:$F) -> 45838 | N54: =COUNTIFS(A:A,A54, L:L,"<="&M54, M:M,">="&L54) -> 4 | O54: =IF(N54>2,"Overallocated","OK") -> Overallocated
A55: emp046 | B55: Neetu Sharma | C55: 44653 | D55: 44653 | E55: Analyst | F55: AI | G55: Intern | H55: 2022 | I55: Q2 | J55: 2022-Q2 | K55: PRJ-060 | L55: =_xlfn.XLOOKUP(K55, Projects!$A:$A, Projects!$D:$D) -> 45748 | M55: =_xlfn.XLOOKUP(K55, Projects!$A:$A, Projects!$F:$F) -> 46387 | N55: =COUNTIFS(A:A,A55, L:L,"<="&M55, M:M,">="&L55) -> 4 | O55: =IF(N55>2,"Overallocated","OK") -> Overallocated
A56: emp047 | B56: Pranav Kulkarni | C56: 43036 | D56: 43036 | E56: Consultant | F56: Digital | G56: Freelancer | H56: 2017 | I56: Q4 | J56: 2017-Q4 | K56: PRJ-006 | L56: =_xlfn.XLOOKUP(K56, Projects!$A:$A, Projects!$D:$D) -> 45748 | M56: =_xlfn.XLOOKUP(K56, Projects!$A:$A, Projects!$F:$F) -> 46387 | N56: =COUNTIFS(A:A,A56, L:L,"<="&M56, M:M,">="&L56) -> 2 | O56: =IF(N56>2,"Overallocated","OK") -> OK
A57: emp052 | B57: Nupur Shah | C57: 43933 | D57: 43933 | E57: Analyst | F57: Design | G57: Intern | H57: 2020 | I57: Q2 | J57: 2020-Q2 | K57: PRJ-006 | L57: =_xlfn.XLOOKUP(K57, Projects!$A:$A, Projects!$D:$D) -> 45748 | M57: =_xlfn.XLOOKUP(K57, Projects!$A:$A, Projects!$F:$F) -> 46387 | N57: =COUNTIFS(A:A,A57, L:L,"<="&M57, M:M,">="&L57) -> 1 | O57: =IF(N57>2,"Overallocated","OK") -> OK
A58: emp057 | B58: Pritam Das | C58: 2019.05.09 | D58: 43594 | E58: Analyst | F58: Design | G58: FTE | H58: 2019 | I58: Q2 | J58: 2019-Q2 | K58: PRJ-006 | L58: =_xlfn.XLOOKUP(K58, Projects!$A:$A, Projects!$D:$D) -> 45748 | M58: =_xlfn.XLOOKUP(K58, Projects!$A:$A, Projects!$F:$F) -> 46387 | N58: =COUNTIFS(A:A,A58, L:L,"<="&M58, M:M,">="&L58) -> 1 | O58: =IF(N58>2,"Overallocated","OK") -> OK
A59: emp067 | B59: Poonam Tiwari | C59: 43621 | D59: 43621 | E59: Consultant | F59: Support | G59: FTE | H59: 2019 | I59: Q2 | J59: 2019-Q2 | K59: PRJ-031 | L59: =_xlfn.XLOOKUP(K59, Projects!$A:$A, Projects!$D:$D) -> 45748 | M59: =_xlfn.XLOOKUP(K59, Projects!$A:$A, Projects!$F:$F) -> 45838 | N59: =COUNTIFS(A:A,A59, L:L,"<="&M59, M:M,">="&L59) -> 1 | O59: =IF(N59>2,"Overallocated","OK") -> OK
A60: emp070 | B60: Rashi Malhotra | C60: 44692 | D60: 44692 | E60: Analyst | F60: PMO | G60: Intern | H60: 2022 | I60: Q2 | J60: 2022-Q2 | K60: PRJ-037 | L60: =_xlfn.XLOOKUP(K60, Projects!$A:$A, Projects!$D:$D) -> 45748 | M60: =_xlfn.XLOOKUP(K60, Projects!$A:$A, Projects!$F:$F) -> 46387 | N60: =COUNTIFS(A:A,A60, L:L,"<="&M60, M:M,">="&L60) -> 1 | O60: =IF(N60>2,"Overallocated","OK") -> OK
A61: emp115 | B61: Shreya Rai | C61: 43788 | D61: 43788 | E61: Consultant | F61: Cloud | G61: FTE | H61: 2019 | I61: Q4 | J61: 2019-Q4 | K61: PRJ-032 | L61: =_xlfn.XLOOKUP(K61, Projects!$A:$A, Projects!$D:$D) -> 45748 | M61: =_xlfn.XLOOKUP(K61, Projects!$A:$A, Projects!$F:$F) -> 46265 | N61: =COUNTIFS(A:A,A61, L:L,"<="&M61, M:M,">="&L61) -> 2 | O61: =IF(N61>2,"Overallocated","OK") -> OK
A62: emp089 | B62: Saurabh Jain | C62: 43390 | D62: 43390 | E62: Consultant | F62: Support | G62: FTE | H62: 2018 | I62: Q4 | J62: 2018-Q4 | K62: PRJ-032 | L62: =_xlfn.XLOOKUP(K62, Projects!$A:$A, Projects!$D:$D) -> 45748 | M62: =_xlfn.XLOOKUP(K62, Projects!$A:$A, Projects!$F:$F) -> 46265 | N62: =COUNTIFS(A:A,A62, L:L,"<="&M62, M:M,">="&L62) -> 1 | O62: =IF(N62>2,"Overallocated","OK") -> OK
A63: emp094 | B63: Naina Sethi | C63: 44506 | D63: 44506 | E63: Analyst | F63: Support | G63: FTE | H63: 2021 | I63: Q4 | J63: 2021-Q4 | K63: PRJ-083 | L63: =_xlfn.XLOOKUP(K63, Projects!$A:$A, Projects!$D:$D) -> 45748 | M63: =_xlfn.XLOOKUP(K63, Projects!$A:$A, Projects!$F:$F) -> 46326 | N63: =COUNTIFS(A:A,A63, L:L,"<="&M63, M:M,">="&L63) -> 2 | O63: =IF(N63>2,"Overallocated","OK") -> OK
A64: emp097 | B64: Lakshya Jain | C64: 42643 | D64: 42643 | E64: Consultant | F64: Cloud | G64: Intern | H64: 2016 | I64: Q3 | J64: 2016-Q3 | K64: PRJ-037 | L64: =_xlfn.XLOOKUP(K64, Projects!$A:$A, Projects!$D:$D) -> 45748 | M64: =_xlfn.XLOOKUP(K64, Projects!$A:$A, Projects!$F:$F) -> 46387 | N64: =COUNTIFS(A:A,A64, L:L,"<="&M64, M:M,">="&L64) -> 1 | O64: =IF(N64>2,"Overallocated","OK") -> OK
A65: emp101 | B65: Taarak Goyal | C65: 45333 | D65: 45333 | E65: Sr. Consultant | F65: Design | G65: FTE | H65: 2024 | I65: Q1 | J65: 2024-Q1 | K65: PRJ-034 | L65: =_xlfn.XLOOKUP(K65, Projects!$A:$A, Projects!$D:$D) -> 45748 | M65: =_xlfn.XLOOKUP(K65, Projects!$A:$A, Projects!$F:$F) -> 46112 | N65: =COUNTIFS(A:A,A65, L:L,"<="&M65, M:M,">="&L65) -> 2 | O65: =IF(N65>2,"Overallocated","OK") -> OK
A66: emp103 | B66: Siddhesh Kunda | E66: Manager | F66: QA | G66: FTe | H66: Missing | I66: Missing | J66: Missing | K66: PRJ-035 | L66: =_xlfn.XLOOKUP(K66, Projects!$A:$A, Projects!$D:$D) -> 45748 | M66: =_xlfn.XLOOKUP(K66, Projects!$A:$A, Projects!$F:$F) -> 46170 | N66: =COUNTIFS(A:A,A66, L:L,"<="&M66, M:M,">="&L66) -> 1 | O66: =IF(N66>2,"Overallocated","OK") -> OK
A67: emp106 | B67: Krishna Arora | C67: 46003 | D67: 46003 | E67: Sr. Analyst | F67: QA | G67: Freelancer | H67: 2025 | I67: Q4 | J67: 2025-Q4 | K67: PRJ-035 | L67: =_xlfn.XLOOKUP(K67, Projects!$A:$A, Projects!$D:$D) -> 45748 | M67: =_xlfn.XLOOKUP(K67, Projects!$A:$A, Projects!$F:$F) -> 46170 | N67: =COUNTIFS(A:A,A67, L:L,"<="&M67, M:M,">="&L67) -> 2 | O67: =IF(N67>2,"Overallocated","OK") -> OK
A68: emp123 | B68: Srishti Jain | C68: 2016.12.31 | D68: 42735 | E68: Sr. Consultant | F68: Data | G68: FTE | H68: 2016 | I68: Q4 | J68: 2016-Q4 | K68: PRJ-061 | L68: =_xlfn.XLOOKUP(K68, Projects!$A:$A, Projects!$D:$D) -> 45748 | M68: =_xlfn.XLOOKUP(K68, Projects!$A:$A, Projects!$F:$F) -> 46387 | N68: =COUNTIFS(A:A,A68, L:L,"<="&M68, M:M,">="&L68) -> 6 | O68: =IF(N68>2,"Overallocated","OK") -> Overallocated
A69: emp046 | B69: Neetu Sharma | C69: 44653 | D69: 44653 | E69: Analyst | F69: AI | G69: Intern | H69: 2022 | I69: Q2 | J69: 2022-Q2 | K69: PRJ-031 | L69: =_xlfn.XLOOKUP(K69, Projects!$A:$A, Projects!$D:$D) -> 45748 | M69: =_xlfn.XLOOKUP(K69, Projects!$A:$A, Projects!$F:$F) -> 45838 | N69: =COUNTIFS(A:A,A69, L:L,"<="&M69, M:M,">="&L69) -> 4 | O69: =IF(N69>2,"Overallocated","OK") -> Overallocated
A70: emp046 | B70: Neetu Sharma | C70: 44653 | D70: 44653 | E70: Analyst | F70: AI | G70: Intern | H70: 2022 | I70: Q2 | J70: 2022-Q2 | K70: PRJ-060 | L70: =_xlfn.XLOOKUP(K70, Projects!$A:$A, Projects!$D:$D) -> 45748 | M70: =_xlfn.XLOOKUP(K70, Projects!$A:$A, Projects!$F:$F) -> 46387 | N70: =COUNTIFS(A:A,A70, L:L,"<="&M70, M:M,">="&L70) -> 4 | O70: =IF(N70>2,"Overallocated","OK") -> Overallocated
A71: emp114 | B71: Naresh Pal | C71: 45638 | D71: 45638 | E71: Analyst | F71: Data | G71: FTE | H71: 2024 | I71: Q4 | J71: 2024-Q4 | K71: PRJ-036 | L71: =_xlfn.XLOOKUP(K71, Projects!$A:$A, Projects!$D:$D) -> 45748 | M71: =_xlfn.XLOOKUP(K71, Projects!$A:$A, Projects!$F:$F) -> 46324 | N71: =COUNTIFS(A:A,A71, L:L,"<="&M71, M:M,">="&L71) -> 2 | O71: =IF(N71>2,"Overallocated","OK") -> OK
A72: emp115 | B72: Shreya Rai | C72: 43788 | D72: 43788 | E72: Consultant | F72: Cloud | G72: FTE | H72: 2019 | I72: Q4 | J72: 2019-Q4 | K72: PRJ-032 | L72: =_xlfn.XLOOKUP(K72, Projects!$A:$A, Projects!$D:$D) -> 45748 | M72: =_xlfn.XLOOKUP(K72, Projects!$A:$A, Projects!$F:$F) -> 46265 | N72: =COUNTIFS(A:A,A72, L:L,"<="&M72, M:M,">="&L72) -> 2 | O72: =IF(N72>2,"Overallocated","OK") -> OK
A73: emp116 | B73: Anjali Kapoor | C73: 2025.12.23 | D73: 46014 | E73: Consultant | F73: Cloud | G73: FTE | H73: 2025 | I73: Q4 | J73: 2025-Q4 | K73: PRJ-083 | L73: =_xlfn.XLOOKUP(K73, Projects!$A:$A, Projects!$D:$D) -> 45748 | M73: =_xlfn.XLOOKUP(K73, Projects!$A:$A, Projects!$F:$F) -> 46326 | N73: =COUNTIFS(A:A,A73, L:L,"<="&M73, M:M,">="&L73) -> 2 | O73: =IF(N73>2,"Overallocated","OK") -> OK
A74: emp123 | B74: Srishti Jain | C74: 42735 | D74: 42735 | E74: Sr. Consultant | F74: Data | G74: FTE | H74: 2016 | I74: Q4 | J74: 2016-Q4 | K74: PRJ-061 | L74: =_xlfn.XLOOKUP(K74, Projects!$A:$A, Projects!$D:$D) -> 45748 | M74: =_xlfn.XLOOKUP(K74, Projects!$A:$A, Projects!$F:$F) -> 46387 | N74: =COUNTIFS(A:A,A74, L:L,"<="&M74, M:M,">="&L74) -> 6 | O74: =IF(N74>2,"Overallocated","OK") -> Overallocated
A75: emp006 | B75: Rahul Mehta | C75: 43405 | D75: 43405 | E75: Principal Consultant | F75: AI | G75: FTE | H75: 2018 | I75: Q4 | J75: 2018-Q4 | K75: PRJ-011 | L75: =_xlfn.XLOOKUP(K75, Projects!$A:$A, Projects!$D:$D) -> 45764 | M75: =_xlfn.XLOOKUP(K75, Projects!$A:$A, Projects!$F:$F) -> 46128 | N75: =COUNTIFS(A:A,A75, L:L,"<="&M75, M:M,">="&L75) -> 1 | O75: =IF(N75>2,"Overallocated","OK") -> OK
A76: emp031 | B76: Deepak Yadav | C76: 42843 | D76: 42843 | E76: Consultant | F76: AI | G76: Freelancer | H76: 2017 | I76: Q2 | J76: 2017-Q2 | K76: PRJ-011 | L76: =_xlfn.XLOOKUP(K76, Projects!$A:$A, Projects!$D:$D) -> 45764 | M76: =_xlfn.XLOOKUP(K76, Projects!$A:$A, Projects!$F:$F) -> 46128 | N76: =COUNTIFS(A:A,A76, L:L,"<="&M76, M:M,">="&L76) -> 2 | O76: =IF(N76>2,"Overallocated","OK") -> OK
A77: emp064 | B77: Neelam Singh | C77: 44599 | D77: 44599 | E77: Analyst | F77: Design | G77: Intern | H77: 2022 | I77: Q1 | J77: 2022-Q1 | K77: PRJ-011 | L77: =_xlfn.XLOOKUP(K77, Projects!$A:$A, Projects!$D:$D) -> 45764 | M77: =_xlfn.XLOOKUP(K77, Projects!$A:$A, Projects!$F:$F) -> 46128 | N77: =COUNTIFS(A:A,A77, L:L,"<="&M77, M:M,">="&L77) -> 1 | O77: =IF(N77>2,"Overallocated","OK") -> OK
A78: emp056 | B78: Rohan Kulkarni | C78: 42420 | D78: 42420 | E78: Consultant | F78: Support | G78: FTE | H78: 2016 | I78: Q1 | J78: 2016-Q1 | K78: PRJ-017 | L78: =_xlfn.XLOOKUP(K78, Projects!$A:$A, Projects!$D:$D) -> 45789 | M78: =_xlfn.XLOOKUP(K78, Projects!$A:$A, Projects!$F:$F) -> 46234 | N78: =COUNTIFS(A:A,A78, L:L,"<="&M78, M:M,">="&L78) -> 2 | O78: =IF(N78>2,"Overallocated","OK") -> OK
A79: emp087 | B79: Vinayak Patil | C79: 42909 | D79: 42909 | E79: Lead Consultant | F79: Cloud | G79: FTE | H79: 2017 | I79: Q2 | J79: 2017-Q2 | K79: PRJ-017 | L79: =_xlfn.XLOOKUP(K79, Projects!$A:$A, Projects!$D:$D) -> 45789 | M79: =_xlfn.XLOOKUP(K79, Projects!$A:$A, Projects!$F:$F) -> 46234 | N79: =COUNTIFS(A:A,A79, L:L,"<="&M79, M:M,">="&L79) -> 1 | O79: =IF(N79>2,"Overallocated","OK") -> OK
A80: emp112 | B80: Atharva Arnav | C80: 42494 | D80: 42494 | E80: Lead Consultant | F80: Cloud | G80: FTE | H80: 2016 | I80: Q2 | J80: 2016-Q2 | K80: PRJ-017 | L80: =_xlfn.XLOOKUP(K80, Projects!$A:$A, Projects!$D:$D) -> 45789 | M80: =_xlfn.XLOOKUP(K80, Projects!$A:$A, Projects!$F:$F) -> 46234 | N80: =COUNTIFS(A:A,A80, L:L,"<="&M80, M:M,">="&L80) -> 1 | O80: =IF(N80>2,"Overallocated","OK") -> OK
A81: emp004 | B81: Megha Jain | C81: 03-15-2019 | D81: 43539 | E81: Consultant | F81: Digital | G81: FTE | H81: 2019 | I81: Q1 | J81: 2019-Q1 | K81: PRJ-053 | L81: =_xlfn.XLOOKUP(K81, Projects!$A:$A, Projects!$D:$D) -> 45793 | M81: =_xlfn.XLOOKUP(K81, Projects!$A:$A, Projects!$F:$F) -> 46242 | N81: =COUNTIFS(A:A,A81, L:L,"<="&M81, M:M,">="&L81) -> 2 | O81: =IF(N81>2,"Overallocated","OK") -> OK
A82: emp017 | B82: Swati Kulkarni | C82: 44423 | D82: 44423 | E82: Consultant | F82: Digital | G82: FTE | H82: 2021 | I82: Q3 | J82: 2021-Q3 | K82: PRJ-053 | L82: =_xlfn.XLOOKUP(K82, Projects!$A:$A, Projects!$D:$D) -> 45793 | M82: =_xlfn.XLOOKUP(K82, Projects!$A:$A, Projects!$F:$F) -> 46242 | N82: =COUNTIFS(A:A,A82, L:L,"<="&M82, M:M,">="&L82) -> 2 | O82: =IF(N82>2,"Overallocated","OK") -> OK
A83: emp069 | B83: Nikhil Arora | C83: 42943 | D83: 42943 | E83: Consultant | F83: Design | G83: FTE | H83: 2017 | I83: Q3 | J83: 2017-Q3 | K83: PRJ-053 | L83: =_xlfn.XLOOKUP(K83, Projects!$A:$A, Projects!$D:$D) -> 45793 | M83: =_xlfn.XLOOKUP(K83, Projects!$A:$A, Projects!$F:$F) -> 46242 | N83: =COUNTIFS(A:A,A83, L:L,"<="&M83, M:M,">="&L83) -> 2 | O83: =IF(N83>2,"Overallocated","OK") -> OK
A84: emp080 | B84: Pallavi Mehta | C84: 43788 | D84: 43788 | E84: Consultant | F84: QA | G84: FTE | H84: 2019 | I84: Q4 | J84: 2019-Q4 | K84: PRJ-054 | L84: =_xlfn.XLOOKUP(K84, Projects!$A:$A, Projects!$D:$D) -> 45793 | M84: =_xlfn.XLOOKUP(K84, Projects!$A:$A, Projects!$F:$F) -> 46172 | N84: =COUNTIFS(A:A,A84, L:L,"<="&M84, M:M,">="&L84) -> 2 | O84: =IF(N84>2,"Overallocated","OK") -> OK
A85: emp104 | B85: Karan Patel | C85: 2025.12.23 | D85: 46014 | E85: Lead Consultant | F85: QA | G85: FTE | H85: 2025 | I85: Q4 | J85: 2025-Q4 | K85: PRJ-054 | L85: =_xlfn.XLOOKUP(K85, Projects!$A:$A, Projects!$D:$D) -> 45793 | M85: =_xlfn.XLOOKUP(K85, Projects!$A:$A, Projects!$F:$F) -> 46172 | N85: =COUNTIFS(A:A,A85, L:L,"<="&M85, M:M,">="&L85) -> 2 | O85: =IF(N85>2,"Overallocated","OK") -> OK
A86: emp059 | B86: Kunal Verma | C86: 43125 | D86: 43125 | E86: Sr Consultant | F86: PMO | G86: FTE | H86: 2018 | I86: Q1 | J86: 2018-Q1 | K86: PRJ-087 | L86: =_xlfn.XLOOKUP(K86, Projects!$A:$A, Projects!$D:$D) -> 45803 | M86: =_xlfn.XLOOKUP(K86, Projects!$A:$A, Projects!$F:$F) -> 46022 | N86: =COUNTIFS(A:A,A86, L:L,"<="&M86, M:M,">="&L86) -> 3 | O86: =IF(N86>2,"Overallocated","OK") -> Overallocated
A87: emp118 | B87: Ayush Negi | C87: 42494 | D87: 42494 | E87: Analyst | F87: Cloud | G87: Freelancer | H87: 2016 | I87: Q2 | J87: 2016-Q2 | K87: PRJ-087 | L87: =_xlfn.XLOOKUP(K87, Projects!$A:$A, Projects!$D:$D) -> 45803 | M87: =_xlfn.XLOOKUP(K87, Projects!$A:$A, Projects!$F:$F) -> 46022 | N87: =COUNTIFS(A:A,A87, L:L,"<="&M87, M:M,">="&L87) -> 2 | O87: =IF(N87>2,"Overallocated","OK") -> OK
A88: emp054 | B88: Kavya Nair | C88: 44440 | D88: 44440 | E88: Consultant | F88: QA | G88: FTE | H88: 2021 | I88: Q3 | J88: 2021-Q3 | K88: PRJ-059 | L88: =_xlfn.XLOOKUP(K88, Projects!$A:$A, Projects!$D:$D) -> 45810 | M88: =_xlfn.XLOOKUP(K88, Projects!$A:$A, Projects!$F:$F) -> 46224 | N88: =COUNTIFS(A:A,A88, L:L,"<="&M88, M:M,">="&L88) -> 2 | O88: =IF(N88>2,"Overallocated","OK") -> OK
A89: emp063 | B89: Aditya Kapoor | C89: 42479 | D89: 42479 | E89: Lead Consultant | F89: QA | G89: FTE | H89: 2016 | I89: Q2 | J89: 2016-Q2 | K89: PRJ-059 | L89: =_xlfn.XLOOKUP(K89, Projects!$A:$A, Projects!$D:$D) -> 45810 | M89: =_xlfn.XLOOKUP(K89, Projects!$A:$A, Projects!$F:$F) -> 46224 | N89: =COUNTIFS(A:A,A89, L:L,"<="&M89, M:M,">="&L89) -> 3 | O89: =IF(N89>2,"Overallocated","OK") -> Overallocated
A90: emp114 | B90: Naresh Pal | C90: 45638 | D90: 45638 | E90: Analyst | F90: Data | G90: FTE | H90: 2024 | I90: Q4 | J90: 2024-Q4 | K90: PRJ-059 | L90: =_xlfn.XLOOKUP(K90, Projects!$A:$A, Projects!$D:$D) -> 45810 | M90: =_xlfn.XLOOKUP(K90, Projects!$A:$A, Projects!$F:$F) -> 46224 | N90: =COUNTIFS(A:A,A90, L:L,"<="&M90, M:M,">="&L90) -> 2 | O90: =IF(N90>2,"Overallocated","OK") -> OK
A91: emp014 | B91: Kavita Joshi | C91: 42780 | D91: 42780 | E91: Consultant | F91: Digital | G91: FTE | H91: 2017 | I91: Q1 | J91: 2017-Q1 | K91: PRJ-080 | L91: =_xlfn.XLOOKUP(K91, Projects!$A:$A, Projects!$D:$D) -> 45820 | M91: =_xlfn.XLOOKUP(K91, Projects!$A:$A, Projects!$F:$F) -> 46249 | N91: =COUNTIFS(A:A,A91, L:L,"<="&M91, M:M,">="&L91) -> 2 | O91: =IF(N91>2,"Overallocated","OK") -> OK
A92: emp045 | B92: Siddharth Bose | C92: 43226 | D92: 43226 | E92: Sr Consultant | F92: Data | G92: FTE | H92: 2018 | I92: Q2 | J92: 2018-Q2 | K92: PRJ-080 | L92: =_xlfn.XLOOKUP(K92, Projects!$A:$A, Projects!$D:$D) -> 45820 | M92: =_xlfn.XLOOKUP(K92, Projects!$A:$A, Projects!$F:$F) -> 46249 | N92: =COUNTIFS(A:A,A92, L:L,"<="&M92, M:M,">="&L92) -> 2 | O92: =IF(N92>2,"Overallocated","OK") -> OK
A93: emp035 | B93: Abhishek Sen | C93: 44499 | D93: 44499 | E93: Consultant | F93: Digital | G93: FTE | H93: 2021 | I93: Q4 | J93: 2021-Q4 | K93: PRJ-089 | L93: =_xlfn.XLOOKUP(K93, Projects!$A:$A, Projects!$D:$D) -> 45823 | M93: =_xlfn.XLOOKUP(K93, Projects!$A:$A, Projects!$F:$F) -> 46053 | N93: =COUNTIFS(A:A,A93, L:L,"<="&M93, M:M,">="&L93) -> 2 | O93: =IF(N93>2,"Overallocated","OK") -> OK
A94: emp130 | B94: Priya Ratwani | C94: 43159 | D94: 43159 | E94: Lead Consultant | F94: Data | G94: FTE | H94: 2018 | I94: Q1 | J94: 2018-Q1 | K94: PRJ-089 | L94: =_xlfn.XLOOKUP(K94, Projects!$A:$A, Projects!$D:$D) -> 45823 | M94: =_xlfn.XLOOKUP(K94, Projects!$A:$A, Projects!$F:$F) -> 46053 | N94: =COUNTIFS(A:A,A94, L:L,"<="&M94, M:M,">="&L94) -> 3 | O94: =IF(N94>2,"Overallocated","OK") -> Overallocated
A95: emp027 | B95: Aditi Chawla | C95: 43777 | D95: 43777 | E95: Consultant | F95: Data | G95: FTE | H95: 2019 | I95: Q4 | J95: 2019-Q4 | K95: PRJ-055 | L95: =_xlfn.XLOOKUP(K95, Projects!$A:$A, Projects!$D:$D) -> 45824 | M95: =_xlfn.XLOOKUP(K95, Projects!$A:$A, Projects!$F:$F) -> 46291 | N95: =COUNTIFS(A:A,A95, L:L,"<="&M95, M:M,">="&L95) -> 2 | O95: =IF(N95>2,"Overallocated","OK") -> OK
A96: emp130 | B96: Priya Ratwani | C96: 43159 | D96: 43159 | E96: Lead Consultant | F96: Data | G96: FTE | H96: 2018 | I96: Q1 | J96: 2018-Q1 | K96: PRJ-055 | L96: =_xlfn.XLOOKUP(K96, Projects!$A:$A, Projects!$D:$D) -> 45824 | M96: =_xlfn.XLOOKUP(K96, Projects!$A:$A, Projects!$F:$F) -> 46291 | N96: =COUNTIFS(A:A,A96, L:L,"<="&M96, M:M,">="&L96) -> 3 | O96: =IF(N96>2,"Overallocated","OK") -> Overallocated
A97: emp113 | B97: Shrey Vishwakarma | C97: 42816 | D97: 42816 | E97: Sr Consultant | F97: Cloud | G97: FTE | H97: 2017 | I97: Q1 | J97: 2017-Q1 | K97: PRJ-055 | L97: =_xlfn.XLOOKUP(K97, Projects!$A:$A, Projects!$D:$D) -> 45824 | M97: =_xlfn.XLOOKUP(K97, Projects!$A:$A, Projects!$F:$F) -> 46291 | N97: =COUNTIFS(A:A,A97, L:L,"<="&M97, M:M,">="&L97) -> 2 | O97: =IF(N97>2,"Overallocated","OK") -> OK
... A106: emp037 | B106: Rohan Iyer | C106: 43717 | D106: 43717 | E106: Consultant | F106: AI | G106: FTE | H106: 2019 | I106: Q3 | J106: 2019-Q3 | K106: PRJ-056 | L106: =_xlfn.XLOOKUP(K106, Projects!$A:$A, Projects!$D:$D) -> 45847 | M106: =_xlfn.XLOOKUP(K106, Projects!$A:$A, Projects!$F:$F) -> 46290 | N106: =COUNTIFS(A:A,A106, L:L,"<="&M106, M:M,">="&L106) -> 2 | O106: =IF(N106>2,"Overallocated","OK") -> OK
A107: emp044 | B107: Komal Srivastava | C107: 11th dec 2024 | D107: 45637 | E107: Consultant | F107: Digital | G107: FTE | H107: 2024 | I107: Q4 | J107: 2024-Q4 | K107: PRJ-010 | L107: =_xlfn.XLOOKUP(K107, Projects!$A:$A, Projects!$D:$D) -> 45847 | M107: =_xlfn.XLOOKUP(K107, Projects!$A:$A, Projects!$F:$F) -> 46249 | N107: =COUNTIFS(A:A,A107, L:L,"<="&M107, M:M,">="&L107) -> 1 | O107: =IF(N107>2,"Overallocated","OK") -> OK
A108: emp051 | B108: Aarav Mehta | C108: 43536 | D108: 43536 | E108: Consultant | F108: QA | G108: FTE | H108: 2019 | I108: Q1 | J108: 2019-Q1 | K108: PRJ-010 | L108: =_xlfn.XLOOKUP(K108, Projects!$A:$A, Projects!$D:$D) -> 45847 | M108: =_xlfn.XLOOKUP(K108, Projects!$A:$A, Projects!$F:$F) -> 46249 | N108: =COUNTIFS(A:A,A108, L:L,"<="&M108, M:M,">="&L108) -> 2 | O108: =IF(N108>2,"Overallocated","OK") -> OK
...

Sheet Emp–Proj Mgmt Count 
A3: Employee Name | B3: Project Count
A4: Aarav Mehta | B4: 2
A5: Abhinav Jain | B5: 2
A6: Abhishek Sen | B6: 2 | F6: I normalized the project allocation data using unpivoting to create a one-to-many mapping between employees and projects
A7: Aditi Chawla | B7: 2
A8: Aditya Kapoor | B8: 3
A9: Aishwarya Kulkarni | B9: 1
A10: Akash Verma | B10: 2
A11: Aman Choudhary | B11: 3
A12: Aman Gupta | B12: 2
A13: Anchal Rastogi | B13: 1
A14: Aniket Rao | B14: 2
A15: Anjali Kapoor | B15: 2
A16: Anjali Verma | B16: 2
A17: Aradhya Jha | B17: 2
A18: Arjun Mehta | B18: 1
... A130: Grand Total | B130: 229

Sheet Utilisation
A3: Corrected Employee ID | B3: Designation | C3: Project Count | D3: Client Hours | E3: Adhoc Hours | F3: Total Workload | G3: Utilisation
A4: emp001 | B4: Sr. Consultant | C4: 2 | D4: =_xlfn.XLOOKUP(B4, $J$4:$J$14, $K$4:$K$14) -> 2 | E4: =_xlfn.XLOOKUP(B4, $J$4:$J$14, $L$4:$L$14) -> 2 | F4: =(C4 * D4) + E4 -> 6 | G4: =IF(F4<40,"Under-utilized", IF(F4<=50,"Optimal","Burnout")) -> Under-utilized | J4: Designation | K4: Client Hrs | L4: Adhoc Hrs
A5: emp002 | B5: Manager | C5: 2 | D5: =_xlfn.XLOOKUP(B5, $J$4:$J$14, $K$4:$K$14) -> 4 | E5: =_xlfn.XLOOKUP(B5, $J$4:$J$14, $L$4:$L$14) -> 2 | F5: =(C5 * D5) + E5 -> 10 | G5: =IF(F5<40,"Under-utilized", IF(F5<=50,"Optimal","Burnout")) -> Under-utilized | J5: Analyst | K5: 5 | L5: 0
A6: emp003 | B6: Lead Consultant | C6: 2 | D6: =_xlfn.XLOOKUP(B6, $J$4:$J$14, $K$4:$K$14) -> 3 | E6: =_xlfn.XLOOKUP(B6, $J$4:$J$14, $L$4:$L$14) -> 2 | F6: =(C6 * D6) + E6 -> 8 | G6: =IF(F6<40,"Under-utilized", IF(F6<=50,"Optimal","Burnout")) -> Under-utilized | J6: Consultant | K6: 5 | L6: 0
A7: emp004 | B7: Consultant | C7: 2 | D7: =_xlfn.XLOOKUP(B7, $J$4:$J$14, $K$4:$K$14) -> 5 | E7: =_xlfn.XLOOKUP(B7, $J$4:$J$14, $L$4:$L$14) -> 0 | F7: =(C7 * D7) + E7 -> 10 | G7: =IF(F7<40,"Under-utilized", IF(F7<=50,"Optimal","Burnout")) -> Under-utilized | J7: Lead Consultant | K7: 3 | L7: 2
A8: emp005 | B8: Senior Consultant | C8: 3 | D8: =_xlfn.XLOOKUP(B8, $J$4:$J$14, $K$4:$K$14) -> 2 | E8: =_xlfn.XLOOKUP(B8, $J$4:$J$14, $L$4:$L$14) -> 2 | F8: =(C8 * D8) + E8 -> 8 | G8: =IF(F8<40,"Under-utilized", IF(F8<=50,"Optimal","Burnout")) -> Under-utilized | J8: Manager | K8: 4 | L8: 2
A9: emp006 | B9: Principal Consultant | C9: 2 | D9: =_xlfn.XLOOKUP(B9, $J$4:$J$14, $K$4:$K$14) -> 2 | E9: =_xlfn.XLOOKUP(B9, $J$4:$J$14, $L$4:$L$14) -> 2 | F9: =(C9 * D9) + E9 -> 6 | G9: =IF(F9<40,"Under-utilized", IF(F9<=50,"Optimal","Burnout")) -> Under-utilized | J9: Principal Consultant | K9: 2 | L9: 2
A10: emp007 | B10: Consultant | C10: 1 | D10: =_xlfn.XLOOKUP(B10, $J$4:$J$14, $K$4:$K$14) -> 5 | E10: =_xlfn.XLOOKUP(B10, $J$4:$J$14, $L$4:$L$14) -> 0 | F10: =(C10 * D10) + E10 -> 5 | G10: =IF(F10<40,"Under-utilized", IF(F10<=50,"Optimal","Burnout")) -> Under-utilized | J10: Sr. Analyst | K10: 2 | L10: 2
A11: emp008 | B11: Consultant | C11: 2 | D11: =_xlfn.XLOOKUP(B11, $J$4:$J$14, $K$4:$K$14) -> 5 | E11: =_xlfn.XLOOKUP(B11, $J$4:$J$14, $L$4:$L$14) -> 0 | F11: =(C11 * D11) + E11 -> 10 | G11: =IF(F11<40,"Under-utilized", IF(F11<=50,"Optimal","Burnout")) -> Under-utilized | J11: Sr. Consultant | K11: 2 | L11: 2
A12: emp009 | B12: Analyst | C12: 1 | D12: =_xlfn.XLOOKUP(B12, $J$4:$J$14, $K$4:$K$14) -> 5 | E12: =_xlfn.XLOOKUP(B12, $J$4:$J$14, $L$4:$L$14) -> 0 | F12: =(C12 * D12) + E12 -> 5 | G12: =IF(F12<40,"Under-utilized", IF(F12<=50,"Optimal","Burnout")) -> Under-utilized | J12: Senior Consultant | K12: 2 | L12: 2
A13: emp010 | B13: Consultant | C13: 1 | D13: =_xlfn.XLOOKUP(B13, $J$4:$J$14, $K$4:$K$14) -> 5 | E13: =_xlfn.XLOOKUP(B13, $J$4:$J$14, $L$4:$L$14) -> 0 | F13: =(C13 * D13) + E13 -> 5 | G13: =IF(F13<40,"Under-utilized", IF(F13<=50,"Optimal","Burnout")) -> Under-utilized | J13: Senior Analyst | K13: 2 | L13: 2
A14: emp011 | B14: Consultant | C14: 2 | D14: =_xlfn.XLOOKUP(B14, $J$4:$J$14, $K$4:$K$14) -> 5 | E14: =_xlfn.XLOOKUP(B14, $J$4:$J$14, $L$4:$L$14) -> 0 | F14: =(C14 * D14) + E14 -> 10 | G14: =IF(F14<40,"Under-utilized", IF(F14<=50,"Optimal","Burnout")) -> Under-utilized | J14: Sr Consultant | K14: 2 | L14: 2
A15: emp012 | B15: Analyst | C15: 1 | D15: =_xlfn.XLOOKUP(B15, $J$4:$J$14, $K$4:$K$14) -> 5 | E15: =_xlfn.XLOOKUP(B15, $J$4:$J$14, $L$4:$L$14) -> 0 | F15: =(C15 * D15) + E15 -> 5 | G15: =IF(F15<40,"Under-utilized", IF(F15<=50,"Optimal","Burnout")) -> Under-utilized
A16: emp013 | B16: Sr. Consultant | C16: 2 | D16: =_xlfn.XLOOKUP(B16, $J$4:$J$14, $K$4:$K$14) -> 2 | E16: =_xlfn.XLOOKUP(B16, $J$4:$J$14, $L$4:$L$14) -> 2 | F16: =(C16 * D16) + E16 -> 6 | G16: =IF(F16<40,"Under-utilized", IF(F16<=50,"Optimal","Burnout")) -> Under-utilized
A17: emp014 | B17: Consultant | C17: 2 | D17: =_xlfn.XLOOKUP(B17, $J$4:$J$14, $K$4:$K$14) -> 5 | E17: =_xlfn.XLOOKUP(B17, $J$4:$J$14, $L$4:$L$14) -> 0 | F17: =(C17 * D17) + E17 -> 10 | G17: =IF(F17<40,"Under-utilized", IF(F17<=50,"Optimal","Burnout")) -> Under-utilized
A18: emp015 | B18: Lead Consultant | C18: 3 | D18: =_xlfn.XLOOKUP(B18, $J$4:$J$14, $K$4:$K$14) -> 3 | E18: =_xlfn.XLOOKUP(B18, $J$4:$J$14, $L$4:$L$14) -> 2 | F18: =(C18 * D18) + E18 -> 11 | G18: =IF(F18<40,"Under-utilized", IF(F18<=50,"Optimal","Burnout")) -> Under-utilized | J18: I calculated workload using project counts and role-based effort assumptions, then classified employees into utilization categories to identify potential burnout.
A19: emp016 | B19: Analyst | C19: 2 | D19: =_xlfn.XLOOKUP(B19, $J$4:$J$14, $K$4:$K$14) -> 5 | E19: =_xlfn.XLOOKUP(B19, $J$4:$J$14, $L$4:$L$14) -> 0 | F19: =(C19 * D19) + E19 -> 10 | G19: =IF(F19<40,"Under-utilized", IF(F19<=50,"Optimal","Burnout")) -> Under-utilized
A20: emp017 | B20: Consultant | C20: 2 | D20: =_xlfn.XLOOKUP(B20, $J$4:$J$14, $K$4:$K$14) -> 5 | E20: =_xlfn.XLOOKUP(B20, $J$4:$J$14, $L$4:$L$14) -> 0 | F20: =(C20 * D20) + E20 -> 10 | G20: =IF(F20<40,"Under-utilized", IF(F20<=50,"Optimal","Burnout")) -> Under-utilized
A21: emp018 | B21: Analyst | C21: 1 | D21: =_xlfn.XLOOKUP(B21, $J$4:$J$14, $K$4:$K$14) -> 5 | E21: =_xlfn.XLOOKUP(B21, $J$4:$J$14, $L$4:$L$14) -> 0 | F21: =(C21 * D21) + E21 -> 5 | G21: =IF(F21<40,"Under-utilized", IF(F21<=50,"Optimal","Burnout")) -> Under-utilized
A22: emp019 | B22: Consultant | C22: 2 | D22: =_xlfn.XLOOKUP(B22, $J$4:$J$14, $K$4:$K$14) -> 5 | E22: =_xlfn.XLOOKUP(B22, $J$4:$J$14, $L$4:$L$14) -> 0 | F22: =(C22 * D22) + E22 -> 10 | G22: =IF(F22<40,"Under-utilized", IF(F22<=50,"Optimal","Burnout")) -> Under-utilized
A23: emp020 | B23: Senior Consultant | C23: 3 | D23: =_xlfn.XLOOKUP(B23, $J$4:$J$14, $K$4:$K$14) -> 2 | E23: =_xlfn.XLOOKUP(B23, $J$4:$J$14, $L$4:$L$14) -> 2 | F23: =(C23 * D23) + E23 -> 8 | G23: =IF(F23<40,"Under-utilized", IF(F23<=50,"Optimal","Burnout")) -> Under-utilized
A24: emp021 | B24: Analyst | C24: 1 | D24: =_xlfn.XLOOKUP(B24, $J$4:$J$14, $K$4:$K$14) -> 5 | E24: =_xlfn.XLOOKUP(B24, $J$4:$J$14, $L$4:$L$14) -> 0 | F24: =(C24 * D24) + E24 -> 5 | G24: =IF(F24<40,"Under-utilized", IF(F24<=50,"Optimal","Burnout")) -> Under-utilized
A25: emp022 | B25: Consultant | C25: 2 | D25: =_xlfn.XLOOKUP(B25, $J$4:$J$14, $K$4:$K$14) -> 5 | E25: =_xlfn.XLOOKUP(B25, $J$4:$J$14, $L$4:$L$14) -> 0 | F25: =(C25 * D25) + E25 -> 10 | G25: =IF(F25<40,"Under-utilized", IF(F25<=50,"Optimal","Burnout")) -> Under-utilized
A26: emp023 | B26: Lead Consultant | C26: 2 | D26: =_xlfn.XLOOKUP(B26, $J$4:$J$14, $K$4:$K$14) -> 3 | E26: =_xlfn.XLOOKUP(B26, $J$4:$J$14, $L$4:$L$14) -> 2 | F26: =(C26 * D26) + E26 -> 8 | G26: =IF(F26<40,"Under-utilized", IF(F26<=50,"Optimal","Burnout")) -> Under-utilized
A27: emp024 | B27: Analyst | C27: 2 | D27: =_xlfn.XLOOKUP(B27, $J$4:$J$14, $K$4:$K$14) -> 5 | E27: =_xlfn.XLOOKUP(B27, $J$4:$J$14, $L$4:$L$14) -> 0 | F27: =(C27 * D27) + E27 -> 10 | G27: =IF(F27<40,"Under-utilized", IF(F27<=50,"Optimal","Burnout")) -> Under-utilized
A28: emp025 | B28: Consultant | C28: 2 | D28: =_xlfn.XLOOKUP(B28, $J$4:$J$14, $K$4:$K$14) -> 5 | E28: =_xlfn.XLOOKUP(B28, $J$4:$J$14, $L$4:$L$14) -> 0 | F28: =(C28 * D28) + E28 -> 10 | G28: =IF(F28<40,"Under-utilized", IF(F28<=50,"Optimal","Burnout")) -> Under-utilized
A29: emp026 | B29: Senior Consultant | C29: 1 | D29: =_xlfn.XLOOKUP(B29, $J$4:$J$14, $K$4:$K$14) -> 2 | E29: =_xlfn.XLOOKUP(B29, $J$4:$J$14, $L$4:$L$14) -> 2 | F29: =(C29 * D29) + E29 -> 4 | G29: =IF(F29<40,"Under-utilized", IF(F29<=50,"Optimal","Burnout")) -> Under-utilized
A30: emp027 | B30: Consultant | C30: 2 | D30: =_xlfn.XLOOKUP(B30, $J$4:$J$14, $K$4:$K$14) -> 5 | E30: =_xlfn.XLOOKUP(B30, $J$4:$J$14, $L$4:$L$14) -> 0 | F30: =(C30 * D30) + E30 -> 10 | G30: =IF(F30<40,"Under-utilized", IF(F30<=50,"Optimal","Burnout")) -> Under-utilized
... A129: emp152 | B129: Lead Consultant | C129: 2 | D129: =_xlfn.XLOOKUP(B129, $J$4:$J$14, $K$4:$K$14) -> 3 | E129: =_xlfn.XLOOKUP(B129, $J$4:$J$14, $L$4:$L$14) -> 2 | F129: =(C129 * D129) + E129 -> 8 | G129: =IF(F129<40,"Under-utilized", IF(F129<=50,"Optimal","Burnout")) -> Under-utilized

Sheet Strategic Tracker
A1: Initiative ID | B1: Initiative Name | C1: Business Unit / Team | D1: Owner | E1: Start Date | F1: End Date | G1: Status | H1: Priority | I1: Progress % | J1: Budget | K1: Risk Level | L1: Overdue Flag | M1: Remarks
A2: INT-001 | B2: AI Forecasting Model | C2: Data | D2: Rahul Sharma | E2: 46023 | F2: 46111 | G2: In Progress | H2: High | I2: 0.6 | J2: 50000 | K2: Medium | L2: =IF(AND(F2<TODAY(), G2<>"Completed"), "Overdue", "") -> Overdue | M2: On track | O2: I created a structured initiative tracker with realistic data, incorporating timelines, risk, priority, and automated overdue tracking for better project governance.
A3: INT-002 | B3: Hiring Expansion Plan | C3: HR | D3: Neha Verma | E3: 46068 | F3: 46173 | G3: Not Started | H3: Medium | I3: 0.1 | J3: 20000 | K3: Low | L3: =IF(AND(F3<TODAY(), G3<>"Completed"), "Overdue", "") | M3: Planning stage
A4: INT-003 | B4: Cloud Migration | C4: IT | D4: Arjun Mehta | E4: 45992 | F4: 46068 | G4: Completed | H4: High | I4: 1 | J4: 75000 | K4: High | L4: =IF(AND(F4<TODAY(), G4<>"Completed"), "Overdue", "") | M4: Successfully delivered
A5: INT-004 | B5: Client Dashboard Revamp | C5: Design | D5: Priya Nair | E5: 46032 | F5: 46132 | G5: In Progress | H5: High | I5: 0.45 | J5: 30000 | K5: Medium | L5: =IF(AND(F5<TODAY(), G5<>"Completed"), "Overdue", "") | M5: UI redesign ongoing
A6: INT-005 | B6: Automation Testing Setup | C6: QA | D6: Karan Patel | E6: 45962 | F6: 46037 | G6: In Progress | H6: Medium | I6: 0.7 | J6: 25000 | K6: High | L6: =IF(AND(F6<TODAY(), G6<>"Completed"), "Overdue", "") -> Overdue | M6: Delayed due to resource gap
A7: INT-006 | B7: Data Governance Framework | C7: Data | D7: Sneha Rao | E7: 46082 | F7: 46203 | G7: Not Started | H7: High | I7: 0 | J7: 40000 | K7: Medium | L7: =IF(AND(F7<TODAY(), G7<>"Completed"), "Overdue", "") | M7: Yet to begin
A8: INT-007 | B8: AI Chatbot Implementation | C8: AI | D8: Vikram Singh | E8: 46037 | F8: 46173 | G8: In Progress | H8: High | I8: 0.5 | J8: 60000 | K8: High | L8: =IF(AND(F8<TODAY(), G8<>"Completed"), "Overdue", "") | M8: Model training ongoing
A9: INT-008 | B9: Security Compliance Upgrade | C9: IT | D9: Aman Gupta | E9: 45931 | F9: 46022 | G9: Completed | H9: High | I9: 1 | J9: 45000 | K9: Low | L9: =IF(AND(F9<TODAY(), G9<>"Completed"), "Overdue", "") | M9: Compliance achieved
